Workbook

Sheet Players
A1: Player Name | B1: Position | C1: Team | D1: Cost | E1: Start | F1: Score | G1: Score 2+ | H1: Score 3+ | I1: Assist | J1: Yellow Card | K1: Clean Sheet | L1: Concede 2+ Goals | M1: Concede 4+ Goals | N1: 3 Saves | O1: 6 Saves | P1: Defensive Contribution - DEF | Q1: Defensive Contribution - MID | R1: F1 XP Pre | S1: F1 Bonus Probability | T1: F1 XP | U1: F1 Difficulty | V1: F1 Opponent | W1: F1 Diff | X1: F1 Venue | Y1: F1 Factor | Z1: F2 Difficulty | AA1: F2 Opponent | AB1: F2 Diff | AC1: F2 Venue | AD1: F2 XP Pre | AE1: F2 Bonus Probability | AF1: F2 XP | AG1: F3 Difficulty | AH1: F3 Opponent | AI1: F3 Diff | AJ1: F3 Venue | AK1: F3 XP Pre | AL1: F3 Bonus Probability | AM1: F3 XP | AN1: F4 Difficulty | AO1: F4 Opponent | AP1: F4 Diff | AQ1: F4 Venue | AR1: F4 XP Pre | AS1: F4 Bonus Probability | AT1: F4 XP | AU1: F5 Difficulty | AV1: F5 Opponent | AW1: F5 Diff | AX1: F5 Venue | AY1: F5 XP Pre | AZ1: F5 Bonus Probability | BA1: F5 XP | BB1: Total XP
A2: ='Players Full'!CU2 -> David Raya | B2: =VLOOKUP(_xlfn.CONCAT('Players Full'!AK2,'Players Full'!BV2),'Players Summarised'!$A$1:$T$1000,20,0) -> GK | C2: =VLOOKUP('Players Full'!CF2,Teams!$A$1:$G$21,6,0) -> Arsenal | D2: ='Players Full'!BD2/10 -> 5.5 | E2: =IFERROR(VLOOKUP($A2,'Starting Lineups'!$A$2:$C$510,3,FALSE),0) -> 1 | F2: =VLOOKUP(A2,'Score & Assist'!$A$1:$G$2000,6,0) -> #N/A | G2: =IF(F2<0.3, 0.01,IF(F2=0.3,0.03,IF(F2<0.5,0.05,IF(F2<0.55,0.06,IF(F2<0.57,0.1,IF(F2<0.58,0.11,IF(F2<0.59,0.12,IF(F2<0.6,0.15,0.28)))))))) -> #N/A | H2: =IF(F2<0.3,0,IF(F2<0.55,0.01,IF(F2<0.59,0.02,IF(F2<0.6,0.03,0.11)))) -> #N/A | I2: =VLOOKUP(A2,'Score & Assist'!$A$1:$G$2000,7,0) -> #N/A | J2: =VLOOKUP(A2,'Yellow Card'!$C$1:$E$987,3,0) -> 0.13605442 | K2: =VLOOKUP(C2,'Team Clean Sheet'!$C$2:$F$21,4,0) -> 0.5 | L2: =VLOOKUP(C2,'Team Total Goals'!$D$2:$N$21,10,0) -> 0.17168675 | M2: =VLOOKUP(C2,'Team Total Goals'!$D$2:$N$21,11,0) -> 0.01926849 | N2: =VLOOKUP(A2,'Goalkeeper Saves'!$D$2:$N$15,10,0) -> 0.27210884 | O2: =VLOOKUP(A2,'Goalkeeper Saves'!$D$2:$N$15,11,0) -> 0 | P2: =IF(B2="DEF",IFERROR(VLOOKUP(A2,'Defensive Contribution - DEF'!A2:H498,8,FALSE),'Defensive Contribution - DEF'!K$2),0) -> 0 | Q2: =IF(B2="MID",IFERROR(VLOOKUP(A2,'Defensive Contribution - MID'!A$2:I$500,9,FALSE),'Defensive Contribution - MID'!L$2),0) -> 0 | R2: =IFERROR(IFERROR(E2,0)*IF(B2="GK",2+IFERROR(F2*10,0)+IFERROR(G2*10,0)+IFERROR(H2*10,0)+IFERROR(I2*3,0)-IFERROR(J2*1,0)+IFERROR(K2*4,0)+IFERROR(N2*1,0)+IFERROR(O2*1,0)-IFERROR(L2*2,0)-IFERROR(M2*2,0),IF(B2="DEF",2+IFERROR(F2*6,0)+IFERROR(G2*6,0)+IFERROR(H2*6,0)+IFERROR(I2*3,0)-IFERROR(J2*1,0)+IFERROR(K2*4,0)-IFERROR(L2*2,0)-IFERROR(M2*2,0)+IFERROR(P2*2,0),IF(B2="MID",2+IFERROR(F2*5,0)+IFERROR(G2*5,0)+IFERROR(H2*5,0)+IFERROR(I2*3,0)-IFERROR(J2*1,0)+IFERROR(K2*1,0)+IFERROR(Q2*2,0),IF(B2="FWD",2+IFERROR(F2*4,0)+IFERROR(G2*4,0)+IFERROR(H2*4,0)+IFERROR(I2*3,0)-IFERROR(J2*1,0),"ERROR")))),0) -> 3.7541439 | S2: =MAX(0, MIN(1, -0.021039 + 0.023522 * R2)) -> 0.067265974 | T2: =R2+S2*2 -> 3.8886759 | U2: =VLOOKUP($C2,'Team Fixtures'!$A$2:$Q$21,2,FALSE) -> 0.88924459 | V2: =VLOOKUP($C2,'Team Fixtures'!$A$2:$Q$21,4,FALSE) -> 0.028011204 | W2: =VLOOKUP($C2,'Team Fixtures'!$A$2:$Q$21,5,FALSE) -> 0.86123338 | X2: =VLOOKUP($C2,'Team Fixtures'!$A$2:$Q$21,6,FALSE) -> H | Y2: =R2/(2.926+0.578*U2-0.576*V2-0.561*W2+0.469*IF(X2="H",1,0)) -> 1.1010198 | Z2: =VLOOKUP($C2,'Team Fixtures'!$A$2:$Q$21,2,FALSE) -> 0.88924459 | AA2: =VLOOKUP($C2,'Team Fixtures'!$A$2:$Q$21,8,FALSE) -> 0.89678056 | AB2: =VLOOKUP($C2,'Team Fixtures'!$A$2:$Q$21,9,FALSE) -> -0.0075359711 | AC2: =VLOOKUP($C2,'Team Fixtures'!$A$2:$Q$21,10,FALSE) -> A | AD2: =IFERROR((2.926+0.578*Z2-0.576*AA2-0.561*AB2+0.469*IF(AC2="H",1,0))*$Y2,0) -> 3.2234177 | AE2: =MAX(0, MIN(1, -0.021039 + 0.023522 * AD2)) -> 0.05478223 | AF2: =AD2+AE2*2 -> 3.3329821 | AG2: =VLOOKUP($C2,'Team Fixtures'!$A$2:$Q$21,2,FALSE) -> 0.88924459 | AH2: =VLOOKUP($C2,'Team Fixtures'!$A$2:$Q$21,12,FALSE) -> 0.10582011 | AI2: =VLOOKUP($C2,'Team Fixtures'!$A$2:$Q$21,13,FALSE) -> 0.78342448 | AJ2: =VLOOKUP($C2,'Team Fixtures'!$A$2:$Q$21,14,FALSE) -> H | AK2: =IFERROR((2.926+0.578*AG2-0.576*AH2-0.561*AI2+0.469*IF(AJ2="H",1,0))*$Y2,0) -> 3.7528589 | AL2: =MAX(0, MIN(1, -0.021039 + 0.023522 * AK2)) -> 0.067235747 | AM2: =AK2+AL2*2 -> 3.8873304 | AN2: =VLOOKUP($C2,'Team Fixtures'!$A$2:$Q$21,2,FALSE) -> 0.88924459 | AO2: =VLOOKUP($C2,'Team Fixtures'!$A$2:$Q$21,16,FALSE) -> 0.87939146 | AP2: =VLOOKUP($C2,'Team Fixtures'!$A$2:$Q$21,17,FALSE) -> 0.0098531256 | AQ2: =VLOOKUP($C2,'Team Fixtures'!$A$2:$V$21,18,FALSE) -> H | AR2: =IFERROR((2.926+0.578*AN2-0.576*AO2-0.561*AP2+0.469*IF(AQ2="H",1,0))*$Y2,0) -> 3.7400832 | AS2: =MAX(0, MIN(1, -0.021039 + 0.023522 * AR2)) -> 0.066935236 | AT2: =AR2+AS2*2 -> 3.8739536 | AU2: =VLOOKUP($C2,'Team Fixtures'!$A$2:$Q$21,2,FALSE) -> 0.88924459 | AV2: =VLOOKUP($C2,'Team Fixtures'!$A$2:$V$21,20,FALSE) -> 0.50125313 | AW2: =VLOOKUP($C2,'Team Fixtures'!$A$2:$V$21,21,FALSE) -> 0.38799145 | AX2: =VLOOKUP($C2,'Team Fixtures'!$A$2:$V$21,22,FALSE) -> A | AY2: =IFERROR((2.926+0.578*AU2-0.576*AV2-0.561*AW2+0.469*IF(AX2="H",1,0))*$Y2,0) -> 3.2299499 | AZ2: =MAX(0, MIN(1, -0.021039 + 0.023522 * AY2)) -> 0.054935882 | BA2: =AY2+AZ2*2 -> 3.3398217 | BB2: =IFERROR(T2*1+AF2*0.85+AM2*0.7+AT2*0.55+BA2*0.4,0) -> 12.909445
A3: ='Players Full'!CU3 -> Kepa Arrizabalaga | B3: =VLOOKUP(_xlfn.CONCAT('Players Full'!AK3,'Players Full'!BV3),'Players Summarised'!$A$1:$T$1000,20,0) -> GK | C3: =VLOOKUP('Players Full'!CF3,Teams!$A$1:$G$21,6,0) -> Arsenal | D3: ='Players Full'!BD3/10 -> 4.5 | E3: =IFERROR(VLOOKUP($A3,'Starting Lineups'!$A$2:$C$510,3,FALSE),0) -> 0 | F3: =VLOOKUP(A3,'Score & Assist'!$A$1:$G$2000,6,0) -> #N/A | G3: =IF(F3<0.3, 0.01,IF(F3=0.3,0.03,IF(F3<0.5,0.05,IF(F3<0.55,0.06,IF(F3<0.57,0.1,IF(F3<0.58,0.11,IF(F3<0.59,0.12,IF(F3<0.6,0.15,0.28)))))))) -> #N/A | H3: =IF(F3<0.3,0,IF(F3<0.55,0.01,IF(F3<0.59,0.02,IF(F3<0.6,0.03,0.11)))) -> #N/A | I3: =VLOOKUP(A3,'Score & Assist'!$A$1:$G$2000,7,0) -> #N/A | J3: =VLOOKUP(A3,'Yellow Card'!$C$1:$E$987,3,0) -> 0.13605442 | K3: =VLOOKUP(C3,'Team Clean Sheet'!$C$2:$F$21,4,0) -> 0.5 | L3: =VLOOKUP(C3,'Team Total Goals'!$D$2:$N$21,10,0) -> 0.17168675 | M3: =VLOOKUP(C3,'Team Total Goals'!$D$2:$N$21,11,0) -> 0.01926849 | N3: =VLOOKUP(A3,'Goalkeeper Saves'!$D$2:$N$15,10,0) -> #N/A | O3: =VLOOKUP(A3,'Goalkeeper Saves'!$D$2:$N$15,11,0) -> #N/A | P3: =IF(B3="DEF",IFERROR(VLOOKUP(A3,'Defensive Contribution - DEF'!A3:H499,8,FALSE),'Defensive Contribution - DEF'!K$2),0) -> 0 | Q3: =IF(B3="MID",IFERROR(VLOOKUP(A3,'Defensive Contribution - MID'!A$2:I$500,9,FALSE),'Defensive Contribution - MID'!L$2),0) -> 0 | R3: =IFERROR(IFERROR(E3,0)*IF(B3="GK",2+IFERROR(F3*10,0)+IFERROR(G3*10,0)+IFERROR(H3*10,0)+IFERROR(I3*3,0)-IFERROR(J3*1,0)+IFERROR(K3*4,0)+IFERROR(N3*1,0)+IFERROR(O3*1,0)-IFERROR(L3*2,0)-IFERROR(M3*2,0),IF(B3="DEF",2+IFERROR(F3*6,0)+IFERROR(G3*6,0)+IFERROR(H3*6,0)+IFERROR(I3*3,0)-IFERROR(J3*1,0)+IFERROR(K3*4,0)-IFERROR(L3*2,0)-IFERROR(M3*2,0)+IFERROR(P3*2,0),IF(B3="MID",2+IFERROR(F3*5,0)+IFERROR(G3*5,0)+IFERROR(H3*5,0)+IFERROR(I3*3,0)-IFERROR(J3*1,0)+IFERROR(K3*1,0)+IFERROR(Q3*2,0),IF(B3="FWD",2+IFERROR(F3*4,0)+IFERROR(G3*4,0)+IFERROR(H3*4,0)+IFERROR(I3*3,0)-IFERROR(J3*1,0),"ERROR")))),0) -> 0 | S3: =MAX(0, MIN(1, -0.021039 + 0.023522 * R3)) -> 0 | T3: =R3+S3*2 -> 0 | U3: =VLOOKUP($C3,'Team Fixtures'!$A$2:$Q$21,2,FALSE) -> 0.88924459 | V3: =VLOOKUP($C3,'Team Fixtures'!$A$2:$Q$21,4,FALSE) -> 0.028011204 | W3: =VLOOKUP($C3,'Team Fixtures'!$A$2:$Q$21,5,FALSE) -> 0.86123338 | X3: =VLOOKUP($C3,'Team Fixtures'!$A$2:$Q$21,6,FALSE) -> H | Y3: =R3/(2.926+0.578*U3-0.576*V3-0.561*W3+0.469*IF(X3="H",1,0)) -> 0 | Z3: =VLOOKUP($C3,'Team Fixtures'!$A$2:$Q$21,2,FALSE) -> 0.88924459 | AA3: =VLOOKUP($C3,'Team Fixtures'!$A$2:$Q$21,8,FALSE) -> 0.89678056 | AB3: =VLOOKUP($C3,'Team Fixtures'!$A$2:$Q$21,9,FALSE) -> -0.0075359711 | AC3: =VLOOKUP($C3,'Team Fixtures'!$A$2:$Q$21,10,FALSE) -> A | AD3: =IFERROR((2.926+0.578*Z3-0.576*AA3-0.561*AB3+0.469*IF(AC3="H",1,0))*$Y3,0) -> 0 | AE3: =MAX(0, MIN(1, -0.021039 + 0.023522 * AD3)) -> 0 | AF3: =AD3+AE3*2 -> 0 | AG3: =VLOOKUP($C3,'Team Fixtures'!$A$2:$Q$21,2,FALSE) -> 0.88924459 | AH3: =VLOOKUP($C3,'Team Fixtures'!$A$2:$Q$21,12,FALSE) -> 0.10582011 | AI3: =VLOOKUP($C3,'Team Fixtures'!$A$2:$Q$21,13,FALSE) -> 0.78342448 | AJ3: =VLOOKUP($C3,'Team Fixtures'!$A$2:$Q$21,14,FALSE) -> H | AK3: =IFERROR((2.926+0.578*AG3-0.576*AH3-0.561*AI3+0.469*IF(AJ3="H",1,0))*$Y3,0) -> 0 | AL3: =MAX(0, MIN(1, -0.021039 + 0.023522 * AK3)) -> 0 | AM3: =AK3+AL3*2 -> 0 | AN3: =VLOOKUP($C3,'Team Fixtures'!$A$2:$Q$21,2,FALSE) -> 0.88924459 | AO3: =VLOOKUP($C3,'Team Fixtures'!$A$2:$Q$21,16,FALSE) -> 0.87939146 | AP3: =VLOOKUP($C3,'Team Fixtures'!$A$2:$Q$21,17,FALSE) -> 0.0098531256 | AQ3: =VLOOKUP($C3,'Team Fixtures'!$A$2:$V$21,18,FALSE) -> H | AR3: =IFERROR((2.926+0.578*AN3-0.576*AO3-0.561*AP3+0.469*IF(AQ3="H",1,0))*$Y3,0) -> 0 | AS3: =MAX(0, MIN(1, -0.021039 + 0.023522 * AR3)) -> 0 | AT3: =AR3+AS3*2 -> 0 | AU3: =VLOOKUP($C3,'Team Fixtures'!$A$2:$Q$21,2,FALSE) -> 0.88924459 | AV3: =VLOOKUP($C3,'Team Fixtures'!$A$2:$V$21,20,FALSE) -> 0.50125313 | AW3: =VLOOKUP($C3,'Team Fixtures'!$A$2:$V$21,21,FALSE) -> 0.38799145 | AX3: =VLOOKUP($C3,'Team Fixtures'!$A$2:$V$21,22,FALSE) -> A | AY3: =IFERROR((2.926+0.578*AU3-0.576*AV3-0.561*AW3+0.469*IF(AX3="H",1,0))*$Y3,0) -> 0 | AZ3: =MAX(0, MIN(1, -0.021039 + 0.023522 * AY3)) -> 0 | BA3: =AY3+AZ3*2 -> 0 | BB3: =IFERROR(T3*1+AF3*0.85+AM3*0.7+AT3*0.55+BA3*0.4,0) -> 0
A4: ='Players Full'!CU4 -> Karl Hein | B4: =VLOOKUP(_xlfn.CONCAT('Players Full'!AK4,'Players Full'!BV4),'Players Summarised'!$A$1:$T$1000,20,0) -> GK | C4: =VLOOKUP('Players Full'!CF4,Teams!$A$1:$G$21,6,0) -> Arsenal | D4: ='Players Full'!BD4/10 -> 4 | E4: =IFERROR(VLOOKUP($A4,'Starting Lineups'!$A$2:$C$510,3,FALSE),0) -> 0 | F4: =VLOOKUP(A4,'Score & Assist'!$A$1:$G$2000,6,0) -> #N/A | G4: =IF(F4<0.3, 0.01,IF(F4=0.3,0.03,IF(F4<0.5,0.05,IF(F4<0.55,0.06,IF(F4<0.57,0.1,IF(F4<0.58,0.11,IF(F4<0.59,0.12,IF(F4<0.6,0.15,0.28)))))))) -> #N/A | H4: =IF(F4<0.3,0,IF(F4<0.55,0.01,IF(F4<0.59,0.02,IF(F4<0.6,0.03,0.11)))) -> #N/A | I4: =VLOOKUP(A4,'Score & Assist'!$A$1:$G$2000,7,0) -> #N/A | J4: =VLOOKUP(A4,'Yellow Card'!$C$1:$E$987,3,0) -> #N/A | K4: =VLOOKUP(C4,'Team Clean Sheet'!$C$2:$F$21,4,0) -> 0.5 | L4: =VLOOKUP(C4,'Team Total Goals'!$D$2:$N$21,10,0) -> 0.17168675 | M4: =VLOOKUP(C4,'Team Total Goals'!$D$2:$N$21,11,0) -> 0.01926849 | N4: =VLOOKUP(A4,'Goalkeeper Saves'!$D$2:$N$15,10,0) -> #N/A | O4: =VLOOKUP(A4,'Goalkeeper Saves'!$D$2:$N$15,11,0) -> #N/A | P4: =IF(B4="DEF",IFERROR(VLOOKUP(A4,'Defensive Contribution - DEF'!A4:H500,8,FALSE),'Defensive Contribution - DEF'!K$2),0) -> 0 | Q4: =IF(B4="MID",IFERROR(VLOOKUP(A4,'Defensive Contribution - MID'!A$2:I$500,9,FALSE),'Defensive Contribution - MID'!L$2),0) -> 0 | R4: =IFERROR(IFERROR(E4,0)*IF(B4="GK",2+IFERROR(F4*10,0)+IFERROR(G4*10,0)+IFERROR(H4*10,0)+IFERROR(I4*3,0)-IFERROR(J4*1,0)+IFERROR(K4*4,0)+IFERROR(N4*1,0)+IFERROR(O4*1,0)-IFERROR(L4*2,0)-IFERROR(M4*2,0),IF(B4="DEF",2+IFERROR(F4*6,0)+IFERROR(G4*6,0)+IFERROR(H4*6,0)+IFERROR(I4*3,0)-IFERROR(J4*1,0)+IFERROR(K4*4,0)-IFERROR(L4*2,0)-IFERROR(M4*2,0)+IFERROR(P4*2,0),IF(B4="MID",2+IFERROR(F4*5,0)+IFERROR(G4*5,0)+IFERROR(H4*5,0)+IFERROR(I4*3,0)-IFERROR(J4*1,0)+IFERROR(K4*1,0)+IFERROR(Q4*2,0),IF(B4="FWD",2+IFERROR(F4*4,0)+IFERROR(G4*4,0)+IFERROR(H4*4,0)+IFERROR(I4*3,0)-IFERROR(J4*1,0),"ERROR")))),0) -> 0 | S4: =MAX(0, MIN(1, -0.021039 + 0.023522 * R4)) -> 0 | T4: =R4+S4*2 -> 0 | U4: =VLOOKUP($C4,'Team Fixtures'!$A$2:$Q$21,2,FALSE) -> 0.88924459 | V4: =VLOOKUP($C4,'Team Fixtures'!$A$2:$Q$21,4,FALSE) -> 0.028011204 | W4: =VLOOKUP($C4,'Team Fixtures'!$A$2:$Q$21,5,FALSE) -> 0.86123338 | X4: =VLOOKUP($C4,'Team Fixtures'!$A$2:$Q$21,6,FALSE) -> H | Y4: =R4/(2.926+0.578*U4-0.576*V4-0.561*W4+0.469*IF(X4="H",1,0)) -> 0 | Z4: =VLOOKUP($C4,'Team Fixtures'!$A$2:$Q$21,2,FALSE) -> 0.88924459 | AA4: =VLOOKUP($C4,'Team Fixtures'!$A$2:$Q$21,8,FALSE) -> 0.89678056 | AB4: =VLOOKUP($C4,'Team Fixtures'!$A$2:$Q$21,9,FALSE) -> -0.0075359711 | AC4: =VLOOKUP($C4,'Team Fixtures'!$A$2:$Q$21,10,FALSE) -> A | AD4: =IFERROR((2.926+0.578*Z4-0.576*AA4-0.561*AB4+0.469*IF(AC4="H",1,0))*$Y4,0) -> 0 | AE4: =MAX(0, MIN(1, -0.021039 + 0.023522 * AD4)) -> 0 | AF4: =AD4+AE4*2 -> 0 | AG4: =VLOOKUP($C4,'Team Fixtures'!$A$2:$Q$21,2,FALSE) -> 0.88924459 | AH4: =VLOOKUP($C4,'Team Fixtures'!$A$2:$Q$21,12,FALSE) -> 0.10582011 | AI4: =VLOOKUP($C4,'Team Fixtures'!$A$2:$Q$21,13,FALSE) -> 0.78342448 | AJ4: =VLOOKUP($C4,'Team Fixtures'!$A$2:$Q$21,14,FALSE) -> H | AK4: =IFERROR((2.926+0.578*AG4-0.576*AH4-0.561*AI4+0.469*IF(AJ4="H",1,0))*$Y4,0) -> 0 | AL4: =MAX(0, MIN(1, -0.021039 + 0.023522 * AK4)) -> 0 | AM4: =AK4+AL4*2 -> 0 | AN4: =VLOOKUP($C4,'Team Fixtures'!$A$2:$Q$21,2,FALSE) -> 0.88924459 | AO4: =VLOOKUP($C4,'Team Fixtures'!$A$2:$Q$21,16,FALSE) -> 0.87939146 | AP4: =VLOOKUP($C4,'Team Fixtures'!$A$2:$Q$21,17,FALSE) -> 0.0098531256 | AQ4: =VLOOKUP($C4,'Team Fixtures'!$A$2:$V$21,18,FALSE) -> H | AR4: =IFERROR((2.926+0.578*AN4-0.576*AO4-0.561*AP4+0.469*IF(AQ4="H",1,0))*$Y4,0) -> 0 | AS4: =MAX(0, MIN(1, -0.021039 + 0.023522 * AR4)) -> 0 | AT4: =AR4+AS4*2 -> 0 | AU4: =VLOOKUP($C4,'Team Fixtures'!$A$2:$Q$21,2,FALSE) -> 0.88924459 | AV4: =VLOOKUP($C4,'Team Fixtures'!$A$2:$V$21,20,FALSE) -> 0.50125313 | AW4: =VLOOKUP($C4,'Team Fixtures'!$A$2:$V$21,21,FALSE) -> 0.38799145 | AX4: =VLOOKUP($C4,'Team Fixtures'!$A$2:$V$21,22,FALSE) -> A | AY4: =IFERROR((2.926+0.578*AU4-0.576*AV4-0.561*AW4+0.469*IF(AX4="H",1,0))*$Y4,0) -> 0 | AZ4: =MAX(0, MIN(1, -0.021039 + 0.023522 * AY4)) -> 0 | BA4: =AY4+AZ4*2 -> 0 | BB4: =IFERROR(T4*1+AF4*0.85+AM4*0.7+AT4*0.55+BA4*0.4,0) -> 0
A5: ='Players Full'!CU5 -> Tommy Setford | B5: =VLOOKUP(_xlfn.CONCAT('Players Full'!AK5,'Players Full'!BV5),'Players Summarised'!$A$1:$T$1000,20,0) -> GK | C5: =VLOOKUP('Players Full'!CF5,Teams!$A$1:$G$21,6,0) -> Arsenal | D5: ='Players Full'!BD5/10 -> 4 | E5: =IFERROR(VLOOKUP($A5,'Starting Lineups'!$A$2:$C$510,3,FALSE),0) -> 0 | F5: =VLOOKUP(A5,'Score & Assist'!$A$1:$G$2000,6,0) -> #N/A | G5: =IF(F5<0.3, 0.01,IF(F5=0.3,0.03,IF(F5<0.5,0.05,IF(F5<0.55,0.06,IF(F5<0.57,0.1,IF(F5<0.58,0.11,IF(F5<0.59,0.12,IF(F5<0.6,0.15,0.28)))))))) -> #N/A | H5: =IF(F5<0.3,0,IF(F5<0.55,0.01,IF(F5<0.59,0.02,IF(F5<0.6,0.03,0.11)))) -> #N/A | I5: =VLOOKUP(A5,'Score & Assist'!$A$1:$G$2000,7,0) -> #N/A | J5: =VLOOKUP(A5,'Yellow Card'!$C$1:$E$987,3,0) -> 0.13605442 | K5: =VLOOKUP(C5,'Team Clean Sheet'!$C$2:$F$21,4,0) -> 0.5 | L5: =VLOOKUP(C5,'Team Total Goals'!$D$2:$N$21,10,0) -> 0.17168675 | M5: =VLOOKUP(C5,'Team Total Goals'!$D$2:$N$21,11,0) -> 0.01926849 | N5: =VLOOKUP(A5,'Goalkeeper Saves'!$D$2:$N$15,10,0) -> #N/A | O5: =VLOOKUP(A5,'Goalkeeper Saves'!$D$2:$N$15,11,0) -> #N/A | P5: =IF(B5="DEF",IFERROR(VLOOKUP(A5,'Defensive Contribution - DEF'!A5:H501,8,FALSE),'Defensive Contribution - DEF'!K$2),0) -> 0 | Q5: =IF(B5="MID",IFERROR(VLOOKUP(A5,'Defensive Contribution - MID'!A$2:I$500,9,FALSE),'Defensive Contribution - MID'!L$2),0) -> 0 | R5: =IFERROR(IFERROR(E5,0)*IF(B5="GK",2+IFERROR(F5*10,0)+IFERROR(G5*10,0)+IFERROR(H5*10,0)+IFERROR(I5*3,0)-IFERROR(J5*1,0)+IFERROR(K5*4,0)+IFERROR(N5*1,0)+IFERROR(O5*1,0)-IFERROR(L5*2,0)-IFERROR(M5*2,0),IF(B5="DEF",2+IFERROR(F5*6,0)+IFERROR(G5*6,0)+IFERROR(H5*6,0)+IFERROR(I5*3,0)-IFERROR(J5*1,0)+IFERROR(K5*4,0)-IFERROR(L5*2,0)-IFERROR(M5*2,0)+IFERROR(P5*2,0),IF(B5="MID",2+IFERROR(F5*5,0)+IFERROR(G5*5,0)+IFERROR(H5*5,0)+IFERROR(I5*3,0)-IFERROR(J5*1,0)+IFERROR(K5*1,0)+IFERROR(Q5*2,0),IF(B5="FWD",2+IFERROR(F5*4,0)+IFERROR(G5*4,0)+IFERROR(H5*4,0)+IFERROR(I5*3,0)-IFERROR(J5*1,0),"ERROR")))),0) -> 0 | S5: =MAX(0, MIN(1, -0.021039 + 0.023522 * R5)) -> 0 | T5: =R5+S5*2 -> 0 | U5: =VLOOKUP($C5,'Team Fixtures'!$A$2:$Q$21,2,FALSE) -> 0.88924459 | V5: =VLOOKUP($C5,'Team Fixtures'!$A$2:$Q$21,4,FALSE) -> 0.028011204 | W5: =VLOOKUP($C5,'Team Fixtures'!$A$2:$Q$21,5,FALSE) -> 0.86123338 | X5: =VLOOKUP($C5,'Team Fixtures'!$A$2:$Q$21,6,FALSE) -> H | Y5: =R5/(2.926+0.578*U5-0.576*V5-0.561*W5+0.469*IF(X5="H",1,0)) -> 0 | Z5: =VLOOKUP($C5,'Team Fixtures'!$A$2:$Q$21,2,FALSE) -> 0.88924459 | AA5: =VLOOKUP($C5,'Team Fixtures'!$A$2:$Q$21,8,FALSE) -> 0.89678056 | AB5: =VLOOKUP($C5,'Team Fixtures'!$A$2:$Q$21,9,FALSE) -> -0.0075359711 | AC5: =VLOOKUP($C5,'Team Fixtures'!$A$2:$Q$21,10,FALSE) -> A | AD5: =IFERROR((2.926+0.578*Z5-0.576*AA5-0.561*AB5+0.469*IF(AC5="H",1,0))*$Y5,0) -> 0 | AE5: =MAX(0, MIN(1, -0.021039 + 0.023522 * AD5)) -> 0 | AF5: =AD5+AE5*2 -> 0 | AG5: =VLOOKUP($C5,'Team Fixtures'!$A$2:$Q$21,2,FALSE) -> 0.88924459 | AH5: =VLOOKUP($C5,'Team Fixtures'!$A$2:$Q$21,12,FALSE) -> 0.10582011 | AI5: =VLOOKUP($C5,'Team Fixtures'!$A$2:$Q$21,13,FALSE) -> 0.78342448 | AJ5: =VLOOKUP($C5,'Team Fixtures'!$A$2:$Q$21,14,FALSE) -> H | AK5: =IFERROR((2.926+0.578*AG5-0.576*AH5-0.561*AI5+0.469*IF(AJ5="H",1,0))*$Y5,0) -> 0 | AL5: =MAX(0, MIN(1, -0.021039 + 0.023522 * AK5)) -> 0 | AM5: =AK5+AL5*2 -> 0 | AN5: =VLOOKUP($C5,'Team Fixtures'!$A$2:$Q$21,2,FALSE) -> 0.88924459 | AO5: =VLOOKUP($C5,'Team Fixtures'!$A$2:$Q$21,16,FALSE) -> 0.87939146 | AP5: =VLOOKUP($C5,'Team Fixtures'!$A$2:$Q$21,17,FALSE) -> 0.0098531256 | AQ5: =VLOOKUP($C5,'Team Fixtures'!$A$2:$V$21,18,FALSE) -> H | AR5: =IFERROR((2.926+0.578*AN5-0.576*AO5-0.561*AP5+0.469*IF(AQ5="H",1,0))*$Y5,0) -> 0 | AS5: =MAX(0, MIN(1, -0.021039 + 0.023522 * AR5)) -> 0 | AT5: =AR5+AS5*2 -> 0 | AU5: =VLOOKUP($C5,'Team Fixtures'!$A$2:$Q$21,2,FALSE) -> 0.88924459 | AV5: =VLOOKUP($C5,'Team Fixtures'!$A$2:$V$21,20,FALSE) -> 0.50125313 | AW5: =VLOOKUP($C5,'Team Fixtures'!$A$2:$V$21,21,FALSE) -> 0.38799145 | AX5: =VLOOKUP($C5,'Team Fixtures'!$A$2:$V$21,22,FALSE) -> A | AY5: =IFERROR((2.926+0.578*AU5-0.576*AV5-0.561*AW5+0.469*IF(AX5="H",1,0))*$Y5,0) -> 0 | AZ5: =MAX(0, MIN(1, -0.021039 + 0.023522 * AY5)) -> 0 | BA5: =AY5+AZ5*2 -> 0 | BB5: =IFERROR(T5*1+AF5*0.85+AM5*0.7+AT5*0.55+BA5*0.4,0) -> 0
A6: ='Players Full'!CU6 -> Gabriel Magalhaes | B6: =VLOOKUP(_xlfn.CONCAT('Players Full'!AK6,'Players Full'!BV6),'Players Summarised'!$A$1:$T$1000,20,0) -> DEF | C6: =VLOOKUP('Players Full'!CF6,Teams!$A$1:$G$21,6,0) -> Arsenal | D6: ='Players Full'!BD6/10 -> 6 | E6: =IFERROR(VLOOKUP($A6,'Starting Lineups'!$A$2:$C$510,3,FALSE),0) -> 1 | F6: =VLOOKUP(A6,'Score & Assist'!$A$1:$G$2000,6,0) -> 0.19047619 | G6: =IF(F6<0.3, 0.01,IF(F6=0.3,0.03,IF(F6<0.5,0.05,IF(F6<0.55,0.06,IF(F6<0.57,0.1,IF(F6<0.58,0.11,IF(F6<0.59,0.12,IF(F6<0.6,0.15,0.28)))))))) -> 0.01 | H6: =IF(F6<0.3,0,IF(F6<0.55,0.01,IF(F6<0.59,0.02,IF(F6<0.6,0.03,0.11)))) -> 0 | I6: =VLOOKUP(A6,'Score & Assist'!$A$1:$G$2000,7,0) -> 0.050125313 | J6: =VLOOKUP(A6,'Yellow Card'!$C$1:$E$987,3,0) -> 0.13605442 | K6: =VLOOKUP(C6,'Team Clean Sheet'!$C$2:$F$21,4,0) -> 0.5 | L6: =VLOOKUP(C6,'Team Total Goals'!$D$2:$N$21,10,0) -> 0.17168675 | M6: =VLOOKUP(C6,'Team Total Goals'!$D$2:$N$21,11,0) -> 0.01926849 | N6: =VLOOKUP(A6,'Goalkeeper Saves'!$D$2:$N$15,10,0) -> #N/A | O6: =VLOOKUP(A6,'Goalkeeper Saves'!$D$2:$N$15,11,0) -> #N/A | P6: =IF(B6="DEF",IFERROR(VLOOKUP(A6,'Defensive Contribution - DEF'!A6:H502,8,FALSE),'Defensive Contribution - DEF'!K$2),0) -> 0.11320273 | Q6: =IF(B6="MID",IFERROR(VLOOKUP(A6,'Defensive Contribution - MID'!A$2:I$500,9,FALSE),'Defensive Contribution - MID'!L$2),0) -> 0 | R6: =IFERROR(IFERROR(E6,0)*IF(B6="GK",2+IFERROR(F6*10,0)+IFERROR(G6*10,0)+IFERROR(H6*10,0)+IFERROR(I6*3,0)-IFERROR(J6*1,0)+IFERROR(K6*4,0)+IFERROR(N6*1,0)+IFERROR(O6*1,0)-IFERROR(L6*2,0)-IFERROR(M6*2,0),IF(B6="DEF",2+IFERROR(F6*6,0)+IFERROR(G6*6,0)+IFERROR(H6*6,0)+IFERROR(I6*3,0)-IFERROR(J6*1,0)+IFERROR(K6*4,0)-IFERROR(L6*2,0)-IFERROR(M6*2,0)+IFERROR(P6*2,0),IF(B6="MID",2+IFERROR(F6*5,0)+IFERROR(G6*5,0)+IFERROR(H6*5,0)+IFERROR(I6*3,0)-IFERROR(J6*1,0)+IFERROR(K6*1,0)+IFERROR(Q6*2,0),IF(B6="FWD",2+IFERROR(F6*4,0)+IFERROR(G6*4,0)+IFERROR(H6*4,0)+IFERROR(I6*3,0)-IFERROR(J6*1,0),"ERROR")))),0) -> 5.0616736 | S6: =MAX(0, MIN(1, -0.021039 + 0.023522 * R6)) -> 0.098021688 | T6: =R6+S6*2 -> 5.257717 | U6: =VLOOKUP($C6,'Team Fixtures'!$A$2:$Q$21,2,FALSE) -> 0.88924459 | V6: =VLOOKUP($C6,'Team Fixtures'!$A$2:$Q$21,4,FALSE) -> 0.028011204 | W6: =VLOOKUP($C6,'Team Fixtures'!$A$2:$Q$21,5,FALSE) -> 0.86123338 | X6: =VLOOKUP($C6,'Team Fixtures'!$A$2:$Q$21,6,FALSE) -> H | Y6: =R6/(2.926+0.578*U6-0.576*V6-0.561*W6+0.469*IF(X6="H",1,0)) -> 1.4844937 | Z6: =VLOOKUP($C6,'Team Fixtures'!$A$2:$Q$21,2,FALSE) -> 0.88924459 | AA6: =VLOOKUP($C6,'Team Fixtures'!$A$2:$Q$21,8,FALSE) -> 0.89678056 | AB6: =VLOOKUP($C6,'Team Fixtures'!$A$2:$Q$21,9,FALSE) -> -0.0075359711 | AC6: =VLOOKUP($C6,'Team Fixtures'!$A$2:$Q$21,10,FALSE) -> A | AD6: =IFERROR((2.926+0.578*Z6-0.576*AA6-0.561*AB6+0.469*IF(AC6="H",1,0))*$Y6,0) -> 4.3461009 | AE6: =MAX(0, MIN(1, -0.021039 + 0.023522 * AD6)) -> 0.081189985 | AF6: =AD6+AE6*2 -> 4.5084808 | AG6: =VLOOKUP($C6,'Team Fixtures'!$A$2:$Q$21,2,FALSE) -> 0.88924459 | AH6: =VLOOKUP($C6,'Team Fixtures'!$A$2:$Q$21,12,FALSE) -> 0.10582011 | AI6: =VLOOKUP($C6,'Team Fixtures'!$A$2:$Q$21,13,FALSE) -> 0.78342448 | AJ6: =VLOOKUP($C6,'Team Fixtures'!$A$2:$Q$21,14,FALSE) -> H | AK6: =IFERROR((2.926+0.578*AG6-0.576*AH6-0.561*AI6+0.469*IF(AJ6="H",1,0))*$Y6,0) -> 5.059941 | AL6: =MAX(0, MIN(1, -0.021039 + 0.023522 * AK6)) -> 0.097980933 | AM6: =AK6+AL6*2 -> 5.2559029 | AN6: =VLOOKUP($C6,'Team Fixtures'!$A$2:$Q$21,2,FALSE) -> 0.88924459 | AO6: =VLOOKUP($C6,'Team Fixtures'!$A$2:$Q$21,16,FALSE) -> 0.87939146 | AP6: =VLOOKUP($C6,'Team Fixtures'!$A$2:$Q$21,17,FALSE) -> 0.0098531256 | AQ6: =VLOOKUP($C6,'Team Fixtures'!$A$2:$V$21,18,FALSE) -> H | AR6: =IFERROR((2.926+0.578*AN6-0.576*AO6-0.561*AP6+0.469*IF(AQ6="H",1,0))*$Y6,0) -> 5.0427156 | AS6: =MAX(0, MIN(1, -0.021039 + 0.023522 * AR6)) -> 0.097575757 | AT6: =AR6+AS6*2 -> 5.2378671 | AU6: =VLOOKUP($C6,'Team Fixtures'!$A$2:$Q$21,2,FALSE) -> 0.88924459 | AV6: =VLOOKUP($C6,'Team Fixtures'!$A$2:$V$21,20,FALSE) -> 0.50125313 | AW6: =VLOOKUP($C6,'Team Fixtures'!$A$2:$V$21,21,FALSE) -> 0.38799145 | AX6: =VLOOKUP($C6,'Team Fixtures'!$A$2:$V$21,22,FALSE) -> A | AY6: =IFERROR((2.926+0.578*AU6-0.576*AV6-0.561*AW6+0.469*IF(AX6="H",1,0))*$Y6,0) -> 4.3549082 | AZ6: =MAX(0, MIN(1, -0.021039 + 0.023522 * AY6)) -> 0.081397152 | BA6: =AY6+AZ6*2 -> 4.5177025 | BB6: =IFERROR(T6*1+AF6*0.85+AM6*0.7+AT6*0.55+BA6*0.4,0) -> 17.456966
A7: ='Players Full'!CU7 -> William Saliba | B7: =VLOOKUP(_xlfn.CONCAT('Players Full'!AK7,'Players Full'!BV7),'Players Summarised'!$A$1:$T$1000,20,0) -> DEF | C7: =VLOOKUP('Players Full'!CF7,Teams!$A$1:$G$21,6,0) -> Arsenal | D7: ='Players Full'!BD7/10 -> 6 | E7: =IFERROR(VLOOKUP($A7,'Starting Lineups'!$A$2:$C$510,3,FALSE),0) -> 1 | F7: =VLOOKUP(A7,'Score & Assist'!$A$1:$G$2000,6,0) -> 0.10025063 | G7: =IF(F7<0.3, 0.01,IF(F7=0.3,0.03,IF(F7<0.5,0.05,IF(F7<0.55,0.06,IF(F7<0.57,0.1,IF(F7<0.58,0.11,IF(F7<0.59,0.12,IF(F7<0.6,0.15,0.28)))))))) -> 0.01 | H7: =IF(F7<0.3,0,IF(F7<0.55,0.01,IF(F7<0.59,0.02,IF(F7<0.6,0.03,0.11)))) -> 0 | I7: =VLOOKUP(A7,'Score & Assist'!$A$1:$G$2000,7,0) -> 0.045351474 | J7: =VLOOKUP(A7,'Yellow Card'!$C$1:$E$987,3,0) -> 0.11204482 | K7: =VLOOKUP(C7,'Team Clean Sheet'!$C$2:$F$21,4,0) -> 0.5 | L7: =VLOOKUP(C7,'Team Total Goals'!$D$2:$N$21,10,0) -> 0.17168675 | M7: =VLOOKUP(C7,'Team Total Goals'!$D$2:$N$21,11,0) -> 0.01926849 | N7: =VLOOKUP(A7,'Goalkeeper Saves'!$D$2:$N$15,10,0) -> #N/A | O7: =VLOOKUP(A7,'Goalkeeper Saves'!$D$2:$N$15,11,0) -> #N/A | P7: =IF(B7="DEF",IFERROR(VLOOKUP(A7,'Defensive Contribution - DEF'!A7:H503,8,FALSE),'Defensive Contribution - DEF'!K$2),0) -> 0.11489343 | Q7: =IF(B7="MID",IFERROR(VLOOKUP(A7,'Defensive Contribution - MID'!A$2:I$500,9,FALSE),'Defensive Contribution - MID'!L$2),0) -> 0 | R7: =IFERROR(IFERROR(E7,0)*IF(B7="GK",2+IFERROR(F7*10,0)+IFERROR(G7*10,0)+IFERROR(H7*10,0)+IFERROR(I7*3,0)-IFERROR(J7*1,0)+IFERROR(K7*4,0)+IFERROR(N7*1,0)+IFERROR(O7*1,0)-IFERROR(L7*2,0)-IFERROR(M7*2,0),IF(B7="DEF",2+IFERROR(F7*6,0)+IFERROR(G7*6,0)+IFERROR(H7*6,0)+IFERROR(I7*3,0)-IFERROR(J7*1,0)+IFERROR(K7*4,0)-IFERROR(L7*2,0)-IFERROR(M7*2,0)+IFERROR(P7*2,0),IF(B7="MID",2+IFERROR(F7*5,0)+IFERROR(G7*5,0)+IFERROR(H7*5,0)+IFERROR(I7*3,0)-IFERROR(J7*1,0)+IFERROR(K7*1,0)+IFERROR(Q7*2,0),IF(B7="FWD",2+IFERROR(F7*4,0)+IFERROR(G7*4,0)+IFERROR(H7*4,0)+IFERROR(I7*3,0)-IFERROR(J7*1,0),"ERROR")))),0) -> 4.5333898 | S7: =MAX(0, MIN(1, -0.021039 + 0.023522 * R7)) -> 0.085595394 | T7: =R7+S7*2 -> 4.7045805 | U7: =VLOOKUP($C7,'Team Fixtures'!$A$2:$Q$21,2,FALSE) -> 0.88924459 | V7: =VLOOKUP($C7,'Team Fixtures'!$A$2:$Q$21,4,FALSE) -> 0.028011204 | W7: =VLOOKUP($C7,'Team Fixtures'!$A$2:$Q$21,5,FALSE) -> 0.86123338 | X7: =VLOOKUP($C7,'Team Fixtures'!$A$2:$Q$21,6,FALSE) -> H | Y7: =R7/(2.926+0.578*U7-0.576*V7-0.561*W7+0.469*IF(X7="H",1,0)) -> 1.329558 | Z7: =VLOOKUP($C7,'Team Fixtures'!$A$2:$Q$21,2,FALSE) -> 0.88924459 | AA7: =VLOOKUP($C7,'Team Fixtures'!$A$2:$Q$21,8,FALSE) -> 0.89678056 | AB7: =VLOOKUP($C7,'Team Fixtures'!$A$2:$Q$21,9,FALSE) -> -0.0075359711 | AC7: =VLOOKUP($C7,'Team Fixtures'!$A$2:$Q$21,10,FALSE) -> A | AD7: =IFERROR((2.926+0.578*Z7-0.576*AA7-0.561*AB7+0.469*IF(AC7="H",1,0))*$Y7,0) -> 3.8925009 | AE7: =MAX(0, MIN(1, -0.021039 + 0.023522 * AD7)) -> 0.070520406 | AF7: =AD7+AE7*2 -> 4.0335417 | AG7: =VLOOKUP($C7,'Team Fixtures'!$A$2:$Q$21,2,FALSE) -> 0.88924459 | AH7: =VLOOKUP($C7,'Team Fixtures'!$A$2:$Q$21,12,FALSE) -> 0.10582011 | AI7: =VLOOKUP($C7,'Team Fixtures'!$A$2:$Q$21,13,FALSE) -> 0.78342448 | AJ7: =VLOOKUP($C7,'Team Fixtures'!$A$2:$Q$21,14,FALSE) -> H | AK7: =IFERROR((2.926+0.578*AG7-0.576*AH7-0.561*AI7+0.469*IF(AJ7="H",1,0))*$Y7,0) -> 4.531838 | AL7: =MAX(0, MIN(1, -0.021039 + 0.023522 * AK7)) -> 0.085558893 | AM7: =AK7+AL7*2 -> 4.7029558 | AN7: =VLOOKUP($C7,'Team Fixtures'!$A$2:$Q$21,2,FALSE) -> 0.88924459 | AO7: =VLOOKUP($C7,'Team Fixtures'!$A$2:$Q$21,16,FALSE) -> 0.87939146 | AP7: =VLOOKUP($C7,'Team Fixtures'!$A$2:$Q$21,17,FALSE) -> 0.0098531256 | AQ7: =VLOOKUP($C7,'Team Fixtures'!$A$2:$V$21,18,FALSE) -> H | AR7: =IFERROR((2.926+0.578*AN7-0.576*AO7-0.561*AP7+0.469*IF(AQ7="H",1,0))*$Y7,0) -> 4.5164104 | AS7: =MAX(0, MIN(1, -0.021039 + 0.023522 * AR7)) -> 0.085196005 | AT7: =AR7+AS7*2 -> 4.6868024 | AU7: =VLOOKUP($C7,'Team Fixtures'!$A$2:$Q$21,2,FALSE) -> 0.88924459 | AV7: =VLOOKUP($C7,'Team Fixtures'!$A$2:$V$21,20,FALSE) -> 0.50125313 | AW7: =VLOOKUP($C7,'Team Fixtures'!$A$2:$V$21,21,FALSE) -> 0.38799145 | AX7: =VLOOKUP($C7,'Team Fixtures'!$A$2:$V$21,22,FALSE) -> A | AY7: =IFERROR((2.926+0.578*AU7-0.576*AV7-0.561*AW7+0.469*IF(AX7="H",1,0))*$Y7,0) -> 3.900389 | AZ7: =MAX(0, MIN(1, -0.021039 + 0.023522 * AY7)) -> 0.070705951 | BA7: =AY7+AZ7*2 -> 4.0418009 | BB7: =IFERROR(T7*1+AF7*0.85+AM7*0.7+AT7*0.55+BA7*0.4,0) -> 15.619622
A8: ='Players Full'!CU8 -> Riccardo Calafiori | B8: =VLOOKUP(_xlfn.CONCAT('Players Full'!AK8,'Players Full'!BV8),'Players Summarised'!$A$1:$T$1000,20,0) -> DEF | C8: =VLOOKUP('Players Full'!CF8,Teams!$A$1:$G$21,6,0) -> Arsenal | D8: ='Players Full'!BD8/10 -> 5.5 | E8: =IFERROR(VLOOKUP($A8,'Starting Lineups'!$A$2:$C$510,3,FALSE),0) -> 0 | F8: =VLOOKUP(A8,'Score & Assist'!$A$1:$G$2000,6,0) -> 0.11204482 | G8: =IF(F8<0.3, 0.01,IF(F8=0.3,0.03,IF(F8<0.5,0.05,IF(F8<0.55,0.06,IF(F8<0.57,0.1,IF(F8<0.58,0.11,IF(F8<0.59,0.12,IF(F8<0.6,0.15,0.28)))))))) -> 0.01 | H8: =IF(F8<0.3,0,IF(F8<0.55,0.01,IF(F8<0.59,0.02,IF(F8<0.6,0.03,0.11)))) -> 0 | I8: =VLOOKUP(A8,'Score & Assist'!$A$1:$G$2000,7,0) -> 0.13605442 | J8: =VLOOKUP(A8,'Yellow Card'!$C$1:$E$987,3,0) -> 0.17316017 | K8: =VLOOKUP(C8,'Team Clean Sheet'!$C$2:$F$21,4,0) -> 0.5 | L8: =VLOOKUP(C8,'Team Total Goals'!$D$2:$N$21,10,0) -> 0.17168675 | M8: =VLOOKUP(C8,'Team Total Goals'!$D$2:$N$21,11,0) -> 0.01926849 | N8: =VLOOKUP(A8,'Goalkeeper Saves'!$D$2:$N$15,10,0) -> #N/A | O8: =VLOOKUP(A8,'Goalkeeper Saves'!$D$2:$N$15,11,0) -> #N/A | P8: =IF(B8="DEF",IFERROR(VLOOKUP(A8,'Defensive Contribution - DEF'!A8:H504,8,FALSE),'Defensive Contribution - DEF'!K$2),0) -> 0.11357041 | Q8: =IF(B8="MID",IFERROR(VLOOKUP(A8,'Defensive Contribution - MID'!A$2:I$500,9,FALSE),'Defensive Contribution - MID'!L$2),0) -> 0 | R8: =IFERROR(IFERROR(E8,0)*IF(B8="GK",2+IFERROR(F8*10,0)+IFERROR(G8*10,0)+IFERROR(H8*10,0)+IFERROR(I8*3,0)-IFERROR(J8*1,0)+IFERROR(K8*4,0)+IFERROR(N8*1,0)+IFERROR(O8*1,0)-IFERROR(L8*2,0)-IFERROR(M8*2,0),IF(B8="DEF",2+IFERROR(F8*6,0)+IFERROR(G8*6,0)+IFERROR(H8*6,0)+IFERROR(I8*3,0)-IFERROR(J8*1,0)+IFERROR(K8*4,0)-IFERROR(L8*2,0)-IFERROR(M8*2,0)+IFERROR(P8*2,0),IF(B8="MID",2+IFERROR(F8*5,0)+IFERROR(G8*5,0)+IFERROR(H8*5,0)+IFERROR(I8*3,0)-IFERROR(J8*1,0)+IFERROR(K8*1,0)+IFERROR(Q8*2,0),IF(B8="FWD",2+IFERROR(F8*4,0)+IFERROR(G8*4,0)+IFERROR(H8*4,0)+IFERROR(I8*3,0)-IFERROR(J8*1,0),"ERROR")))),0) -> 0 | S8: =MAX(0, MIN(1, -0.021039 + 0.023522 * R8)) -> 0 | T8: =R8+S8*2 -> 0 | U8: =VLOOKUP($C8,'Team Fixtures'!$A$2:$Q$21,2,FALSE) -> 0.88924459 | V8: =VLOOKUP($C8,'Team Fixtures'!$A$2:$Q$21,4,FALSE) -> 0.028011204 | W8: =VLOOKUP($C8,'Team Fixtures'!$A$2:$Q$21,5,FALSE) -> 0.86123338 | X8: =VLOOKUP($C8,'Team Fixtures'!$A$2:$Q$21,6,FALSE) -> H | Y8: =R8/(2.926+0.578*U8-0.576*V8-0.561*W8+0.469*IF(X8="H",1,0)) -> 0 | Z8: =VLOOKUP($C8,'Team Fixtures'!$A$2:$Q$21,2,FALSE) -> 0.88924459 | AA8: =VLOOKUP($C8,'Team Fixtures'!$A$2:$Q$21,8,FALSE) -> 0.89678056 | AB8: =VLOOKUP($C8,'Team Fixtures'!$A$2:$Q$21,9,FALSE) -> -0.0075359711 | AC8: =VLOOKUP($C8,'Team Fixtures'!$A$2:$Q$21,10,FALSE) -> A | AD8: =IFERROR((2.926+0.578*Z8-0.576*AA8-0.561*AB8+0.469*IF(AC8="H",1,0))*$Y8,0) -> 0 | AE8: =MAX(0, MIN(1, -0.021039 + 0.023522 * AD8)) -> 0 | AF8: =AD8+AE8*2 -> 0 | AG8: =VLOOKUP($C8,'Team Fixtures'!$A$2:$Q$21,2,FALSE) -> 0.88924459 | AH8: =VLOOKUP($C8,'Team Fixtures'!$A$2:$Q$21,12,FALSE) -> 0.10582011 | AI8: =VLOOKUP($C8,'Team Fixtures'!$A$2:$Q$21,13,FALSE) -> 0.78342448 | AJ8: =VLOOKUP($C8,'Team Fixtures'!$A$2:$Q$21,14,FALSE) -> H | AK8: =IFERROR((2.926+0.578*AG8-0.576*AH8-0.561*AI8+0.469*IF(AJ8="H",1,0))*$Y8,0) -> 0 | AL8: =MAX(0, MIN(1, -0.021039 + 0.023522 * AK8)) -> 0 | AM8: =AK8+AL8*2 -> 0 | AN8: =VLOOKUP($C8,'Team Fixtures'!$A$2:$Q$21,2,FALSE) -> 0.88924459 | AO8: =VLOOKUP($C8,'Team Fixtures'!$A$2:$Q$21,16,FALSE) -> 0.87939146 | AP8: =VLOOKUP($C8,'Team Fixtures'!$A$2:$Q$21,17,FALSE) -> 0.0098531256 | AQ8: =VLOOKUP($C8,'Team Fixtures'!$A$2:$V$21,18,FALSE) -> H | AR8: =IFERROR((2.926+0.578*AN8-0.576*AO8-0.561*AP8+0.469*IF(AQ8="H",1,0))*$Y8,0) -> 0 | AS8: =MAX(0, MIN(1, -0.021039 + 0.023522 * AR8)) -> 0 | AT8: =AR8+AS8*2 -> 0 | AU8: =VLOOKUP($C8,'Team Fixtures'!$A$2:$Q$21,2,FALSE) -> 0.88924459 | AV8: =VLOOKUP($C8,'Team Fixtures'!$A$2:$V$21,20,FALSE) -> 0.50125313 | AW8: =VLOOKUP($C8,'Team Fixtures'!$A$2:$V$21,21,FALSE) -> 0.38799145 | AX8: =VLOOKUP($C8,'Team Fixtures'!$A$2:$V$21,22,FALSE) -> A | AY8: =IFERROR((2.926+0.578*AU8-0.576*AV8-0.561*AW8+0.469*IF(AX8="H",1,0))*$Y8,0) -> 0 | AZ8: =MAX(0, MIN(1, -0.021039 + 0.023522 * AY8)) -> 0 | BA8: =AY8+AZ8*2 -> 0 | BB8: =IFERROR(T8*1+AF8*0.85+AM8*0.7+AT8*0.55+BA8*0.4,0) -> 0
A9: ='Players Full'!CU9 -> Jurrian Timber | B9: =VLOOKUP(_xlfn.CONCAT('Players Full'!AK9,'Players Full'!BV9),'Players Summarised'!$A$1:$T$1000,20,0) -> DEF | C9: =VLOOKUP('Players Full'!CF9,Teams!$A$1:$G$21,6,0) -> Arsenal | D9: ='Players Full'!BD9/10 -> 5.5 | E9: =IFERROR(VLOOKUP($A9,'Starting Lineups'!$A$2:$C$510,3,FALSE),0) -> 0 | F9: =VLOOKUP(A9,'Score & Assist'!$A$1:$G$2000,6,0) -> #N/A | G9: =IF(F9<0.3, 0.01,IF(F9=0.3,0.03,IF(F9<0.5,0.05,IF(F9<0.55,0.06,IF(F9<0.57,0.1,IF(F9<0.58,0.11,IF(F9<0.59,0.12,IF(F9<0.6,0.15,0.28)))))))) -> #N/A | H9: =IF(F9<0.3,0,IF(F9<0.55,0.01,IF(F9<0.59,0.02,IF(F9<0.6,0.03,0.11)))) -> #N/A | I9: =VLOOKUP(A9,'Score & Assist'!$A$1:$G$2000,7,0) -> #N/A | J9: =VLOOKUP(A9,'Yellow Card'!$C$1:$E$987,3,0) -> #N/A | K9: =VLOOKUP(C9,'Team Clean Sheet'!$C$2:$F$21,4,0) -> 0.5 | L9: =VLOOKUP(C9,'Team Total Goals'!$D$2:$N$21,10,0) -> 0.17168675 | M9: =VLOOKUP(C9,'Team Total Goals'!$D$2:$N$21,11,0) -> 0.01926849 | N9: =VLOOKUP(A9,'Goalkeeper Saves'!$D$2:$N$15,10,0) -> #N/A | O9: =VLOOKUP(A9,'Goalkeeper Saves'!$D$2:$N$15,11,0) -> #N/A | P9: =IF(B9="DEF",IFERROR(VLOOKUP(A9,'Defensive Contribution - DEF'!A9:H505,8,FALSE),'Defensive Contribution - DEF'!K$2),0) -> 0.2915234 | Q9: =IF(B9="MID",IFERROR(VLOOKUP(A9,'Defensive Contribution - MID'!A$2:I$500,9,FALSE),'Defensive Contribution - MID'!L$2),0) -> 0 | R9: =IFERROR(IFERROR(E9,0)*IF(B9="GK",2+IFERROR(F9*10,0)+IFERROR(G9*10,0)+IFERROR(H9*10,0)+IFERROR(I9*3,0)-IFERROR(J9*1,0)+IFERROR(K9*4,0)+IFERROR(N9*1,0)+IFERROR(O9*1,0)-IFERROR(L9*2,0)-IFERROR(M9*2,0),IF(B9="DEF",2+IFERROR(F9*6,0)+IFERROR(G9*6,0)+IFERROR(H9*6,0)+IFERROR(I9*3,0)-IFERROR(J9*1,0)+IFERROR(K9*4,0)-IFERROR(L9*2,0)-IFERROR(M9*2,0)+IFERROR(P9*2,0),IF(B9="MID",2+IFERROR(F9*5,0)+IFERROR(G9*5,0)+IFERROR(H9*5,0)+IFERROR(I9*3,0)-IFERROR(J9*1,0)+IFERROR(K9*1,0)+IFERROR(Q9*2,0),IF(B9="FWD",2+IFERROR(F9*4,0)+IFERROR(G9*4,0)+IFERROR(H9*4,0)+IFERROR(I9*3,0)-IFERROR(J9*1,0),"ERROR")))),0) -> 0 | S9: =MAX(0, MIN(1, -0.021039 + 0.023522 * R9)) -> 0 | T9: =R9+S9*2 -> 0 | U9: =VLOOKUP($C9,'Team Fixtures'!$A$2:$Q$21,2,FALSE) -> 0.88924459 | V9: =VLOOKUP($C9,'Team Fixtures'!$A$2:$Q$21,4,FALSE) -> 0.028011204 | W9: =VLOOKUP($C9,'Team Fixtures'!$A$2:$Q$21,5,FALSE) -> 0.86123338 | X9: =VLOOKUP($C9,'Team Fixtures'!$A$2:$Q$21,6,FALSE) -> H | Y9: =R9/(2.926+0.578*U9-0.576*V9-0.561*W9+0.469*IF(X9="H",1,0)) -> 0 | Z9: =VLOOKUP($C9,'Team Fixtures'!$A$2:$Q$21,2,FALSE) -> 0.88924459 | AA9: =VLOOKUP($C9,'Team Fixtures'!$A$2:$Q$21,8,FALSE) -> 0.89678056 | AB9: =VLOOKUP($C9,'Team Fixtures'!$A$2:$Q$21,9,FALSE) -> -0.0075359711 | AC9: =VLOOKUP($C9,'Team Fixtures'!$A$2:$Q$21,10,FALSE) -> A | AD9: =IFERROR((2.926+0.578*Z9-0.576*AA9-0.561*AB9+0.469*IF(AC9="H",1,0))*$Y9,0) -> 0 | AE9: =MAX(0, MIN(1, -0.021039 + 0.023522 * AD9)) -> 0 | AF9: =AD9+AE9*2 -> 0 | AG9: =VLOOKUP($C9,'Team Fixtures'!$A$2:$Q$21,2,FALSE) -> 0.88924459 | AH9: =VLOOKUP($C9,'Team Fixtures'!$A$2:$Q$21,12,FALSE) -> 0.10582011 | AI9: =VLOOKUP($C9,'Team Fixtures'!$A$2:$Q$21,13,FALSE) -> 0.78342448 | AJ9: =VLOOKUP($C9,'Team Fixtures'!$A$2:$Q$21,14,FALSE) -> H | AK9: =IFERROR((2.926+0.578*AG9-0.576*AH9-0.561*AI9+0.469*IF(AJ9="H",1,0))*$Y9,0) -> 0 | AL9: =MAX(0, MIN(1, -0.021039 + 0.023522 * AK9)) -> 0 | AM9: =AK9+AL9*2 -> 0 | AN9: =VLOOKUP($C9,'Team Fixtures'!$A$2:$Q$21,2,FALSE) -> 0.88924459 | AO9: =VLOOKUP($C9,'Team Fixtures'!$A$2:$Q$21,16,FALSE) -> 0.87939146 | AP9: =VLOOKUP($C9,'Team Fixtures'!$A$2:$Q$21,17,FALSE) -> 0.0098531256 | AQ9: =VLOOKUP($C9,'Team Fixtures'!$A$2:$V$21,18,FALSE) -> H | AR9: =IFERROR((2.926+0.578*AN9-0.576*AO9-0.561*AP9+0.469*IF(AQ9="H",1,0))*$Y9,0) -> 0 | AS9: =MAX(0, MIN(1, -0.021039 + 0.023522 * AR9)) -> 0 | AT9: =AR9+AS9*2 -> 0 | AU9: =VLOOKUP($C9,'Team Fixtures'!$A$2:$Q$21,2,FALSE) -> 0.88924459 | AV9: =VLOOKUP($C9,'Team Fixtures'!$A$2:$V$21,20,FALSE) -> 0.50125313 | AW9: =VLOOKUP($C9,'Team Fixtures'!$A$2:$V$21,21,FALSE) -> 0.38799145 | AX9: =VLOOKUP($C9,'Team Fixtures'!$A$2:$V$21,22,FALSE) -> A | AY9: =IFERROR((2.926+0.578*AU9-0.576*AV9-0.561*AW9+0.469*IF(AX9="H",1,0))*$Y9,0) -> 0 | AZ9: =MAX(0, MIN(1, -0.021039 + 0.023522 * AY9)) -> 0 | BA9: =AY9+AZ9*2 -> 0 | BB9: =IFERROR(T9*1+AF9*0.85+AM9*0.7+AT9*0.55+BA9*0.4,0) -> 0
A10: ='Players Full'!CU10 -> Jakub Kiwior | B10: =VLOOKUP(_xlfn.CONCAT('Players Full'!AK10,'Players Full'!BV10),'Players Summarised'!$A$1:$T$1000,20,0) -> DEF | C10: =VLOOKUP('Players Full'!CF10,Teams!$A$1:$G$21,6,0) -> Arsenal | D10: ='Players Full'!BD10/10 -> 5.5 | E10: =IFERROR(VLOOKUP($A10,'Starting Lineups'!$A$2:$C$510,3,FALSE),0) -> 0 | F10: =VLOOKUP(A10,'Score & Assist'!$A$1:$G$2000,6,0) -> 0.10025063 | G10: =IF(F10<0.3, 0.01,IF(F10=0.3,0.03,IF(F10<0.5,0.05,IF(F10<0.55,0.06,IF(F10<0.57,0.1,IF(F10<0.58,0.11,IF(F10<0.59,0.12,IF(F10<0.6,0.15,0.28)))))))) -> 0.01 | H10: =IF(F10<0.3,0,IF(F10<0.55,0.01,IF(F10<0.59,0.02,IF(F10<0.6,0.03,0.11)))) -> 0 | I10: =VLOOKUP(A10,'Score & Assist'!$A$1:$G$2000,7,0) -> 0.10582011 | J10: =VLOOKUP(A10,'Yellow Card'!$C$1:$E$987,3,0) -> 0.13605442 | K10: =VLOOKUP(C10,'Team Clean Sheet'!$C$2:$F$21,4,0) -> 0.5 | L10: =VLOOKUP(C10,'Team Total Goals'!$D$2:$N$21,10,0) -> 0.17168675 | M10: =VLOOKUP(C10,'Team Total Goals'!$D$2:$N$21,11,0) -> 0.01926849 | N10: =VLOOKUP(A10,'Goalkeeper Saves'!$D$2:$N$15,10,0) -> #N/A | O10: =VLOOKUP(A10,'Goalkeeper Saves'!$D$2:$N$15,11,0) -> #N/A | P10: =IF(B10="DEF",IFERROR(VLOOKUP(A10,'Defensive Contribution - DEF'!A10:H506,8,FALSE),'Defensive Contribution - DEF'!K$2),0) -> 0.22344252 | Q10: =IF(B10="MID",IFERROR(VLOOKUP(A10,'Defensive Contribution - MID'!A$2:I$500,9,FALSE),'Defensive Contribution - MID'!L$2),0) -> 0 | R10: =IFERROR(IFERROR(E10,0)*IF(B10="GK",2+IFERROR(F10*10,0)+IFERROR(G10*10,0)+IFERROR(H10*10,0)+IFERROR(I10*3,0)-IFERROR(J10*1,0)+IFERROR(K10*4,0)+IFERROR(N10*1,0)+IFERROR(O10*1,0)-IFERROR(L10*2,0)-IFERROR(M10*2,0),IF(B10="DEF",2+IFERROR(F10*6,0)+IFERROR(G10*6,0)+IFERROR(H10*6,0)+IFERROR(I10*3,0)-IFERROR(J10*1,0)+IFERROR(K10*4,0)-IFERROR(L10*2,0)-IFERROR(M10*2,0)+IFERROR(P10*2,0),IF(B10="MID",2+IFERROR(F10*5,0)+IFERROR(G10*5,0)+IFERROR(H10*5,0)+IFERROR(I10*3,0)-IFERROR(J10*1,0)+IFERROR(K10*1,0)+IFERROR(Q10*2,0),IF(B10="FWD",2+IFERROR(F10*4,0)+IFERROR(G10*4,0)+IFERROR(H10*4,0)+IFERROR(I10*3,0)-IFERROR(J10*1,0),"ERROR")))),0) -> 0 | S10: =MAX(0, MIN(1, -0.021039 + 0.023522 * R10)) -> 0 | T10: =R10+S10*2 -> 0 | U10: =VLOOKUP($C10,'Team Fixtures'!$A$2:$Q$21,2,FALSE) -> 0.88924459 | V10: =VLOOKUP($C10,'Team Fixtures'!$A$2:$Q$21,4,FALSE) -> 0.028011204 | W10: =VLOOKUP($C10,'Team Fixtures'!$A$2:$Q$21,5,FALSE) -> 0.86123338 | X10: =VLOOKUP($C10,'Team Fixtures'!$A$2:$Q$21,6,FALSE) -> H | Y10: =R10/(2.926+0.578*U10-0.576*V10-0.561*W10+0.469*IF(X10="H",1,0)) -> 0 | Z10: =VLOOKUP($C10,'Team Fixtures'!$A$2:$Q$21,2,FALSE) -> 0.88924459 | AA10: =VLOOKUP($C10,'Team Fixtures'!$A$2:$Q$21,8,FALSE) -> 0.89678056 | AB10: =VLOOKUP($C10,'Team Fixtures'!$A$2:$Q$21,9,FALSE) -> -0.0075359711 | AC10: =VLOOKUP($C10,'Team Fixtures'!$A$2:$Q$21,10,FALSE) -> A | AD10: =IFERROR((2.926+0.578*Z10-0.576*AA10-0.561*AB10+0.469*IF(AC10="H",1,0))*$Y10,0) -> 0 | AE10: =MAX(0, MIN(1, -0.021039 + 0.023522 * AD10)) -> 0 | AF10: =AD10+AE10*2 -> 0 | AG10: =VLOOKUP($C10,'Team Fixtures'!$A$2:$Q$21,2,FALSE) -> 0.88924459 | AH10: =VLOOKUP($C10,'Team Fixtures'!$A$2:$Q$21,12,FALSE) -> 0.10582011 | AI10: =VLOOKUP($C10,'Team Fixtures'!$A$2:$Q$21,13,FALSE) -> 0.78342448 | AJ10: =VLOOKUP($C10,'Team Fixtures'!$A$2:$Q$21,14,FALSE) -> H | AK10: =IFERROR((2.926+0.578*AG10-0.576*AH10-0.561*AI10+0.469*IF(AJ10="H",1,0))*$Y10,0) -> 0 | AL10: =MAX(0, MIN(1, -0.021039 + 0.023522 * AK10)) -> 0 | AM10: =AK10+AL10*2 -> 0 | AN10: =VLOOKUP($C10,'Team Fixtures'!$A$2:$Q$21,2,FALSE) -> 0.88924459 | AO10: =VLOOKUP($C10,'Team Fixtures'!$A$2:$Q$21,16,FALSE) -> 0.87939146 | AP10: =VLOOKUP($C10,'Team Fixtures'!$A$2:$Q$21,17,FALSE) -> 0.0098531256 | AQ10: =VLOOKUP($C10,'Team Fixtures'!$A$2:$V$21,18,FALSE) -> H | AR10: =IFERROR((2.926+0.578*AN10-0.576*AO10-0.561*AP10+0.469*IF(AQ10="H",1,0))*$Y10,0) -> 0 | AS10: =MAX(0, MIN(1, -0.021039 + 0.023522 * AR10)) -> 0 | AT10: =AR10+AS10*2 -> 0 | AU10: =VLOOKUP($C10,'Team Fixtures'!$A$2:$Q$21,2,FALSE) -> 0.88924459 | AV10: =VLOOKUP($C10,'Team Fixtures'!$A$2:$V$21,20,FALSE) -> 0.50125313 | AW10: =VLOOKUP($C10,'Team Fixtures'!$A$2:$V$21,21,FALSE) -> 0.38799145 | AX10: =VLOOKUP($C10,'Team Fixtures'!$A$2:$V$21,22,FALSE) -> A | AY10: =IFERROR((2.926+0.578*AU10-0.576*AV10-0.561*AW10+0.469*IF(AX10="H",1,0))*$Y10,0) -> 0 | AZ10: =MAX(0, MIN(1, -0.021039 + 0.023522 * AY10)) -> 0 | BA10: =AY10+AZ10*2 -> 0 | BB10: =IFERROR(T10*1+AF10*0.85+AM10*0.7+AT10*0.55+BA10*0.4,0) -> 0
A11: ='Players Full'!CU11 -> Myles Lewis-Skelly | B11: =VLOOKUP(_xlfn.CONCAT('Players Full'!AK11,'Players Full'!BV11),'Players Summarised'!$A$1:$T$1000,20,0) -> DEF | C11: =VLOOKUP('Players Full'!CF11,Teams!$A$1:$G$21,6,0) -> Arsenal | D11: ='Players Full'!BD11/10 -> 5.5 | E11: =IFERROR(VLOOKUP($A11,'Starting Lineups'!$A$2:$C$510,3,FALSE),0) -> 1 | F11: =VLOOKUP(A11,'Score & Assist'!$A$1:$G$2000,6,0) -> 0.13605442 | G11: =IF(F11<0.3, 0.01,IF(F11=0.3,0.03,IF(F11<0.5,0.05,IF(F11<0.55,0.06,IF(F11<0.57,0.1,IF(F11<0.58,0.11,IF(F11<0.59,0.12,IF(F11<0.6,0.15,0.28)))))))) -> 0.01 | H11: =IF(F11<0.3,0,IF(F11<0.55,0.01,IF(F11<0.59,0.02,IF(F11<0.6,0.03,0.11)))) -> 0 | I11: =VLOOKUP(A11,'Score & Assist'!$A$1:$G$2000,7,0) -> 0.095238095 | J11: =VLOOKUP(A11,'Yellow Card'!$C$1:$E$987,3,0) -> 0.17316017 | K11: =VLOOKUP(C11,'Team Clean Sheet'!$C$2:$F$21,4,0) -> 0.5 | L11: =VLOOKUP(C11,'Team Total Goals'!$D$2:$N$21,10,0) -> 0.17168675 | M11: =VLOOKUP(C11,'Team Total Goals'!$D$2:$N$21,11,0) -> 0.01926849 | N11: =VLOOKUP(A11,'Goalkeeper Saves'!$D$2:$N$15,10,0) -> #N/A | O11: =VLOOKUP(A11,'Goalkeeper Saves'!$D$2:$N$15,11,0) -> #N/A | P11: =IF(B11="DEF",IFERROR(VLOOKUP(A11,'Defensive Contribution - DEF'!A11:H507,8,FALSE),'Defensive Contribution - DEF'!K$2),0) -> 0.013437179 | Q11: =IF(B11="MID",IFERROR(VLOOKUP(A11,'Defensive Contribution - MID'!A$2:I$500,9,FALSE),'Defensive Contribution - MID'!L$2),0) -> 0 | R11: =IFERROR(IFERROR(E11,0)*IF(B11="GK",2+IFERROR(F11*10,0)+IFERROR(G11*10,0)+IFERROR(H11*10,0)+IFERROR(I11*3,0)-IFERROR(J11*1,0)+IFERROR(K11*4,0)+IFERROR(N11*1,0)+IFERROR(O11*1,0)-IFERROR(L11*2,0)-IFERROR(M11*2,0),IF(B11="DEF",2+IFERROR(F11*6,0)+IFERROR(G11*6,0)+IFERROR(H11*6,0)+IFERROR(I11*3,0)-IFERROR(J11*1,0)+IFERROR(K11*4,0)-IFERROR(L11*2,0)-IFERROR(M11*2,0)+IFERROR(P11*2,0),IF(B11="MID",2+IFERROR(F11*5,0)+IFERROR(G11*5,0)+IFERROR(H11*5,0)+IFERROR(I11*3,0)-IFERROR(J11*1,0)+IFERROR(K11*1,0)+IFERROR(Q11*2,0),IF(B11="FWD",2+IFERROR(F11*4,0)+IFERROR(G11*4,0)+IFERROR(H11*4,0)+IFERROR(I11*3,0)-IFERROR(J11*1,0),"ERROR")))),0) -> 4.6338445 | S11: =MAX(0, MIN(1, -0.021039 + 0.023522 * R11)) -> 0.087958291 | T11: =R11+S11*2 -> 4.8097611 | U11: =VLOOKUP($C11,'Team Fixtures'!$A$2:$Q$21,2,FALSE) -> 0.88924459 | V11: =VLOOKUP($C11,'Team Fixtures'!$A$2:$Q$21,4,FALSE) -> 0.028011204 | W11: =VLOOKUP($C11,'Team Fixtures'!$A$2:$Q$21,5,FALSE) -> 0.86123338 | X11: =VLOOKUP($C11,'Team Fixtures'!$A$2:$Q$21,6,FALSE) -> H | Y11: =R11/(2.926+0.578*U11-0.576*V11-0.561*W11+0.469*IF(X11="H",1,0)) -> 1.3590194 | Z11: =VLOOKUP($C11,'Team Fixtures'!$A$2:$Q$21,2,FALSE) -> 0.88924459 | AA11: =VLOOKUP($C11,'Team Fixtures'!$A$2:$Q$21,8,FALSE) -> 0.89678056 | AB11: =VLOOKUP($C11,'Team Fixtures'!$A$2:$Q$21,9,FALSE) -> -0.0075359711 | AC11: =VLOOKUP($C11,'Team Fixtures'!$A$2:$Q$21,10,FALSE) -> A | AD11: =IFERROR((2.926+0.578*Z11-0.576*AA11-0.561*AB11+0.469*IF(AC11="H",1,0))*$Y11,0) -> 3.9787543 | AE11: =MAX(0, MIN(1, -0.021039 + 0.023522 * AD11)) -> 0.072549258 | AF11: =AD11+AE11*2 -> 4.1238528 | AG11: =VLOOKUP($C11,'Team Fixtures'!$A$2:$Q$21,2,FALSE) -> 0.88924459 | AH11: =VLOOKUP($C11,'Team Fixtures'!$A$2:$Q$21,12,FALSE) -> 0.10582011 | AI11: =VLOOKUP($C11,'Team Fixtures'!$A$2:$Q$21,13,FALSE) -> 0.78342448 | AJ11: =VLOOKUP($C11,'Team Fixtures'!$A$2:$Q$21,14,FALSE) -> H | AK11: =IFERROR((2.926+0.578*AG11-0.576*AH11-0.561*AI11+0.469*IF(AJ11="H",1,0))*$Y11,0) -> 4.6322584 | AL11: =MAX(0, MIN(1, -0.021039 + 0.023522 * AK11)) -> 0.087920981 | AM11: =AK11+AL11*2 -> 4.8081003 | AN11: =VLOOKUP($C11,'Team Fixtures'!$A$2:$Q$21,2,FALSE) -> 0.88924459 | AO11: =VLOOKUP($C11,'Team Fixtures'!$A$2:$Q$21,16,FALSE) -> 0.87939146 | AP11: =VLOOKUP($C11,'Team Fixtures'!$A$2:$Q$21,17,FALSE) -> 0.0098531256 | AQ11: =VLOOKUP($C11,'Team Fixtures'!$A$2:$V$21,18,FALSE) -> H | AR11: =IFERROR((2.926+0.578*AN11-0.576*AO11-0.561*AP11+0.469*IF(AQ11="H",1,0))*$Y11,0) -> 4.6164889 | AS11: =MAX(0, MIN(1, -0.021039 + 0.023522 * AR11)) -> 0.087550052 | AT11: =AR11+AS11*2 -> 4.791589 | AU11: =VLOOKUP($C11,'Team Fixtures'!$A$2:$Q$21,2,FALSE) -> 0.88924459 | AV11: =VLOOKUP($C11,'Team Fixtures'!$A$2:$V$21,20,FALSE) -> 0.50125313 | AW11: =VLOOKUP($C11,'Team Fixtures'!$A$2:$V$21,21,FALSE) -> 0.38799145 | AX11: =VLOOKUP($C11,'Team Fixtures'!$A$2:$V$21,22,FALSE) -> A | AY11: =IFERROR((2.926+0.578*AU11-0.576*AV11-0.561*AW11+0.469*IF(AX11="H",1,0))*$Y11,0) -> 3.9868172 | AZ11: =MAX(0, MIN(1, -0.021039 + 0.023522 * AY11)) -> 0.072738915 | BA11: =AY11+AZ11*2 -> 4.1322951 | BB11: =IFERROR(T11*1+AF11*0.85+AM11*0.7+AT11*0.55+BA11*0.4,0) -> 15.968998
A12: ='Players Full'!CU12 -> Ben White | B12: =VLOOKUP(_xlfn.CONCAT('Players Full'!AK12,'Players Full'!BV12),'Players Summarised'!$A$1:$T$1000,20,0) -> DEF | C12: =VLOOKUP('Players Full'!CF12,Teams!$A$1:$G$21,6,0) -> Arsenal | D12: ='Players Full'!BD12/10 -> 5.5 | E12: =IFERROR(VLOOKUP($A12,'Starting Lineups'!$A$2:$C$510,3,FALSE),0) -> 1 | F12: =VLOOKUP(A12,'Score & Assist'!$A$1:$G$2000,6,0) -> 0.10025063 | G12: =IF(F12<0.3, 0.01,IF(F12=0.3,0.03,IF(F12<0.5,0.05,IF(F12<0.55,0.06,IF(F12<0.57,0.1,IF(F12<0.58,0.11,IF(F12<0.59,0.12,IF(F12<0.6,0.15,0.28)))))))) -> 0.01 | H12: =IF(F12<0.3,0,IF(F12<0.55,0.01,IF(F12<0.59,0.02,IF(F12<0.6,0.03,0.11)))) -> 0 | I12: =VLOOKUP(A12,'Score & Assist'!$A$1:$G$2000,7,0) -> 0.11904762 | J12: =VLOOKUP(A12,'Yellow Card'!$C$1:$E$987,3,0) -> 0.14652015 | K12: =VLOOKUP(C12,'Team Clean Sheet'!$C$2:$F$21,4,0) -> 0.5 | L12: =VLOOKUP(C12,'Team Total Goals'!$D$2:$N$21,10,0) -> 0.17168675 | M12: =VLOOKUP(C12,'Team Total Goals'!$D$2:$N$21,11,0) -> 0.01926849 | N12: =VLOOKUP(A12,'Goalkeeper Saves'!$D$2:$N$15,10,0) -> #N/A | O12: =VLOOKUP(A12,'Goalkeeper Saves'!$D$2:$N$15,11,0) -> #N/A | P12: =IF(B12="DEF",IFERROR(VLOOKUP(A12,'Defensive Contribution - DEF'!A12:H508,8,FALSE),'Defensive Contribution - DEF'!K$2),0) -> 0.11854733 | Q12: =IF(B12="MID",IFERROR(VLOOKUP(A12,'Defensive Contribution - MID'!A$2:I$500,9,FALSE),'Defensive Contribution - MID'!L$2),0) -> 0 | R12: =IFERROR(IFERROR(E12,0)*IF(B12="GK",2+IFERROR(F12*10,0)+IFERROR(G12*10,0)+IFERROR(H12*10,0)+IFERROR(I12*3,0)-IFERROR(J12*1,0)+IFERROR(K12*4,0)+IFERROR(N12*1,0)+IFERROR(O12*1,0)-IFERROR(L12*2,0)-IFERROR(M12*2,0),IF(B12="DEF",2+IFERROR(F12*6,0)+IFERROR(G12*6,0)+IFERROR(H12*6,0)+IFERROR(I12*3,0)-IFERROR(J12*1,0)+IFERROR(K12*4,0)-IFERROR(L12*2,0)-IFERROR(M12*2,0)+IFERROR(P12*2,0),IF(B12="MID",2+IFERROR(F12*5,0)+IFERROR(G12*5,0)+IFERROR(H12*5,0)+IFERROR(I12*3,0)-IFERROR(J12*1,0)+IFERROR(K12*1,0)+IFERROR(Q12*2,0),IF(B12="FWD",2+IFERROR(F12*4,0)+IFERROR(G12*4,0)+IFERROR(H12*4,0)+IFERROR(I12*3,0)-IFERROR(J12*1,0),"ERROR")))),0) -> 4.7273107 | S12: =MAX(0, MIN(1, -0.021039 + 0.023522 * R12)) -> 0.090156801 | T12: =R12+S12*2 -> 4.9076243 | U12: =VLOOKUP($C12,'Team Fixtures'!$A$2:$Q$21,2,FALSE) -> 0.88924459 | V12: =VLOOKUP($C12,'Team Fixtures'!$A$2:$Q$21,4,FALSE) -> 0.028011204 | W12: =VLOOKUP($C12,'Team Fixtures'!$A$2:$Q$21,5,FALSE) -> 0.86123338 | X12: =VLOOKUP($C12,'Team Fixtures'!$A$2:$Q$21,6,FALSE) -> H | Y12: =R12/(2.926+0.578*U12-0.576*V12-0.561*W12+0.469*IF(X12="H",1,0)) -> 1.3864313 | Z12: =VLOOKUP($C12,'Team Fixtures'!$A$2:$Q$21,2,FALSE) -> 0.88924459 | AA12: =VLOOKUP($C12,'Team Fixtures'!$A$2:$Q$21,8,FALSE) -> 0.89678056 | AB12: =VLOOKUP($C12,'Team Fixtures'!$A$2:$Q$21,9,FALSE) -> -0.0075359711 | AC12: =VLOOKUP($C12,'Team Fixtures'!$A$2:$Q$21,10,FALSE) -> A | AD12: =IFERROR((2.926+0.578*Z12-0.576*AA12-0.561*AB12+0.469*IF(AC12="H",1,0))*$Y12,0) -> 4.059007 | AE12: =MAX(0, MIN(1, -0.021039 + 0.023522 * AD12)) -> 0.074436964 | AF12: =AD12+AE12*2 -> 4.207881 | AG12: =VLOOKUP($C12,'Team Fixtures'!$A$2:$Q$21,2,FALSE) -> 0.88924459 | AH12: =VLOOKUP($C12,'Team Fixtures'!$A$2:$Q$21,12,FALSE) -> 0.10582011 | AI12: =VLOOKUP($C12,'Team Fixtures'!$A$2:$Q$21,13,FALSE) -> 0.78342448 | AJ12: =VLOOKUP($C12,'Team Fixtures'!$A$2:$Q$21,14,FALSE) -> H | AK12: =IFERROR((2.926+0.578*AG12-0.576*AH12-0.561*AI12+0.469*IF(AJ12="H",1,0))*$Y12,0) -> 4.7256925 | AL12: =MAX(0, MIN(1, -0.021039 + 0.023522 * AK12)) -> 0.090118739 | AM12: =AK12+AL12*2 -> 4.90593 | AN12: =VLOOKUP($C12,'Team Fixtures'!$A$2:$Q$21,2,FALSE) -> 0.88924459 | AO12: =VLOOKUP($C12,'Team Fixtures'!$A$2:$Q$21,16,FALSE) -> 0.87939146 | AP12: =VLOOKUP($C12,'Team Fixtures'!$A$2:$Q$21,17,FALSE) -> 0.0098531256 | AQ12: =VLOOKUP($C12,'Team Fixtures'!$A$2:$V$21,18,FALSE) -> H | AR12: =IFERROR((2.926+0.578*AN12-0.576*AO12-0.561*AP12+0.469*IF(AQ12="H",1,0))*$Y12,0) -> 4.709605 | AS12: =MAX(0, MIN(1, -0.021039 + 0.023522 * AR12)) -> 0.089740328 | AT12: =AR12+AS12*2 -> 4.8890856 | AU12: =VLOOKUP($C12,'Team Fixtures'!$A$2:$Q$21,2,FALSE) -> 0.88924459 | AV12: =VLOOKUP($C12,'Team Fixtures'!$A$2:$V$21,20,FALSE) -> 0.50125313 | AW12: =VLOOKUP($C12,'Team Fixtures'!$A$2:$V$21,21,FALSE) -> 0.38799145 | AX12: =VLOOKUP($C12,'Team Fixtures'!$A$2:$V$21,22,FALSE) -> A | AY12: =IFERROR((2.926+0.578*AU12-0.576*AV12-0.561*AW12+0.469*IF(AX12="H",1,0))*$Y12,0) -> 4.0672326 | AZ12: =MAX(0, MIN(1, -0.021039 + 0.023522 * AY12)) -> 0.074630446 | BA12: =AY12+AZ12*2 -> 4.2164935 | BB12: =IFERROR(T12*1+AF12*0.85+AM12*0.7+AT12*0.55+BA12*0.4,0) -> 16.294069
A13: ='Players Full'!CU13 -> Oleksandr Zinchenko | B13: =VLOOKUP(_xlfn.CONCAT('Players Full'!AK13,'Players Full'!BV13),'Players Summarised'!$A$1:$T$1000,20,0) -> DEF | C13: =VLOOKUP('Players Full'!CF13,Teams!$A$1:$G$21,6,0) -> Arsenal | D13: ='Players Full'!BD13/10 -> 5 | E13: =IFERROR(VLOOKUP($A13,'Starting Lineups'!$A$2:$C$510,3,FALSE),0) -> 0 | F13: =VLOOKUP(A13,'Score & Assist'!$A$1:$G$2000,6,0) -> 0.15873016 | G13: =IF(F13<0.3, 0.01,IF(F13=0.3,0.03,IF(F13<0.5,0.05,IF(F13<0.55,0.06,IF(F13<0.57,0.1,IF(F13<0.58,0.11,IF(F13<0.59,0.12,IF(F13<0.6,0.15,0.28)))))))) -> 0.01 | H13: =IF(F13<0.3,0,IF(F13<0.55,0.01,IF(F13<0.59,0.02,IF(F13<0.6,0.03,0.11)))) -> 0 | I13: =VLOOKUP(A13,'Score & Assist'!$A$1:$G$2000,7,0) -> 0.11904762 | J13: =VLOOKUP(A13,'Yellow Card'!$C$1:$E$987,3,0) -> 0.11204482 | K13: =VLOOKUP(C13,'Team Clean Sheet'!$C$2:$F$21,4,0) -> 0.5 | L13: =VLOOKUP(C13,'Team Total Goals'!$D$2:$N$21,10,0) -> 0.17168675 | M13: =VLOOKUP(C13,'Team Total Goals'!$D$2:$N$21,11,0) -> 0.01926849 | N13: =VLOOKUP(A13,'Goalkeeper Saves'!$D$2:$N$15,10,0) -> #N/A | O13: =VLOOKUP(A13,'Goalkeeper Saves'!$D$2:$N$15,11,0) -> #N/A | P13: =IF(B13="DEF",IFERROR(VLOOKUP(A13,'Defensive Contribution - DEF'!A13:H509,8,FALSE),'Defensive Contribution - DEF'!K$2),0) -> 0.2915234 | Q13: =IF(B13="MID",IFERROR(VLOOKUP(A13,'Defensive Contribution - MID'!A$2:I$500,9,FALSE),'Defensive Contribution - MID'!L$2),0) -> 0 | R13: =IFERROR(IFERROR(E13,0)*IF(B13="GK",2+IFERROR(F13*10,0)+IFERROR(G13*10,0)+IFERROR(H13*10,0)+IFERROR(I13*3,0)-IFERROR(J13*1,0)+IFERROR(K13*4,0)+IFERROR(N13*1,0)+IFERROR(O13*1,0)-IFERROR(L13*2,0)-IFERROR(M13*2,0),IF(B13="DEF",2+IFERROR(F13*6,0)+IFERROR(G13*6,0)+IFERROR(H13*6,0)+IFERROR(I13*3,0)-IFERROR(J13*1,0)+IFERROR(K13*4,0)-IFERROR(L13*2,0)-IFERROR(M13*2,0)+IFERROR(P13*2,0),IF(B13="MID",2+IFERROR(F13*5,0)+IFERROR(G13*5,0)+IFERROR(H13*5,0)+IFERROR(I13*3,0)-IFERROR(J13*1,0)+IFERROR(K13*1,0)+IFERROR(Q13*2,0),IF(B13="FWD",2+IFERROR(F13*4,0)+IFERROR(G13*4,0)+IFERROR(H13*4,0)+IFERROR(I13*3,0)-IFERROR(J13*1,0),"ERROR")))),0) -> 0 | S13: =MAX(0, MIN(1, -0.021039 + 0.023522 * R13)) -> 0 | T13: =R13+S13*2 -> 0 | U13: =VLOOKUP($C13,'Team Fixtures'!$A$2:$Q$21,2,FALSE) -> 0.88924459 | V13: =VLOOKUP($C13,'Team Fixtures'!$A$2:$Q$21,4,FALSE) -> 0.028011204 | W13: =VLOOKUP($C13,'Team Fixtures'!$A$2:$Q$21,5,FALSE) -> 0.86123338 | X13: =VLOOKUP($C13,'Team Fixtures'!$A$2:$Q$21,6,FALSE) -> H | Y13: =R13/(2.926+0.578*U13-0.576*V13-0.561*W13+0.469*IF(X13="H",1,0)) -> 0 | Z13: =VLOOKUP($C13,'Team Fixtures'!$A$2:$Q$21,2,FALSE) -> 0.88924459 | AA13: =VLOOKUP($C13,'Team Fixtures'!$A$2:$Q$21,8,FALSE) -> 0.89678056 | AB13: =VLOOKUP($C13,'Team Fixtures'!$A$2:$Q$21,9,FALSE) -> -0.0075359711 | AC13: =VLOOKUP($C13,'Team Fixtures'!$A$2:$Q$21,10,FALSE) -> A | AD13: =IFERROR((2.926+0.578*Z13-0.576*AA13-0.561*AB13+0.469*IF(AC13="H",1,0))*$Y13,0) -> 0 | AE13: =MAX(0, MIN(1, -0.021039 + 0.023522 * AD13)) -> 0 | AF13: =AD13+AE13*2 -> 0 | AG13: =VLOOKUP($C13,'Team Fixtures'!$A$2:$Q$21,2,FALSE) -> 0.88924459 | AH13: =VLOOKUP($C13,'Team Fixtures'!$A$2:$Q$21,12,FALSE) -> 0.10582011 | AI13: =VLOOKUP($C13,'Team Fixtures'!$A$2:$Q$21,13,FALSE) -> 0.78342448 | AJ13: =VLOOKUP($C13,'Team Fixtures'!$A$2:$Q$21,14,FALSE) -> H | AK13: =IFERROR((2.926+0.578*AG13-0.576*AH13-0.561*AI13+0.469*IF(AJ13="H",1,0))*$Y13,0) -> 0 | AL13: =MAX(0, MIN(1, -0.021039 + 0.023522 * AK13)) -> 0 | AM13: =AK13+AL13*2 -> 0 | AN13: =VLOOKUP($C13,'Team Fixtures'!$A$2:$Q$21,2,FALSE) -> 0.88924459 | AO13: =VLOOKUP($C13,'Team Fixtures'!$A$2:$Q$21,16,FALSE) -> 0.87939146 | AP13: =VLOOKUP($C13,'Team Fixtures'!$A$2:$Q$21,17,FALSE) -> 0.0098531256 | AQ13: =VLOOKUP($C13,'Team Fixtures'!$A$2:$V$21,18,FALSE) -> H | AR13: =IFERROR((2.926+0.578*AN13-0.576*AO13-0.561*AP13+0.469*IF(AQ13="H",1,0))*$Y13,0) -> 0 | AS13: =MAX(0, MIN(1, -0.021039 + 0.023522 * AR13)) -> 0 | AT13: =AR13+AS13*2 -> 0 | AU13: =VLOOKUP($C13,'Team Fixtures'!$A$2:$Q$21,2,FALSE) -> 0.88924459 | AV13: =VLOOKUP($C13,'Team Fixtures'!$A$2:$V$21,20,FALSE) -> 0.50125313 | AW13: =VLOOKUP($C13,'Team Fixtures'!$A$2:$V$21,21,FALSE) -> 0.38799145 | AX13: =VLOOKUP($C13,'Team Fixtures'!$A$2:$V$21,22,FALSE) -> A | AY13: =IFERROR((2.926+0.578*AU13-0.576*AV13-0.561*AW13+0.469*IF(AX13="H",1,0))*$Y13,0) -> 0 | AZ13: =MAX(0, MIN(1, -0.021039 + 0.023522 * AY13)) -> 0 | BA13: =AY13+AZ13*2 -> 0 | BB13: =IFERROR(T13*1+AF13*0.85+AM13*0.7+AT13*0.55+BA13*0.4,0) -> 0
... A57: ='Players Full'!CU57 -> John McGinn | B57: =VLOOKUP(_xlfn.CONCAT('Players Full'!AK57,'Players Full'!BV57),'Players Summarised'!$A$1:$T$1000,20,0) -> MID | C57: =VLOOKUP('Players Full'!CF57,Teams!$A$1:$G$21,6,0) -> Aston Villa | D57: ='Players Full'!BD57/10 -> 5.5 | E57: =IFERROR(VLOOKUP($A57,'Starting Lineups'!$A$2:$C$510,3,FALSE),0) -> 1 | F57: =VLOOKUP(A57,'Score & Assist'!$A$1:$G$2000,6,0) -> 0.19047619 | G57: =IF(F57<0.3, 0.01,IF(F57=0.3,0.03,IF(F57<0.5,0.05,IF(F57<0.55,0.06,IF(F57<0.57,0.1,IF(F57<0.58,0.11,IF(F57<0.59,0.12,IF(F57<0.6,0.15,0.28)))))))) -> 0.01 | H57: =IF(F57<0.3,0,IF(F57<0.55,0.01,IF(F57<0.59,0.02,IF(F57<0.6,0.03,0.11)))) -> 0 | I57: =VLOOKUP(A57,'Score & Assist'!$A$1:$G$2000,7,0) -> 0.11904762 | J57: =VLOOKUP(A57,'Yellow Card'!$C$1:$E$987,3,0) -> 0.31746032 | K57: =VLOOKUP(C57,'Team Clean Sheet'!$C$2:$F$21,4,0) -> 0.29039301 | L57: =VLOOKUP(C57,'Team Total Goals'!$D$2:$N$21,10,0) -> 0.3546798 | M57: =VLOOKUP(C57,'Team Total Goals'!$D$2:$N$21,11,0) -> 0.050949051 | N57: =VLOOKUP(A57,'Goalkeeper Saves'!$D$2:$N$15,10,0) -> #N/A | O57: =VLOOKUP(A57,'Goalkeeper Saves'!$D$2:$N$15,11,0) -> #N/A | P57: =IF(B57="DEF",IFERROR(VLOOKUP(A57,'Defensive Contribution - DEF'!A57:H553,8,FALSE),'Defensive Contribution - DEF'!K$2),0) -> 0 | Q57: =IF(B57="MID",IFERROR(VLOOKUP(A57,'Defensive Contribution - MID'!A$2:I$500,9,FALSE),'Defensive Contribution - MID'!L$2),0) -> 0.38575005 | R57: =IFERROR(IFERROR(E57,0)*IF(B57="GK",2+IFERROR(F57*10,0)+IFERROR(G57*10,0)+IFERROR(H57*10,0)+IFERROR(I57*3,0)-IFERROR(J57*1,0)+IFERROR(K57*4,0)+IFERROR(N57*1,0)+IFERROR(O57*1,0)-IFERROR(L57*2,0)-IFERROR(M57*2,0),IF(B57="DEF",2+IFERROR(F57*6,0)+IFERROR(G57*6,0)+IFERROR(H57*6,0)+IFERROR(I57*3,0)-IFERROR(J57*1,0)+IFERROR(K57*4,0)-IFERROR(L57*2,0)-IFERROR(M57*2,0)+IFERROR(P57*2,0),IF(B57="MID",2+IFERROR(F57*5,0)+IFERROR(G57*5,0)+IFERROR(H57*5,0)+IFERROR(I57*3,0)-IFERROR(J57*1,0)+IFERROR(K57*1,0)+IFERROR(Q57*2,0),IF(B57="FWD",2+IFERROR(F57*4,0)+IFERROR(G57*4,0)+IFERROR(H57*4,0)+IFERROR(I57*3,0)-IFERROR(J57*1,0),"ERROR")))),0) -> 4.1039566 | S57: =MAX(0, MIN(1, -0.021039 + 0.023522 * R57)) -> 0.075494267 | T57: =R57+S57*2 -> 4.2549451 | U57: =VLOOKUP($C57,'Team Fixtures'!$A$2:$Q$21,2,FALSE) -> 0.42328042 | V57: =VLOOKUP($C57,'Team Fixtures'!$A$2:$Q$21,4,FALSE) -> 0.056022409 | W57: =VLOOKUP($C57,'Team Fixtures'!$A$2:$Q$21,5,FALSE) -> 0.36725801 | X57: =VLOOKUP($C57,'Team Fixtures'!$A$2:$Q$21,6,FALSE) -> A | Y57: =R57/(2.926+0.578*U57-0.576*V57-0.561*W57+0.469*IF(X57="H",1,0)) -> 1.3995427 | Z57: =VLOOKUP($C57,'Team Fixtures'!$A$2:$Q$21,2,FALSE) -> 0.42328042 | AA57: =VLOOKUP($C57,'Team Fixtures'!$A$2:$Q$21,8,FALSE) -> 0.10582011 | AB57: =VLOOKUP($C57,'Team Fixtures'!$A$2:$Q$21,9,FALSE) -> 0.31746032 | AC57: =VLOOKUP($C57,'Team Fixtures'!$A$2:$Q$21,10,FALSE) -> H | AD57: =IFERROR((2.926+0.578*Z57-0.576*AA57-0.561*AB57+0.469*IF(AC57="H",1,0))*$Y57,0) -> 4.7592967 | AE57: =MAX(0, MIN(1, -0.021039 + 0.023522 * AD57)) -> 0.090909177 | AF57: =AD57+AE57*2 -> 4.9411151 | AG57: =VLOOKUP($C57,'Team Fixtures'!$A$2:$Q$21,2,FALSE) -> 0.42328042 | AH57: =VLOOKUP($C57,'Team Fixtures'!$A$2:$Q$21,12,FALSE) -> 0.086580087 | AI57: =VLOOKUP($C57,'Team Fixtures'!$A$2:$Q$21,13,FALSE) -> 0.33670034 | AJ57: =VLOOKUP($C57,'Team Fixtures'!$A$2:$Q$21,14,FALSE) -> H | AK57: =IFERROR((2.926+0.578*AG57-0.576*AH57-0.561*AI57+0.469*IF(AJ57="H",1,0))*$Y57,0) -> 4.7597006 | AL57: =MAX(0, MIN(1, -0.021039 + 0.023522 * AK57)) -> 0.090918678 | AM57: =AK57+AL57*2 -> 4.941538 | AN57: =VLOOKUP($C57,'Team Fixtures'!$A$2:$Q$21,2,FALSE) -> 0.42328042 | AO57: =VLOOKUP($C57,'Team Fixtures'!$A$2:$Q$21,16,FALSE) -> 0.018674136 | AP57: =VLOOKUP($C57,'Team Fixtures'!$A$2:$Q$21,17,FALSE) -> 0.40460629 | AQ57: =VLOOKUP($C57,'Team Fixtures'!$A$2:$V$21,18,FALSE) -> A | AR57: =IFERROR((2.926+0.578*AN57-0.576*AO57-0.561*AP57+0.469*IF(AQ57="H",1,0))*$Y57,0) -> 4.1047407 | AS57: =MAX(0, MIN(1, -0.021039 + 0.023522 * AR57)) -> 0.07551271 | AT57: =AR57+AS57*2 -> 4.2557661 | AU57: =VLOOKUP($C57,'Team Fixtures'!$A$2:$Q$21,2,FALSE) -> 0.42328042 | AV57: =VLOOKUP($C57,'Team Fixtures'!$A$2:$V$21,20,FALSE) -> 0.063492063 | AW57: =VLOOKUP($C57,'Team Fixtures'!$A$2:$V$21,21,FALSE) -> 0.35978836 | AX57: =VLOOKUP($C57,'Team Fixtures'!$A$2:$V$21,22,FALSE) -> H | AY57: =IFERROR((2.926+0.578*AU57-0.576*AV57-0.561*AW57+0.469*IF(AX57="H",1,0))*$Y57,0) -> 4.7601853 | AZ57: =MAX(0, MIN(1, -0.021039 + 0.023522 * AY57)) -> 0.090930079 | BA57: =AY57+AZ57*2 -> 4.9420455 | BB57: =IFERROR(T57*1+AF57*0.85+AM57*0.7+AT57*0.55+BA57*0.4,0) -> 16.231459
A58: ='Players Full'!CU58 -> Ross Barkley | B58: =VLOOKUP(_xlfn.CONCAT('Players Full'!AK58,'Players Full'!BV58),'Players Summarised'!$A$1:$T$1000,20,0) -> MID | C58: =VLOOKUP('Players Full'!CF58,Teams!$A$1:$G$21,6,0) -> Aston Villa | D58: ='Players Full'!BD58/10 -> 5 | E58: =IFERROR(VLOOKUP($A58,'Starting Lineups'!$A$2:$C$510,3,FALSE),0) -> 0 | F58: =VLOOKUP(A58,'Score & Assist'!$A$1:$G$2000,6,0) -> 0.19047619 | G58: =IF(F58<0.3, 0.01,IF(F58=0.3,0.03,IF(F58<0.5,0.05,IF(F58<0.55,0.06,IF(F58<0.57,0.1,IF(F58<0.58,0.11,IF(F58<0.59,0.12,IF(F58<0.6,0.15,0.28)))))))) -> 0.01 | H58: =IF(F58<0.3,0,IF(F58<0.55,0.01,IF(F58<0.59,0.02,IF(F58<0.6,0.03,0.11)))) -> 0 | I58: =VLOOKUP(A58,'Score & Assist'!$A$1:$G$2000,7,0) -> 0.14652015 | J58: =VLOOKUP(A58,'Yellow Card'!$C$1:$E$987,3,0) -> 0.26455026 | K58: =VLOOKUP(C58,'Team Clean Sheet'!$C$2:$F$21,4,0) -> 0.29039301 | L58: =VLOOKUP(C58,'Team Total Goals'!$D$2:$N$21,10,0) -> 0.3546798 | M58: =VLOOKUP(C58,'Team Total Goals'!$D$2:$N$21,11,0) -> 0.050949051 | N58: =VLOOKUP(A58,'Goalkeeper Saves'!$D$2:$N$15,10,0) -> #N/A | O58: =VLOOKUP(A58,'Goalkeeper Saves'!$D$2:$N$15,11,0) -> #N/A | P58: =IF(B58="DEF",IFERROR(VLOOKUP(A58,'Defensive Contribution - DEF'!A57:H554,8,FALSE),'Defensive Contribution - DEF'!K$2),0) -> 0 | Q58: =IF(B58="MID",IFERROR(VLOOKUP(A58,'Defensive Contribution - MID'!A$2:I$500,9,FALSE),'Defensive Contribution - MID'!L$2),0) -> 0.52892439 | R58: =IFERROR(IFERROR(E58,0)*IF(B58="GK",2+IFERROR(F58*10,0)+IFERROR(G58*10,0)+IFERROR(H58*10,0)+IFERROR(I58*3,0)-IFERROR(J58*1,0)+IFERROR(K58*4,0)+IFERROR(N58*1,0)+IFERROR(O58*1,0)-IFERROR(L58*2,0)-IFERROR(M58*2,0),IF(B58="DEF",2+IFERROR(F58*6,0)+IFERROR(G58*6,0)+IFERROR(H58*6,0)+IFERROR(I58*3,0)-IFERROR(J58*1,0)+IFERROR(K58*4,0)-IFERROR(L58*2,0)-IFERROR(M58*2,0)+IFERROR(P58*2,0),IF(B58="MID",2+IFERROR(F58*5,0)+IFERROR(G58*5,0)+IFERROR(H58*5,0)+IFERROR(I58*3,0)-IFERROR(J58*1,0)+IFERROR(K58*1,0)+IFERROR(Q58*2,0),IF(B58="FWD",2+IFERROR(F58*4,0)+IFERROR(G58*4,0)+IFERROR(H58*4,0)+IFERROR(I58*3,0)-IFERROR(J58*1,0),"ERROR")))),0) -> 0 | S58: =MAX(0, MIN(1, -0.021039 + 0.023522 * R58)) -> 0 | T58: =R58+S58*2 -> 0 | U58: =VLOOKUP($C58,'Team Fixtures'!$A$2:$Q$21,2,FALSE) -> 0.42328042 | V58: =VLOOKUP($C58,'Team Fixtures'!$A$2:$Q$21,4,FALSE) -> 0.056022409 | W58: =VLOOKUP($C58,'Team Fixtures'!$A$2:$Q$21,5,FALSE) -> 0.36725801 | X58: =VLOOKUP($C58,'Team Fixtures'!$A$2:$Q$21,6,FALSE) -> A | Y58: =R58/(2.926+0.578*U58-0.576*V58-0.561*W58+0.469*IF(X58="H",1,0)) -> 0 | Z58: =VLOOKUP($C58,'Team Fixtures'!$A$2:$Q$21,2,FALSE) -> 0.42328042 | AA58: =VLOOKUP($C58,'Team Fixtures'!$A$2:$Q$21,8,FALSE) -> 0.10582011 | AB58: =VLOOKUP($C58,'Team Fixtures'!$A$2:$Q$21,9,FALSE) -> 0.31746032 | AC58: =VLOOKUP($C58,'Team Fixtures'!$A$2:$Q$21,10,FALSE) -> H | AD58: =IFERROR((2.926+0.578*Z58-0.576*AA58-0.561*AB58+0.469*IF(AC58="H",1,0))*$Y58,0) -> 0 | AE58: =MAX(0, MIN(1, -0.021039 + 0.023522 * AD58)) -> 0 | AF58: =AD58+AE58*2 -> 0 | AG58: =VLOOKUP($C58,'Team Fixtures'!$A$2:$Q$21,2,FALSE) -> 0.42328042 | AH58: =VLOOKUP($C58,'Team Fixtures'!$A$2:$Q$21,12,FALSE) -> 0.086580087 | AI58: =VLOOKUP($C58,'Team Fixtures'!$A$2:$Q$21,13,FALSE) -> 0.33670034 | AJ58: =VLOOKUP($C58,'Team Fixtures'!$A$2:$Q$21,14,FALSE) -> H | AK58: =IFERROR((2.926+0.578*AG58-0.576*AH58-0.561*AI58+0.469*IF(AJ58="H",1,0))*$Y58,0) -> 0 | AL58: =MAX(0, MIN(1, -0.021039 + 0.023522 * AK58)) -> 0 | AM58: =AK58+AL58*2 -> 0 | AN58: =VLOOKUP($C58,'Team Fixtures'!$A$2:$Q$21,2,FALSE) -> 0.42328042 | AO58: =VLOOKUP($C58,'Team Fixtures'!$A$2:$Q$21,16,FALSE) -> 0.018674136 | AP58: =VLOOKUP($C58,'Team Fixtures'!$A$2:$Q$21,17,FALSE) -> 0.40460629 | AQ58: =VLOOKUP($C58,'Team Fixtures'!$A$2:$V$21,18,FALSE) -> A | AR58: =IFERROR((2.926+0.578*AN58-0.576*AO58-0.561*AP58+0.469*IF(AQ58="H",1,0))*$Y58,0) -> 0 | AS58: =MAX(0, MIN(1, -0.021039 + 0.023522 * AR58)) -> 0 | AT58: =AR58+AS58*2 -> 0 | AU58: =VLOOKUP($C58,'Team Fixtures'!$A$2:$Q$21,2,FALSE) -> 0.42328042 | AV58: =VLOOKUP($C58,'Team Fixtures'!$A$2:$V$21,20,FALSE) -> 0.063492063 | AW58: =VLOOKUP($C58,'Team Fixtures'!$A$2:$V$21,21,FALSE) -> 0.35978836 | AX58: =VLOOKUP($C58,'Team Fixtures'!$A$2:$V$21,22,FALSE) -> H | AY58: =IFERROR((2.926+0.578*AU58-0.576*AV58-0.561*AW58+0.469*IF(AX58="H",1,0))*$Y58,0) -> 0 | AZ58: =MAX(0, MIN(1, -0.021039 + 0.023522 * AY58)) -> 0 | BA58: =AY58+AZ58*2 -> 0 | BB58: =IFERROR(T58*1+AF58*0.85+AM58*0.7+AT58*0.55+BA58*0.4,0) -> 0
A59: ='Players Full'!CU59 -> Enzo Barrenechea | B59: =VLOOKUP(_xlfn.CONCAT('Players Full'!AK59,'Players Full'!BV59),'Players Summarised'!$A$1:$T$1000,20,0) -> MID | C59: =VLOOKUP('Players Full'!CF59,Teams!$A$1:$G$21,6,0) -> Aston Villa | D59: ='Players Full'!BD59/10 -> 5 | E59: =IFERROR(VLOOKUP($A59,'Starting Lineups'!$A$2:$C$510,3,FALSE),0) -> 0 | F59: =VLOOKUP(A59,'Score & Assist'!$A$1:$G$2000,6,0) -> #N/A | G59: =IF(F59<0.3, 0.01,IF(F59=0.3,0.03,IF(F59<0.5,0.05,IF(F59<0.55,0.06,IF(F59<0.57,0.1,IF(F59<0.58,0.11,IF(F59<0.59,0.12,IF(F59<0.6,0.15,0.28)))))))) -> #N/A | H59: =IF(F59<0.3,0,IF(F59<0.55,0.01,IF(F59<0.59,0.02,IF(F59<0.6,0.03,0.11)))) -> #N/A | I59: =VLOOKUP(A59,'Score & Assist'!$A$1:$G$2000,7,0) -> #N/A | J59: =VLOOKUP(A59,'Yellow Card'!$C$1:$E$987,3,0) -> #N/A | K59: =VLOOKUP(C59,'Team Clean Sheet'!$C$2:$F$21,4,0) -> 0.29039301 | L59: =VLOOKUP(C59,'Team Total Goals'!$D$2:$N$21,10,0) -> 0.3546798 | M59: =VLOOKUP(C59,'Team Total Goals'!$D$2:$N$21,11,0) -> 0.050949051 | N59: =VLOOKUP(A59,'Goalkeeper Saves'!$D$2:$N$15,10,0) -> #N/A | O59: =VLOOKUP(A59,'Goalkeeper Saves'!$D$2:$N$15,11,0) -> #N/A | P59: =IF(B59="DEF",IFERROR(VLOOKUP(A59,'Defensive Contribution - DEF'!A57:H555,8,FALSE),'Defensive Contribution - DEF'!K$2),0) -> 0 | Q59: =IF(B59="MID",IFERROR(VLOOKUP(A59,'Defensive Contribution - MID'!A$2:I$500,9,FALSE),'Defensive Contribution - MID'!L$2),0) -> 0.38575005 | R59: =IFERROR(IFERROR(E59,0)*IF(B59="GK",2+IFERROR(F59*10,0)+IFERROR(G59*10,0)+IFERROR(H59*10,0)+IFERROR(I59*3,0)-IFERROR(J59*1,0)+IFERROR(K59*4,0)+IFERROR(N59*1,0)+IFERROR(O59*1,0)-IFERROR(L59*2,0)-IFERROR(M59*2,0),IF(B59="DEF",2+IFERROR(F59*6,0)+IFERROR(G59*6,0)+IFERROR(H59*6,0)+IFERROR(I59*3,0)-IFERROR(J59*1,0)+IFERROR(K59*4,0)-IFERROR(L59*2,0)-IFERROR(M59*2,0)+IFERROR(P59*2,0),IF(B59="MID",2+IFERROR(F59*5,0)+IFERROR(G59*5,0)+IFERROR(H59*5,0)+IFERROR(I59*3,0)-IFERROR(J59*1,0)+IFERROR(K59*1,0)+IFERROR(Q59*2,0),IF(B59="FWD",2+IFERROR(F59*4,0)+IFERROR(G59*4,0)+IFERROR(H59*4,0)+IFERROR(I59*3,0)-IFERROR(J59*1,0),"ERROR")))),0) -> 0 | S59: =MAX(0, MIN(1, -0.021039 + 0.023522 * R59)) -> 0 | T59: =R59+S59*2 -> 0 | U59: =VLOOKUP($C59,'Team Fixtures'!$A$2:$Q$21,2,FALSE) -> 0.42328042 | V59: =VLOOKUP($C59,'Team Fixtures'!$A$2:$Q$21,4,FALSE) -> 0.056022409 | W59: =VLOOKUP($C59,'Team Fixtures'!$A$2:$Q$21,5,FALSE) -> 0.36725801 | X59: =VLOOKUP($C59,'Team Fixtures'!$A$2:$Q$21,6,FALSE) -> A | Y59: =R59/(2.926+0.578*U59-0.576*V59-0.561*W59+0.469*IF(X59="H",1,0)) -> 0 | Z59: =VLOOKUP($C59,'Team Fixtures'!$A$2:$Q$21,2,FALSE) -> 0.42328042 | AA59: =VLOOKUP($C59,'Team Fixtures'!$A$2:$Q$21,8,FALSE) -> 0.10582011 | AB59: =VLOOKUP($C59,'Team Fixtures'!$A$2:$Q$21,9,FALSE) -> 0.31746032 | AC59: =VLOOKUP($C59,'Team Fixtures'!$A$2:$Q$21,10,FALSE) -> H | AD59: =IFERROR((2.926+0.578*Z59-0.576*AA59-0.561*AB59+0.469*IF(AC59="H",1,0))*$Y59,0) -> 0 | AE59: =MAX(0, MIN(1, -0.021039 + 0.023522 * AD59)) -> 0 | AF59: =AD59+AE59*2 -> 0 | AG59: =VLOOKUP($C59,'Team Fixtures'!$A$2:$Q$21,2,FALSE) -> 0.42328042 | AH59: =VLOOKUP($C59,'Team Fixtures'!$A$2:$Q$21,12,FALSE) -> 0.086580087 | AI59: =VLOOKUP($C59,'Team Fixtures'!$A$2:$Q$21,13,FALSE) -> 0.33670034 | AJ59: =VLOOKUP($C59,'Team Fixtures'!$A$2:$Q$21,14,FALSE) -> H | AK59: =IFERROR((2.926+0.578*AG59-0.576*AH59-0.561*AI59+0.469*IF(AJ59="H",1,0))*$Y59,0) -> 0 | AL59: =MAX(0, MIN(1, -0.021039 + 0.023522 * AK59)) -> 0 | AM59: =AK59+AL59*2 -> 0 | AN59: =VLOOKUP($C59,'Team Fixtures'!$A$2:$Q$21,2,FALSE) -> 0.42328042 | AO59: =VLOOKUP($C59,'Team Fixtures'!$A$2:$Q$21,16,FALSE) -> 0.018674136 | AP59: =VLOOKUP($C59,'Team Fixtures'!$A$2:$Q$21,17,FALSE) -> 0.40460629 | AQ59: =VLOOKUP($C59,'Team Fixtures'!$A$2:$V$21,18,FALSE) -> A | AR59: =IFERROR((2.926+0.578*AN59-0.576*AO59-0.561*AP59+0.469*IF(AQ59="H",1,0))*$Y59,0) -> 0 | AS59: =MAX(0, MIN(1, -0.021039 + 0.023522 * AR59)) -> 0 | AT59: =AR59+AS59*2 -> 0 | AU59: =VLOOKUP($C59,'Team Fixtures'!$A$2:$Q$21,2,FALSE) -> 0.42328042 | AV59: =VLOOKUP($C59,'Team Fixtures'!$A$2:$V$21,20,FALSE) -> 0.063492063 | AW59: =VLOOKUP($C59,'Team Fixtures'!$A$2:$V$21,21,FALSE) -> 0.35978836 | AX59: =VLOOKUP($C59,'Team Fixtures'!$A$2:$V$21,22,FALSE) -> H | AY59: =IFERROR((2.926+0.578*AU59-0.576*AV59-0.561*AW59+0.469*IF(AX59="H",1,0))*$Y59,0) -> 0 | AZ59: =MAX(0, MIN(1, -0.021039 + 0.023522 * AY59)) -> 0 | BA59: =AY59+AZ59*2 -> 0 | BB59: =IFERROR(T59*1+AF59*0.85+AM59*0.7+AT59*0.55+BA59*0.4,0) -> 0
A60: ='Players Full'!CU60 -> Lewis Dobbin | B60: =VLOOKUP(_xlfn.CONCAT('Players Full'!AK60,'Players Full'!BV60),'Players Summarised'!$A$1:$T$1000,20,0) -> MID | C60: =VLOOKUP('Players Full'!CF60,Teams!$A$1:$G$21,6,0) -> Aston Villa | D60: ='Players Full'!BD60/10 -> 5 | E60: =IFERROR(VLOOKUP($A60,'Starting Lineups'!$A$2:$C$510,3,FALSE),0) -> 0 | F60: =VLOOKUP(A60,'Score & Assist'!$A$1:$G$2000,6,0) -> 0.27210884 | G60: =IF(F60<0.3, 0.01,IF(F60=0.3,0.03,IF(F60<0.5,0.05,IF(F60<0.55,0.06,IF(F60<0.57,0.1,IF(F60<0.58,0.11,IF(F60<0.59,0.12,IF(F60<0.6,0.15,0.28)))))))) -> 0.01 | H60: =IF(F60<0.3,0,IF(F60<0.55,0.01,IF(F60<0.59,0.02,IF(F60<0.6,0.03,0.11)))) -> 0 | I60: =VLOOKUP(A60,'Score & Assist'!$A$1:$G$2000,7,0) -> 0.13605442 | J60: =VLOOKUP(A60,'Yellow Card'!$C$1:$E$987,3,0) -> 0.23809524 | K60: =VLOOKUP(C60,'Team Clean Sheet'!$C$2:$F$21,4,0) -> 0.29039301 | L60: =VLOOKUP(C60,'Team Total Goals'!$D$2:$N$21,10,0) -> 0.3546798 | M60: =VLOOKUP(C60,'Team Total Goals'!$D$2:$N$21,11,0) -> 0.050949051 | N60: =VLOOKUP(A60,'Goalkeeper Saves'!$D$2:$N$15,10,0) -> #N/A | O60: =VLOOKUP(A60,'Goalkeeper Saves'!$D$2:$N$15,11,0) -> #N/A | P60: =IF(B60="DEF",IFERROR(VLOOKUP(A60,'Defensive Contribution - DEF'!A58:H556,8,FALSE),'Defensive Contribution - DEF'!K$2),0) -> 0 | Q60: =IF(B60="MID",IFERROR(VLOOKUP(A60,'Defensive Contribution - MID'!A$2:I$500,9,FALSE),'Defensive Contribution - MID'!L$2),0) -> 0.38575005 | R60: =IFERROR(IFERROR(E60,0)*IF(B60="GK",2+IFERROR(F60*10,0)+IFERROR(G60*10,0)+IFERROR(H60*10,0)+IFERROR(I60*3,0)-IFERROR(J60*1,0)+IFERROR(K60*4,0)+IFERROR(N60*1,0)+IFERROR(O60*1,0)-IFERROR(L60*2,0)-IFERROR(M60*2,0),IF(B60="DEF",2+IFERROR(F60*6,0)+IFERROR(G60*6,0)+IFERROR(H60*6,0)+IFERROR(I60*3,0)-IFERROR(J60*1,0)+IFERROR(K60*4,0)-IFERROR(L60*2,0)-IFERROR(M60*2,0)+IFERROR(P60*2,0),IF(B60="MID",2+IFERROR(F60*5,0)+IFERROR(G60*5,0)+IFERROR(H60*5,0)+IFERROR(I60*3,0)-IFERROR(J60*1,0)+IFERROR(K60*1,0)+IFERROR(Q60*2,0),IF(B60="FWD",2+IFERROR(F60*4,0)+IFERROR(G60*4,0)+IFERROR(H60*4,0)+IFERROR(I60*3,0)-IFERROR(J60*1,0),"ERROR")))),0) -> 0 | S60: =MAX(0, MIN(1, -0.021039 + 0.023522 * R60)) -> 0 | T60: =R60+S60*2 -> 0 | U60: =VLOOKUP($C60,'Team Fixtures'!$A$2:$Q$21,2,FALSE) -> 0.42328042 | V60: =VLOOKUP($C60,'Team Fixtures'!$A$2:$Q$21,4,FALSE) -> 0.056022409 | W60: =VLOOKUP($C60,'Team Fixtures'!$A$2:$Q$21,5,FALSE) -> 0.36725801 | X60: =VLOOKUP($C60,'Team Fixtures'!$A$2:$Q$21,6,FALSE) -> A | Y60: =R60/(2.926+0.578*U60-0.576*V60-0.561*W60+0.469*IF(X60="H",1,0)) -> 0 | Z60: =VLOOKUP($C60,'Team Fixtures'!$A$2:$Q$21,2,FALSE) -> 0.42328042 | AA60: =VLOOKUP($C60,'Team Fixtures'!$A$2:$Q$21,8,FALSE) -> 0.10582011 | AB60: =VLOOKUP($C60,'Team Fixtures'!$A$2:$Q$21,9,FALSE) -> 0.31746032 | AC60: =VLOOKUP($C60,'Team Fixtures'!$A$2:$Q$21,10,FALSE) -> H | AD60: =IFERROR((2.926+0.578*Z60-0.576*AA60-0.561*AB60+0.469*IF(AC60="H",1,0))*$Y60,0) -> 0 | AE60: =MAX(0, MIN(1, -0.021039 + 0.023522 * AD60)) -> 0 | AF60: =AD60+AE60*2 -> 0 | AG60: =VLOOKUP($C60,'Team Fixtures'!$A$2:$Q$21,2,FALSE) -> 0.42328042 | AH60: =VLOOKUP($C60,'Team Fixtures'!$A$2:$Q$21,12,FALSE) -> 0.086580087 | AI60: =VLOOKUP($C60,'Team Fixtures'!$A$2:$Q$21,13,FALSE) -> 0.33670034 | AJ60: =VLOOKUP($C60,'Team Fixtures'!$A$2:$Q$21,14,FALSE) -> H | AK60: =IFERROR((2.926+0.578*AG60-0.576*AH60-0.561*AI60+0.469*IF(AJ60="H",1,0))*$Y60,0) -> 0 | AL60: =MAX(0, MIN(1, -0.021039 + 0.023522 * AK60)) -> 0 | AM60: =AK60+AL60*2 -> 0 | AN60: =VLOOKUP($C60,'Team Fixtures'!$A$2:$Q$21,2,FALSE) -> 0.42328042 | AO60: =VLOOKUP($C60,'Team Fixtures'!$A$2:$Q$21,16,FALSE) -> 0.018674136 | AP60: =VLOOKUP($C60,'Team Fixtures'!$A$2:$Q$21,17,FALSE) -> 0.40460629 | AQ60: =VLOOKUP($C60,'Team Fixtures'!$A$2:$V$21,18,FALSE) -> A | AR60: =IFERROR((2.926+0.578*AN60-0.576*AO60-0.561*AP60+0.469*IF(AQ60="H",1,0))*$Y60,0) -> 0 | AS60: =MAX(0, MIN(1, -0.021039 + 0.023522 * AR60)) -> 0 | AT60: =AR60+AS60*2 -> 0 | AU60: =VLOOKUP($C60,'Team Fixtures'!$A$2:$Q$21,2,FALSE) -> 0.42328042 | AV60: =VLOOKUP($C60,'Team Fixtures'!$A$2:$V$21,20,FALSE) -> 0.063492063 | AW60: =VLOOKUP($C60,'Team Fixtures'!$A$2:$V$21,21,FALSE) -> 0.35978836 | AX60: =VLOOKUP($C60,'Team Fixtures'!$A$2:$V$21,22,FALSE) -> H | AY60: =IFERROR((2.926+0.578*AU60-0.576*AV60-0.561*AW60+0.469*IF(AX60="H",1,0))*$Y60,0) -> 0 | AZ60: =MAX(0, MIN(1, -0.021039 + 0.023522 * AY60)) -> 0 | BA60: =AY60+AZ60*2 -> 0 | BB60: =IFERROR(T60*1+AF60*0.85+AM60*0.7+AT60*0.55+BA60*0.4,0) -> 0
A61: ='Players Full'!CU61 -> Boubacar Kamara | B61: =VLOOKUP(_xlfn.CONCAT('Players Full'!AK61,'Players Full'!BV61),'Players Summarised'!$A$1:$T$1000,20,0) -> MID | C61: =VLOOKUP('Players Full'!CF61,Teams!$A$1:$G$21,6,0) -> Aston Villa | D61: ='Players Full'!BD61/10 -> 5 | E61: =IFERROR(VLOOKUP($A61,'Starting Lineups'!$A$2:$C$510,3,FALSE),0) -> 1 | F61: =VLOOKUP(A61,'Score & Assist'!$A$1:$G$2000,6,0) -> 0.086580087 | G61: =IF(F61<0.3, 0.01,IF(F61=0.3,0.03,IF(F61<0.5,0.05,IF(F61<0.55,0.06,IF(F61<0.57,0.1,IF(F61<0.58,0.11,IF(F61<0.59,0.12,IF(F61<0.6,0.15,0.28)))))))) -> 0.01 | H61: =IF(F61<0.3,0,IF(F61<0.55,0.01,IF(F61<0.59,0.02,IF(F61<0.6,0.03,0.11)))) -> 0 | I61: =VLOOKUP(A61,'Score & Assist'!$A$1:$G$2000,7,0) -> 0.086580087 | J61: =VLOOKUP(A61,'Yellow Card'!$C$1:$E$987,3,0) -> 0.36630037 | K61: =VLOOKUP(C61,'Team Clean Sheet'!$C$2:$F$21,4,0) -> 0.29039301 | L61: =VLOOKUP(C61,'Team Total Goals'!$D$2:$N$21,10,0) -> 0.3546798 | M61: =VLOOKUP(C61,'Team Total Goals'!$D$2:$N$21,11,0) -> 0.050949051 | N61: =VLOOKUP(A61,'Goalkeeper Saves'!$D$2:$N$15,10,0) -> #N/A | O61: =VLOOKUP(A61,'Goalkeeper Saves'!$D$2:$N$15,11,0) -> #N/A | P61: =IF(B61="DEF",IFERROR(VLOOKUP(A61,'Defensive Contribution - DEF'!A59:H557,8,FALSE),'Defensive Contribution - DEF'!K$2),0) -> 0 | Q61: =IF(B61="MID",IFERROR(VLOOKUP(A61,'Defensive Contribution - MID'!A$2:I$500,9,FALSE),'Defensive Contribution - MID'!L$2),0) -> 0.48562874 | R61: =IFERROR(IFERROR(E61,0)*IF(B61="GK",2+IFERROR(F61*10,0)+IFERROR(G61*10,0)+IFERROR(H61*10,0)+IFERROR(I61*3,0)-IFERROR(J61*1,0)+IFERROR(K61*4,0)+IFERROR(N61*1,0)+IFERROR(O61*1,0)-IFERROR(L61*2,0)-IFERROR(M61*2,0),IF(B61="DEF",2+IFERROR(F61*6,0)+IFERROR(G61*6,0)+IFERROR(H61*6,0)+IFERROR(I61*3,0)-IFERROR(J61*1,0)+IFERROR(K61*4,0)-IFERROR(L61*2,0)-IFERROR(M61*2,0)+IFERROR(P61*2,0),IF(B61="MID",2+IFERROR(F61*5,0)+IFERROR(G61*5,0)+IFERROR(H61*5,0)+IFERROR(I61*3,0)-IFERROR(J61*1,0)+IFERROR(K61*1,0)+IFERROR(Q61*2,0),IF(B61="FWD",2+IFERROR(F61*4,0)+IFERROR(G61*4,0)+IFERROR(H61*4,0)+IFERROR(I61*3,0)-IFERROR(J61*1,0),"ERROR")))),0) -> 3.6379908 | S61: =MAX(0, MIN(1, -0.021039 + 0.023522 * R61)) -> 0.06453382 | T61: =R61+S61*2 -> 3.7670585 | U61: =VLOOKUP($C61,'Team Fixtures'!$A$2:$Q$21,2,FALSE) -> 0.42328042 | V61: =VLOOKUP($C61,'Team Fixtures'!$A$2:$Q$21,4,FALSE) -> 0.056022409 | W61: =VLOOKUP($C61,'Team Fixtures'!$A$2:$Q$21,5,FALSE) -> 0.36725801 | X61: =VLOOKUP($C61,'Team Fixtures'!$A$2:$Q$21,6,FALSE) -> A | Y61: =R61/(2.926+0.578*U61-0.576*V61-0.561*W61+0.469*IF(X61="H",1,0)) -> 1.2406377 | Z61: =VLOOKUP($C61,'Team Fixtures'!$A$2:$Q$21,2,FALSE) -> 0.42328042 | AA61: =VLOOKUP($C61,'Team Fixtures'!$A$2:$Q$21,8,FALSE) -> 0.10582011 | AB61: =VLOOKUP($C61,'Team Fixtures'!$A$2:$Q$21,9,FALSE) -> 0.31746032 | AC61: =VLOOKUP($C61,'Team Fixtures'!$A$2:$Q$21,10,FALSE) -> H | AD61: =IFERROR((2.926+0.578*Z61-0.576*AA61-0.561*AB61+0.469*IF(AC61="H",1,0))*$Y61,0) -> 4.2189232 | AE61: =MAX(0, MIN(1, -0.021039 + 0.023522 * AD61)) -> 0.078198512 | AF61: =AD61+AE61*2 -> 4.3753202 | AG61: =VLOOKUP($C61,'Team Fixtures'!$A$2:$Q$21,2,FALSE) -> 0.42328042 | AH61: =VLOOKUP($C61,'Team Fixtures'!$A$2:$Q$21,12,FALSE) -> 0.086580087 | AI61: =VLOOKUP($C61,'Team Fixtures'!$A$2:$Q$21,13,FALSE) -> 0.33670034 | AJ61: =VLOOKUP($C61,'Team Fixtures'!$A$2:$Q$21,14,FALSE) -> H | AK61: =IFERROR((2.926+0.578*AG61-0.576*AH61-0.561*AI61+0.469*IF(AJ61="H",1,0))*$Y61,0) -> 4.2192813 | AL61: =MAX(0, MIN(1, -0.021039 + 0.023522 * AK61)) -> 0.078206934 | AM61: =AK61+AL61*2 -> 4.3756951 | AN61: =VLOOKUP($C61,'Team Fixtures'!$A$2:$Q$21,2,FALSE) -> 0.42328042 | AO61: =VLOOKUP($C61,'Team Fixtures'!$A$2:$Q$21,16,FALSE) -> 0.018674136 | AP61: =VLOOKUP($C61,'Team Fixtures'!$A$2:$Q$21,17,FALSE) -> 0.40460629 | AQ61: =VLOOKUP($C61,'Team Fixtures'!$A$2:$V$21,18,FALSE) -> A | AR61: =IFERROR((2.926+0.578*AN61-0.576*AO61-0.561*AP61+0.469*IF(AQ61="H",1,0))*$Y61,0) -> 3.6386859 | AS61: =MAX(0, MIN(1, -0.021039 + 0.023522 * AR61)) -> 0.064550169 | AT61: =AR61+AS61*2 -> 3.7677862 | AU61: =VLOOKUP($C61,'Team Fixtures'!$A$2:$Q$21,2,FALSE) -> 0.42328042 | AV61: =VLOOKUP($C61,'Team Fixtures'!$A$2:$V$21,20,FALSE) -> 0.063492063 | AW61: =VLOOKUP($C61,'Team Fixtures'!$A$2:$V$21,21,FALSE) -> 0.35978836 | AX61: =VLOOKUP($C61,'Team Fixtures'!$A$2:$V$21,22,FALSE) -> H | AY61: =IFERROR((2.926+0.578*AU61-0.576*AV61-0.561*AW61+0.469*IF(AX61="H",1,0))*$Y61,0) -> 4.2197109 | AZ61: =MAX(0, MIN(1, -0.021039 + 0.023522 * AY61)) -> 0.07821704 | BA61: =AY61+AZ61*2 -> 4.376145 | BB61: =IFERROR(T61*1+AF61*0.85+AM61*0.7+AT61*0.55+BA61*0.4,0) -> 14.371808
A62: ='Players Full'!CU62 -> Amadou Onana | B62: =VLOOKUP(_xlfn.CONCAT('Players Full'!AK62,'Players Full'!BV62),'Players Summarised'!$A$1:$T$1000,20,0) -> MID | C62: =VLOOKUP('Players Full'!CF62,Teams!$A$1:$G$21,6,0) -> Aston Villa | D62: ='Players Full'!BD62/10 -> 5 | E62: =IFERROR(VLOOKUP($A62,'Starting Lineups'!$A$2:$C$510,3,FALSE),0) -> 1 | F62: =VLOOKUP(A62,'Score & Assist'!$A$1:$G$2000,6,0) -> 0.17316017 | G62: =IF(F62<0.3, 0.01,IF(F62=0.3,0.03,IF(F62<0.5,0.05,IF(F62<0.55,0.06,IF(F62<0.57,0.1,IF(F62<0.58,0.11,IF(F62<0.59,0.12,IF(F62<0.6,0.15,0.28)))))))) -> 0.01 | H62: =IF(F62<0.3,0,IF(F62<0.55,0.01,IF(F62<0.59,0.02,IF(F62<0.6,0.03,0.11)))) -> 0 | I62: =VLOOKUP(A62,'Score & Assist'!$A$1:$G$2000,7,0) -> 0.073260073 | J62: =VLOOKUP(A62,'Yellow Card'!$C$1:$E$987,3,0) -> 0.29761905 | K62: =VLOOKUP(C62,'Team Clean Sheet'!$C$2:$F$21,4,0) -> 0.29039301 | L62: =VLOOKUP(C62,'Team Total Goals'!$D$2:$N$21,10,0) -> 0.3546798 | M62: =VLOOKUP(C62,'Team Total Goals'!$D$2:$N$21,11,0) -> 0.050949051 | N62: =VLOOKUP(A62,'Goalkeeper Saves'!$D$2:$N$15,10,0) -> #N/A | O62: =VLOOKUP(A62,'Goalkeeper Saves'!$D$2:$N$15,11,0) -> #N/A | P62: =IF(B62="DEF",IFERROR(VLOOKUP(A62,'Defensive Contribution - DEF'!A60:H558,8,FALSE),'Defensive Contribution - DEF'!K$2),0) -> 0 | Q62: =IF(B62="MID",IFERROR(VLOOKUP(A62,'Defensive Contribution - MID'!A$2:I$500,9,FALSE),'Defensive Contribution - MID'!L$2),0) -> 0.4791014 | R62: =IFERROR(IFERROR(E62,0)*IF(B62="GK",2+IFERROR(F62*10,0)+IFERROR(G62*10,0)+IFERROR(H62*10,0)+IFERROR(I62*3,0)-IFERROR(J62*1,0)+IFERROR(K62*4,0)+IFERROR(N62*1,0)+IFERROR(O62*1,0)-IFERROR(L62*2,0)-IFERROR(M62*2,0),IF(B62="DEF",2+IFERROR(F62*6,0)+IFERROR(G62*6,0)+IFERROR(H62*6,0)+IFERROR(I62*3,0)-IFERROR(J62*1,0)+IFERROR(K62*4,0)-IFERROR(L62*2,0)-IFERROR(M62*2,0)+IFERROR(P62*2,0),IF(B62="MID",2+IFERROR(F62*5,0)+IFERROR(G62*5,0)+IFERROR(H62*5,0)+IFERROR(I62*3,0)-IFERROR(J62*1,0)+IFERROR(K62*1,0)+IFERROR(Q62*2,0),IF(B62="FWD",2+IFERROR(F62*4,0)+IFERROR(G62*4,0)+IFERROR(H62*4,0)+IFERROR(I62*3,0)-IFERROR(J62*1,0),"ERROR")))),0) -> 4.0865578 | S62: =MAX(0, MIN(1, -0.021039 + 0.023522 * R62)) -> 0.075085014 | T62: =R62+S62*2 -> 4.2367279 | U62: =VLOOKUP($C62,'Team Fixtures'!$A$2:$Q$21,2,FALSE) -> 0.42328042 | V62: =VLOOKUP($C62,'Team Fixtures'!$A$2:$Q$21,4,FALSE) -> 0.056022409 | W62: =VLOOKUP($C62,'Team Fixtures'!$A$2:$Q$21,5,FALSE) -> 0.36725801 | X62: =VLOOKUP($C62,'Team Fixtures'!$A$2:$Q$21,6,FALSE) -> A | Y62: =R62/(2.926+0.578*U62-0.576*V62-0.561*W62+0.469*IF(X62="H",1,0)) -> 1.3936093 | Z62: =VLOOKUP($C62,'Team Fixtures'!$A$2:$Q$21,2,FALSE) -> 0.42328042 | AA62: =VLOOKUP($C62,'Team Fixtures'!$A$2:$Q$21,8,FALSE) -> 0.10582011 | AB62: =VLOOKUP($C62,'Team Fixtures'!$A$2:$Q$21,9,FALSE) -> 0.31746032 | AC62: =VLOOKUP($C62,'Team Fixtures'!$A$2:$Q$21,10,FALSE) -> H | AD62: =IFERROR((2.926+0.578*Z62-0.576*AA62-0.561*AB62+0.469*IF(AC62="H",1,0))*$Y62,0) -> 4.7391196 | AE62: =MAX(0, MIN(1, -0.021039 + 0.023522 * AD62)) -> 0.090434572 | AF62: =AD62+AE62*2 -> 4.9199888 | AG62: =VLOOKUP($C62,'Team Fixtures'!$A$2:$Q$21,2,FALSE) -> 0.42328042 | AH62: =VLOOKUP($C62,'Team Fixtures'!$A$2:$Q$21,12,FALSE) -> 0.086580087 | AI62: =VLOOKUP($C62,'Team Fixtures'!$A$2:$Q$21,13,FALSE) -> 0.33670034 | AJ62: =VLOOKUP($C62,'Team Fixtures'!$A$2:$Q$21,14,FALSE) -> H | AK62: =IFERROR((2.926+0.578*AG62-0.576*AH62-0.561*AI62+0.469*IF(AJ62="H",1,0))*$Y62,0) -> 4.7395218 | AL62: =MAX(0, MIN(1, -0.021039 + 0.023522 * AK62)) -> 0.090444033 | AM62: =AK62+AL62*2 -> 4.9204099 | AN62: =VLOOKUP($C62,'Team Fixtures'!$A$2:$Q$21,2,FALSE) -> 0.42328042 | AO62: =VLOOKUP($C62,'Team Fixtures'!$A$2:$Q$21,16,FALSE) -> 0.018674136 | AP62: =VLOOKUP($C62,'Team Fixtures'!$A$2:$Q$21,17,FALSE) -> 0.40460629 | AQ62: =VLOOKUP($C62,'Team Fixtures'!$A$2:$V$21,18,FALSE) -> A | AR62: =IFERROR((2.926+0.578*AN62-0.576*AO62-0.561*AP62+0.469*IF(AQ62="H",1,0))*$Y62,0) -> 4.0873386 | AS62: =MAX(0, MIN(1, -0.021039 + 0.023522 * AR62)) -> 0.075103378 | AT62: =AR62+AS62*2 -> 4.2375453 | AU62: =VLOOKUP($C62,'Team Fixtures'!$A$2:$Q$21,2,FALSE) -> 0.42328042 | AV62: =VLOOKUP($C62,'Team Fixtures'!$A$2:$V$21,20,FALSE) -> 0.063492063 | AW62: =VLOOKUP($C62,'Team Fixtures'!$A$2:$V$21,21,FALSE) -> 0.35978836 | AX62: =VLOOKUP($C62,'Team Fixtures'!$A$2:$V$21,22,FALSE) -> H | AY62: =IFERROR((2.926+0.578*AU62-0.576*AV62-0.561*AW62+0.469*IF(AX62="H",1,0))*$Y62,0) -> 4.7400045 | AZ62: =MAX(0, MIN(1, -0.021039 + 0.023522 * AY62)) -> 0.090455385 | BA62: =AY62+AZ62*2 -> 4.9209152 | BB62: =IFERROR(T62*1+AF62*0.85+AM62*0.7+AT62*0.55+BA62*0.4,0) -> 16.162021
A63: ='Players Full'!CU63 -> Ben Broggio | B63: =VLOOKUP(_xlfn.CONCAT('Players Full'!AK63,'Players Full'!BV63),'Players Summarised'!$A$1:$T$1000,20,0) -> MID | C63: =VLOOKUP('Players Full'!CF63,Teams!$A$1:$G$21,6,0) -> Aston Villa | D63: ='Players Full'!BD63/10 -> 4.5 | E63: =IFERROR(VLOOKUP($A63,'Starting Lineups'!$A$2:$C$510,3,FALSE),0) -> 0 | F63: =VLOOKUP(A63,'Score & Assist'!$A$1:$G$2000,6,0) -> #N/A | G63: =IF(F63<0.3, 0.01,IF(F63=0.3,0.03,IF(F63<0.5,0.05,IF(F63<0.55,0.06,IF(F63<0.57,0.1,IF(F63<0.58,0.11,IF(F63<0.59,0.12,IF(F63<0.6,0.15,0.28)))))))) -> #N/A | H63: =IF(F63<0.3,0,IF(F63<0.55,0.01,IF(F63<0.59,0.02,IF(F63<0.6,0.03,0.11)))) -> #N/A | I63: =VLOOKUP(A63,'Score & Assist'!$A$1:$G$2000,7,0) -> #N/A | J63: =VLOOKUP(A63,'Yellow Card'!$C$1:$E$987,3,0) -> #N/A | K63: =VLOOKUP(C63,'Team Clean Sheet'!$C$2:$F$21,4,0) -> 0.29039301 | L63: =VLOOKUP(C63,'Team Total Goals'!$D$2:$N$21,10,0) -> 0.3546798 | M63: =VLOOKUP(C63,'Team Total Goals'!$D$2:$N$21,11,0) -> 0.050949051 | N63: =VLOOKUP(A63,'Goalkeeper Saves'!$D$2:$N$15,10,0) -> #N/A | O63: =VLOOKUP(A63,'Goalkeeper Saves'!$D$2:$N$15,11,0) -> #N/A | P63: =IF(B63="DEF",IFERROR(VLOOKUP(A63,'Defensive Contribution - DEF'!A61:H559,8,FALSE),'Defensive Contribution - DEF'!K$2),0) -> 0 | Q63: =IF(B63="MID",IFERROR(VLOOKUP(A63,'Defensive Contribution - MID'!A$2:I$500,9,FALSE),'Defensive Contribution - MID'!L$2),0) -> 0.38575005 | R63: =IFERROR(IFERROR(E63,0)*IF(B63="GK",2+IFERROR(F63*10,0)+IFERROR(G63*10,0)+IFERROR(H63*10,0)+IFERROR(I63*3,0)-IFERROR(J63*1,0)+IFERROR(K63*4,0)+IFERROR(N63*1,0)+IFERROR(O63*1,0)-IFERROR(L63*2,0)-IFERROR(M63*2,0),IF(B63="DEF",2+IFERROR(F63*6,0)+IFERROR(G63*6,0)+IFERROR(H63*6,0)+IFERROR(I63*3,0)-IFERROR(J63*1,0)+IFERROR(K63*4,0)-IFERROR(L63*2,0)-IFERROR(M63*2,0)+IFERROR(P63*2,0),IF(B63="MID",2+IFERROR(F63*5,0)+IFERROR(G63*5,0)+IFERROR(H63*5,0)+IFERROR(I63*3,0)-IFERROR(J63*1,0)+IFERROR(K63*1,0)+IFERROR(Q63*2,0),IF(B63="FWD",2+IFERROR(F63*4,0)+IFERROR(G63*4,0)+IFERROR(H63*4,0)+IFERROR(I63*3,0)-IFERROR(J63*1,0),"ERROR")))),0) -> 0 | S63: =MAX(0, MIN(1, -0.021039 + 0.023522 * R63)) -> 0 | T63: =R63+S63*2 -> 0 | U63: =VLOOKUP($C63,'Team Fixtures'!$A$2:$Q$21,2,FALSE) -> 0.42328042 | V63: =VLOOKUP($C63,'Team Fixtures'!$A$2:$Q$21,4,FALSE) -> 0.056022409 | W63: =VLOOKUP($C63,'Team Fixtures'!$A$2:$Q$21,5,FALSE) -> 0.36725801 | X63: =VLOOKUP($C63,'Team Fixtures'!$A$2:$Q$21,6,FALSE) -> A | Y63: =R63/(2.926+0.578*U63-0.576*V63-0.561*W63+0.469*IF(X63="H",1,0)) -> 0 | Z63: =VLOOKUP($C63,'Team Fixtures'!$A$2:$Q$21,2,FALSE) -> 0.42328042 | AA63: =VLOOKUP($C63,'Team Fixtures'!$A$2:$Q$21,8,FALSE) -> 0.10582011 | AB63: =VLOOKUP($C63,'Team Fixtures'!$A$2:$Q$21,9,FALSE) -> 0.31746032 | AC63: =VLOOKUP($C63,'Team Fixtures'!$A$2:$Q$21,10,FALSE) -> H | AD63: =IFERROR((2.926+0.578*Z63-0.576*AA63-0.561*AB63+0.469*IF(AC63="H",1,0))*$Y63,0) -> 0 | AE63: =MAX(0, MIN(1, -0.021039 + 0.023522 * AD63)) -> 0 | AF63: =AD63+AE63*2 -> 0 | AG63: =VLOOKUP($C63,'Team Fixtures'!$A$2:$Q$21,2,FALSE) -> 0.42328042 | AH63: =VLOOKUP($C63,'Team Fixtures'!$A$2:$Q$21,12,FALSE) -> 0.086580087 | AI63: =VLOOKUP($C63,'Team Fixtures'!$A$2:$Q$21,13,FALSE) -> 0.33670034 | AJ63: =VLOOKUP($C63,'Team Fixtures'!$A$2:$Q$21,14,FALSE) -> H | AK63: =IFERROR((2.926+0.578*AG63-0.576*AH63-0.561*AI63+0.469*IF(AJ63="H",1,0))*$Y63,0) -> 0 | AL63: =MAX(0, MIN(1, -0.021039 + 0.023522 * AK63)) -> 0 | AM63: =AK63+AL63*2 -> 0 | AN63: =VLOOKUP($C63,'Team Fixtures'!$A$2:$Q$21,2,FALSE) -> 0.42328042 | AO63: =VLOOKUP($C63,'Team Fixtures'!$A$2:$Q$21,16,FALSE) -> 0.018674136 | AP63: =VLOOKUP($C63,'Team Fixtures'!$A$2:$Q$21,17,FALSE) -> 0.40460629 | AQ63: =VLOOKUP($C63,'Team Fixtures'!$A$2:$V$21,18,FALSE) -> A | AR63: =IFERROR((2.926+0.578*AN63-0.576*AO63-0.561*AP63+0.469*IF(AQ63="H",1,0))*$Y63,0) -> 0 | AS63: =MAX(0, MIN(1, -0.021039 + 0.023522 * AR63)) -> 0 | AT63: =AR63+AS63*2 -> 0 | AU63: =VLOOKUP($C63,'Team Fixtures'!$A$2:$Q$21,2,FALSE) -> 0.42328042 | AV63: =VLOOKUP($C63,'Team Fixtures'!$A$2:$V$21,20,FALSE) -> 0.063492063 | AW63: =VLOOKUP($C63,'Team Fixtures'!$A$2:$V$21,21,FALSE) -> 0.35978836 | AX63: =VLOOKUP($C63,'Team Fixtures'!$A$2:$V$21,22,FALSE) -> H | AY63: =IFERROR((2.926+0.578*AU63-0.576*AV63-0.561*AW63+0.469*IF(AX63="H",1,0))*$Y63,0) -> 0 | AZ63: =MAX(0, MIN(1, -0.021039 + 0.023522 * AY63)) -> 0 | BA63: =AY63+AZ63*2 -> 0 | BB63: =IFERROR(T63*1+AF63*0.85+AM63*0.7+AT63*0.55+BA63*0.4,0) -> 0
A64: ='Players Full'!CU64 -> Leander Dendoncker | B64: =VLOOKUP(_xlfn.CONCAT('Players Full'!AK64,'Players Full'!BV64),'Players Summarised'!$A$1:$T$1000,20,0) -> MID | C64: =VLOOKUP('Players Full'!CF64,Teams!$A$1:$G$21,6,0) -> Aston Villa | D64: ='Players Full'!BD64/10 -> 4.5 | E64: =IFERROR(VLOOKUP($A64,'Starting Lineups'!$A$2:$C$510,3,FALSE),0) -> 0 | F64: =VLOOKUP(A64,'Score & Assist'!$A$1:$G$2000,6,0) -> #N/A | G64: =IF(F64<0.3, 0.01,IF(F64=0.3,0.03,IF(F64<0.5,0.05,IF(F64<0.55,0.06,IF(F64<0.57,0.1,IF(F64<0.58,0.11,IF(F64<0.59,0.12,IF(F64<0.6,0.15,0.28)))))))) -> #N/A | H64: =IF(F64<0.3,0,IF(F64<0.55,0.01,IF(F64<0.59,0.02,IF(F64<0.6,0.03,0.11)))) -> #N/A | I64: =VLOOKUP(A64,'Score & Assist'!$A$1:$G$2000,7,0) -> #N/A | J64: =VLOOKUP(A64,'Yellow Card'!$C$1:$E$987,3,0) -> #N/A | K64: =VLOOKUP(C64,'Team Clean Sheet'!$C$2:$F$21,4,0) -> 0.29039301 | L64: =VLOOKUP(C64,'Team Total Goals'!$D$2:$N$21,10,0) -> 0.3546798 | M64: =VLOOKUP(C64,'Team Total Goals'!$D$2:$N$21,11,0) -> 0.050949051 | N64: =VLOOKUP(A64,'Goalkeeper Saves'!$D$2:$N$15,10,0) -> #N/A | O64: =VLOOKUP(A64,'Goalkeeper Saves'!$D$2:$N$15,11,0) -> #N/A | P64: =IF(B64="DEF",IFERROR(VLOOKUP(A64,'Defensive Contribution - DEF'!A62:H560,8,FALSE),'Defensive Contribution - DEF'!K$2),0) -> 0 | Q64: =IF(B64="MID",IFERROR(VLOOKUP(A64,'Defensive Contribution - MID'!A$2:I$500,9,FALSE),'Defensive Contribution - MID'!L$2),0) -> 0.38575005 | R64: =IFERROR(IFERROR(E64,0)*IF(B64="GK",2+IFERROR(F64*10,0)+IFERROR(G64*10,0)+IFERROR(H64*10,0)+IFERROR(I64*3,0)-IFERROR(J64*1,0)+IFERROR(K64*4,0)+IFERROR(N64*1,0)+IFERROR(O64*1,0)-IFERROR(L64*2,0)-IFERROR(M64*2,0),IF(B64="DEF",2+IFERROR(F64*6,0)+IFERROR(G64*6,0)+IFERROR(H64*6,0)+IFERROR(I64*3,0)-IFERROR(J64*1,0)+IFERROR(K64*4,0)-IFERROR(L64*2,0)-IFERROR(M64*2,0)+IFERROR(P64*2,0),IF(B64="MID",2+IFERROR(F64*5,0)+IFERROR(G64*5,0)+IFERROR(H64*5,0)+IFERROR(I64*3,0)-IFERROR(J64*1,0)+IFERROR(K64*1,0)+IFERROR(Q64*2,0),IF(B64="FWD",2+IFERROR(F64*4,0)+IFERROR(G64*4,0)+IFERROR(H64*4,0)+IFERROR(I64*3,0)-IFERROR(J64*1,0),"ERROR")))),0) -> 0 | S64: =MAX(0, MIN(1, -0.021039 + 0.023522 * R64)) -> 0 | T64: =R64+S64*2 -> 0 | U64: =VLOOKUP($C64,'Team Fixtures'!$A$2:$Q$21,2,FALSE) -> 0.42328042 | V64: =VLOOKUP($C64,'Team Fixtures'!$A$2:$Q$21,4,FALSE) -> 0.056022409 | W64: =VLOOKUP($C64,'Team Fixtures'!$A$2:$Q$21,5,FALSE) -> 0.36725801 | X64: =VLOOKUP($C64,'Team Fixtures'!$A$2:$Q$21,6,FALSE) -> A | Y64: =R64/(2.926+0.578*U64-0.576*V64-0.561*W64+0.469*IF(X64="H",1,0)) -> 0 | Z64: =VLOOKUP($C64,'Team Fixtures'!$A$2:$Q$21,2,FALSE) -> 0.42328042 | AA64: =VLOOKUP($C64,'Team Fixtures'!$A$2:$Q$21,8,FALSE) -> 0.10582011 | AB64: =VLOOKUP($C64,'Team Fixtures'!$A$2:$Q$21,9,FALSE) -> 0.31746032 | AC64: =VLOOKUP($C64,'Team Fixtures'!$A$2:$Q$21,10,FALSE) -> H | AD64: =IFERROR((2.926+0.578*Z64-0.576*AA64-0.561*AB64+0.469*IF(AC64="H",1,0))*$Y64,0) -> 0 | AE64: =MAX(0, MIN(1, -0.021039 + 0.023522 * AD64)) -> 0 | AF64: =AD64+AE64*2 -> 0 | AG64: =VLOOKUP($C64,'Team Fixtures'!$A$2:$Q$21,2,FALSE) -> 0.42328042 | AH64: =VLOOKUP($C64,'Team Fixtures'!$A$2:$Q$21,12,FALSE) -> 0.086580087 | AI64: =VLOOKUP($C64,'Team Fixtures'!$A$2:$Q$21,13,FALSE) -> 0.33670034 | AJ64: =VLOOKUP($C64,'Team Fixtures'!$A$2:$Q$21,14,FALSE) -> H | AK64: =IFERROR((2.926+0.578*AG64-0.576*AH64-0.561*AI64+0.469*IF(AJ64="H",1,0))*$Y64,0) -> 0 | AL64: =MAX(0, MIN(1, -0.021039 + 0.023522 * AK64)) -> 0 | AM64: =AK64+AL64*2 -> 0 | AN64: =VLOOKUP($C64,'Team Fixtures'!$A$2:$Q$21,2,FALSE) -> 0.42328042 | AO64: =VLOOKUP($C64,'Team Fixtures'!$A$2:$Q$21,16,FALSE) -> 0.018674136 | AP64: =VLOOKUP($C64,'Team Fixtures'!$A$2:$Q$21,17,FALSE) -> 0.40460629 | AQ64: =VLOOKUP($C64,'Team Fixtures'!$A$2:$V$21,18,FALSE) -> A | AR64: =IFERROR((2.926+0.578*AN64-0.576*AO64-0.561*AP64+0.469*IF(AQ64="H",1,0))*$Y64,0) -> 0 | AS64: =MAX(0, MIN(1, -0.021039 + 0.023522 * AR64)) -> 0 | AT64: =AR64+AS64*2 -> 0 | AU64: =VLOOKUP($C64,'Team Fixtures'!$A$2:$Q$21,2,FALSE) -> 0.42328042 | AV64: =VLOOKUP($C64,'Team Fixtures'!$A$2:$V$21,20,FALSE) -> 0.063492063 | AW64: =VLOOKUP($C64,'Team Fixtures'!$A$2:$V$21,21,FALSE) -> 0.35978836 | AX64: =VLOOKUP($C64,'Team Fixtures'!$A$2:$V$21,22,FALSE) -> H | AY64: =IFERROR((2.926+0.578*AU64-0.576*AV64-0.561*AW64+0.469*IF(AX64="H",1,0))*$Y64,0) -> 0 | AZ64: =MAX(0, MIN(1, -0.021039 + 0.023522 * AY64)) -> 0 | BA64: =AY64+AZ64*2 -> 0 | BB64: =IFERROR(T64*1+AF64*0.85+AM64*0.7+AT64*0.55+BA64*0.4,0) -> 0
A65: ='Players Full'!CU65 -> Jamaldeen Jimoh-Aloba | B65: =VLOOKUP(_xlfn.CONCAT('Players Full'!AK65,'Players Full'!BV65),'Players Summarised'!$A$1:$T$1000,20,0) -> MID | C65: =VLOOKUP('Players Full'!CF65,Teams!$A$1:$G$21,6,0) -> Aston Villa | D65: ='Players Full'!BD65/10 -> 4.5 | E65: =IFERROR(VLOOKUP($A65,'Starting Lineups'!$A$2:$C$510,3,FALSE),0) -> 0 | F65: =VLOOKUP(A65,'Score & Assist'!$A$1:$G$2000,6,0) -> #N/A | G65: =IF(F65<0.3, 0.01,IF(F65=0.3,0.03,IF(F65<0.5,0.05,IF(F65<0.55,0.06,IF(F65<0.57,0.1,IF(F65<0.58,0.11,IF(F65<0.59,0.12,IF(F65<0.6,0.15,0.28)))))))) -> #N/A | H65: =IF(F65<0.3,0,IF(F65<0.55,0.01,IF(F65<0.59,0.02,IF(F65<0.6,0.03,0.11)))) -> #N/A | I65: =VLOOKUP(A65,'Score & Assist'!$A$1:$G$2000,7,0) -> #N/A | J65: =VLOOKUP(A65,'Yellow Card'!$C$1:$E$987,3,0) -> #N/A | K65: =VLOOKUP(C65,'Team Clean Sheet'!$C$2:$F$21,4,0) -> 0.29039301 | L65: =VLOOKUP(C65,'Team Total Goals'!$D$2:$N$21,10,0) -> 0.3546798 | M65: =VLOOKUP(C65,'Team Total Goals'!$D$2:$N$21,11,0) -> 0.050949051 | N65: =VLOOKUP(A65,'Goalkeeper Saves'!$D$2:$N$15,10,0) -> #N/A | O65: =VLOOKUP(A65,'Goalkeeper Saves'!$D$2:$N$15,11,0) -> #N/A | P65: =IF(B65="DEF",IFERROR(VLOOKUP(A65,'Defensive Contribution - DEF'!A63:H561,8,FALSE),'Defensive Contribution - DEF'!K$2),0) -> 0 | Q65: =IF(B65="MID",IFERROR(VLOOKUP(A65,'Defensive Contribution - MID'!A$2:I$500,9,FALSE),'Defensive Contribution - MID'!L$2),0) -> 0.38575005 | R65: =IFERROR(IFERROR(E65,0)*IF(B65="GK",2+IFERROR(F65*10,0)+IFERROR(G65*10,0)+IFERROR(H65*10,0)+IFERROR(I65*3,0)-IFERROR(J65*1,0)+IFERROR(K65*4,0)+IFERROR(N65*1,0)+IFERROR(O65*1,0)-IFERROR(L65*2,0)-IFERROR(M65*2,0),IF(B65="DEF",2+IFERROR(F65*6,0)+IFERROR(G65*6,0)+IFERROR(H65*6,0)+IFERROR(I65*3,0)-IFERROR(J65*1,0)+IFERROR(K65*4,0)-IFERROR(L65*2,0)-IFERROR(M65*2,0)+IFERROR(P65*2,0),IF(B65="MID",2+IFERROR(F65*5,0)+IFERROR(G65*5,0)+IFERROR(H65*5,0)+IFERROR(I65*3,0)-IFERROR(J65*1,0)+IFERROR(K65*1,0)+IFERROR(Q65*2,0),IF(B65="FWD",2+IFERROR(F65*4,0)+IFERROR(G65*4,0)+IFERROR(H65*4,0)+IFERROR(I65*3,0)-IFERROR(J65*1,0),"ERROR")))),0) -> 0 | S65: =MAX(0, MIN(1, -0.021039 + 0.023522 * R65)) -> 0 | T65: =R65+S65*2 -> 0 | U65: =VLOOKUP($C65,'Team Fixtures'!$A$2:$Q$21,2,FALSE) -> 0.42328042 | V65: =VLOOKUP($C65,'Team Fixtures'!$A$2:$Q$21,4,FALSE) -> 0.056022409 | W65: =VLOOKUP($C65,'Team Fixtures'!$A$2:$Q$21,5,FALSE) -> 0.36725801 | X65: =VLOOKUP($C65,'Team Fixtures'!$A$2:$Q$21,6,FALSE) -> A | Y65: =R65/(2.926+0.578*U65-0.576*V65-0.561*W65+0.469*IF(X65="H",1,0)) -> 0 | Z65: =VLOOKUP($C65,'Team Fixtures'!$A$2:$Q$21,2,FALSE) -> 0.42328042 | AA65: =VLOOKUP($C65,'Team Fixtures'!$A$2:$Q$21,8,FALSE) -> 0.10582011 | AB65: =VLOOKUP($C65,'Team Fixtures'!$A$2:$Q$21,9,FALSE) -> 0.31746032 | AC65: =VLOOKUP($C65,'Team Fixtures'!$A$2:$Q$21,10,FALSE) -> H | AD65: =IFERROR((2.926+0.578*Z65-0.576*AA65-0.561*AB65+0.469*IF(AC65="H",1,0))*$Y65,0) -> 0 | AE65: =MAX(0, MIN(1, -0.021039 + 0.023522 * AD65)) -> 0 | AF65: =AD65+AE65*2 -> 0 | AG65: =VLOOKUP($C65,'Team Fixtures'!$A$2:$Q$21,2,FALSE) -> 0.42328042 | AH65: =VLOOKUP($C65,'Team Fixtures'!$A$2:$Q$21,12,FALSE) -> 0.086580087 | AI65: =VLOOKUP($C65,'Team Fixtures'!$A$2:$Q$21,13,FALSE) -> 0.33670034 | AJ65: =VLOOKUP($C65,'Team Fixtures'!$A$2:$Q$21,14,FALSE) -> H | AK65: =IFERROR((2.926+0.578*AG65-0.576*AH65-0.561*AI65+0.469*IF(AJ65="H",1,0))*$Y65,0) -> 0 | AL65: =MAX(0, MIN(1, -0.021039 + 0.023522 * AK65)) -> 0 | AM65: =AK65+AL65*2 -> 0 | AN65: =VLOOKUP($C65,'Team Fixtures'!$A$2:$Q$21,2,FALSE) -> 0.42328042 | AO65: =VLOOKUP($C65,'Team Fixtures'!$A$2:$Q$21,16,FALSE) -> 0.018674136 | AP65: =VLOOKUP($C65,'Team Fixtures'!$A$2:$Q$21,17,FALSE) -> 0.40460629 | AQ65: =VLOOKUP($C65,'Team Fixtures'!$A$2:$V$21,18,FALSE) -> A | AR65: =IFERROR((2.926+0.578*AN65-0.576*AO65-0.561*AP65+0.469*IF(AQ65="H",1,0))*$Y65,0) -> 0 | AS65: =MAX(0, MIN(1, -0.021039 + 0.023522 * AR65)) -> 0 | AT65: =AR65+AS65*2 -> 0 | AU65: =VLOOKUP($C65,'Team Fixtures'!$A$2:$Q$21,2,FALSE) -> 0.42328042 | AV65: =VLOOKUP($C65,'Team Fixtures'!$A$2:$V$21,20,FALSE) -> 0.063492063 | AW65: =VLOOKUP($C65,'Team Fixtures'!$A$2:$V$21,21,FALSE) -> 0.35978836 | AX65: =VLOOKUP($C65,'Team Fixtures'!$A$2:$V$21,22,FALSE) -> H | AY65: =IFERROR((2.926+0.578*AU65-0.576*AV65-0.561*AW65+0.469*IF(AX65="H",1,0))*$Y65,0) -> 0 | AZ65: =MAX(0, MIN(1, -0.021039 + 0.023522 * AY65)) -> 0 | BA65: =AY65+AZ65*2 -> 0 | BB65: =IFERROR(T65*1+AF65*0.85+AM65*0.7+AT65*0.55+BA65*0.4,0) -> 0
A66: ='Players Full'!CU66 -> Kadan Young | B66: =VLOOKUP(_xlfn.CONCAT('Players Full'!AK66,'Players Full'!BV66),'Players Summarised'!$A$1:$T$1000,20,0) -> MID | C66: =VLOOKUP('Players Full'!CF66,Teams!$A$1:$G$21,6,0) -> Aston Villa | D66: ='Players Full'!BD66/10 -> 4.5 | E66: =IFERROR(VLOOKUP($A66,'Starting Lineups'!$A$2:$C$510,3,FALSE),0) -> 0 | F66: =VLOOKUP(A66,'Score & Assist'!$A$1:$G$2000,6,0) -> #N/A | G66: =IF(F66<0.3, 0.01,IF(F66=0.3,0.03,IF(F66<0.5,0.05,IF(F66<0.55,0.06,IF(F66<0.57,0.1,IF(F66<0.58,0.11,IF(F66<0.59,0.12,IF(F66<0.6,0.15,0.28)))))))) -> #N/A | H66: =IF(F66<0.3,0,IF(F66<0.55,0.01,IF(F66<0.59,0.02,IF(F66<0.6,0.03,0.11)))) -> #N/A | I66: =VLOOKUP(A66,'Score & Assist'!$A$1:$G$2000,7,0) -> #N/A | J66: =VLOOKUP(A66,'Yellow Card'!$C$1:$E$987,3,0) -> #N/A | K66: =VLOOKUP(C66,'Team Clean Sheet'!$C$2:$F$21,4,0) -> 0.29039301 | L66: =VLOOKUP(C66,'Team Total Goals'!$D$2:$N$21,10,0) -> 0.3546798 | M66: =VLOOKUP(C66,'Team Total Goals'!$D$2:$N$21,11,0) -> 0.050949051 | N66: =VLOOKUP(A66,'Goalkeeper Saves'!$D$2:$N$15,10,0) -> #N/A | O66: =VLOOKUP(A66,'Goalkeeper Saves'!$D$2:$N$15,11,0) -> #N/A | P66: =IF(B66="DEF",IFERROR(VLOOKUP(A66,'Defensive Contribution - DEF'!A64:H562,8,FALSE),'Defensive Contribution - DEF'!K$2),0) -> 0 | Q66: =IF(B66="MID",IFERROR(VLOOKUP(A66,'Defensive Contribution - MID'!A$2:I$500,9,FALSE),'Defensive Contribution - MID'!L$2),0) -> 0.38575005 | R66: =IFERROR(IFERROR(E66,0)*IF(B66="GK",2+IFERROR(F66*10,0)+IFERROR(G66*10,0)+IFERROR(H66*10,0)+IFERROR(I66*3,0)-IFERROR(J66*1,0)+IFERROR(K66*4,0)+IFERROR(N66*1,0)+IFERROR(O66*1,0)-IFERROR(L66*2,0)-IFERROR(M66*2,0),IF(B66="DEF",2+IFERROR(F66*6,0)+IFERROR(G66*6,0)+IFERROR(H66*6,0)+IFERROR(I66*3,0)-IFERROR(J66*1,0)+IFERROR(K66*4,0)-IFERROR(L66*2,0)-IFERROR(M66*2,0)+IFERROR(P66*2,0),IF(B66="MID",2+IFERROR(F66*5,0)+IFERROR(G66*5,0)+IFERROR(H66*5,0)+IFERROR(I66*3,0)-IFERROR(J66*1,0)+IFERROR(K66*1,0)+IFERROR(Q66*2,0),IF(B66="FWD",2+IFERROR(F66*4,0)+IFERROR(G66*4,0)+IFERROR(H66*4,0)+IFERROR(I66*3,0)-IFERROR(J66*1,0),"ERROR")))),0) -> 0 | S66: =MAX(0, MIN(1, -0.021039 + 0.023522 * R66)) -> 0 | T66: =R66+S66*2 -> 0 | U66: =VLOOKUP($C66,'Team Fixtures'!$A$2:$Q$21,2,FALSE) -> 0.42328042 | V66: =VLOOKUP($C66,'Team Fixtures'!$A$2:$Q$21,4,FALSE) -> 0.056022409 | W66: =VLOOKUP($C66,'Team Fixtures'!$A$2:$Q$21,5,FALSE) -> 0.36725801 | X66: =VLOOKUP($C66,'Team Fixtures'!$A$2:$Q$21,6,FALSE) -> A | Y66: =R66/(2.926+0.578*U66-0.576*V66-0.561*W66+0.469*IF(X66="H",1,0)) -> 0 | Z66: =VLOOKUP($C66,'Team Fixtures'!$A$2:$Q$21,2,FALSE) -> 0.42328042 | AA66: =VLOOKUP($C66,'Team Fixtures'!$A$2:$Q$21,8,FALSE) -> 0.10582011 | AB66: =VLOOKUP($C66,'Team Fixtures'!$A$2:$Q$21,9,FALSE) -> 0.31746032 | AC66: =VLOOKUP($C66,'Team Fixtures'!$A$2:$Q$21,10,FALSE) -> H | AD66: =IFERROR((2.926+0.578*Z66-0.576*AA66-0.561*AB66+0.469*IF(AC66="H",1,0))*$Y66,0) -> 0 | AE66: =MAX(0, MIN(1, -0.021039 + 0.023522 * AD66)) -> 0 | AF66: =AD66+AE66*2 -> 0 | AG66: =VLOOKUP($C66,'Team Fixtures'!$A$2:$Q$21,2,FALSE) -> 0.42328042 | AH66: =VLOOKUP($C66,'Team Fixtures'!$A$2:$Q$21,12,FALSE) -> 0.086580087 | AI66: =VLOOKUP($C66,'Team Fixtures'!$A$2:$Q$21,13,FALSE) -> 0.33670034 | AJ66: =VLOOKUP($C66,'Team Fixtures'!$A$2:$Q$21,14,FALSE) -> H | AK66: =IFERROR((2.926+0.578*AG66-0.576*AH66-0.561*AI66+0.469*IF(AJ66="H",1,0))*$Y66,0) -> 0 | AL66: =MAX(0, MIN(1, -0.021039 + 0.023522 * AK66)) -> 0 | AM66: =AK66+AL66*2 -> 0 | AN66: =VLOOKUP($C66,'Team Fixtures'!$A$2:$Q$21,2,FALSE) -> 0.42328042 | AO66: =VLOOKUP($C66,'Team Fixtures'!$A$2:$Q$21,16,FALSE) -> 0.018674136 | AP66: =VLOOKUP($C66,'Team Fixtures'!$A$2:$Q$21,17,FALSE) -> 0.40460629 | AQ66: =VLOOKUP($C66,'Team Fixtures'!$A$2:$V$21,18,FALSE) -> A | AR66: =IFERROR((2.926+0.578*AN66-0.576*AO66-0.561*AP66+0.469*IF(AQ66="H",1,0))*$Y66,0) -> 0 | AS66: =MAX(0, MIN(1, -0.021039 + 0.023522 * AR66)) -> 0 | AT66: =AR66+AS66*2 -> 0 | AU66: =VLOOKUP($C66,'Team Fixtures'!$A$2:$Q$21,2,FALSE) -> 0.42328042 | AV66: =VLOOKUP($C66,'Team Fixtures'!$A$2:$V$21,20,FALSE) -> 0.063492063 | AW66: =VLOOKUP($C66,'Team Fixtures'!$A$2:$V$21,21,FALSE) -> 0.35978836 | AX66: =VLOOKUP($C66,'Team Fixtures'!$A$2:$V$21,22,FALSE) -> H | AY66: =IFERROR((2.926+0.578*AU66-0.576*AV66-0.561*AW66+0.469*IF(AX66="H",1,0))*$Y66,0) -> 0 | AZ66: =MAX(0, MIN(1, -0.021039 + 0.023522 * AY66)) -> 0 | BA66: =AY66+AZ66*2 -> 0 | BB66: =IFERROR(T66*1+AF66*0.85+AM66*0.7+AT66*0.55+BA66*0.4,0) -> 0
A67: ='Players Full'!CU67 -> Ollie Watkins | B67: =VLOOKUP(_xlfn.CONCAT('Players Full'!AK67,'Players Full'!BV67),'Players Summarised'!$A$1:$T$1000,20,0) -> FWD | C67: =VLOOKUP('Players Full'!CF67,Teams!$A$1:$G$21,6,0) -> Aston Villa | D67: ='Players Full'!BD67/10 -> 9 | E67: =IFERROR(VLOOKUP($A67,'Starting Lineups'!$A$2:$C$510,3,FALSE),0) -> 1 | F67: =VLOOKUP(A67,'Score & Assist'!$A$1:$G$2000,6,0) -> 0.41407867 | G67: =IF(F67<0.3, 0.01,IF(F67=0.3,0.03,IF(F67<0.5,0.05,IF(F67<0.55,0.06,IF(F67<0.57,0.1,IF(F67<0.58,0.11,IF(F67<0.59,0.12,IF(F67<0.6,0.15,0.28)))))))) -> 0.05 | H67: =IF(F67<0.3,0,IF(F67<0.55,0.01,IF(F67<0.59,0.02,IF(F67<0.6,0.03,0.11)))) -> 0.01 | I67: =VLOOKUP(A67,'Score & Assist'!$A$1:$G$2000,7,0) -> 0.13605442 | J67: =VLOOKUP(A67,'Yellow Card'!$C$1:$E$987,3,0) -> 0.15873016 | K67: =VLOOKUP(C67,'Team Clean Sheet'!$C$2:$F$21,4,0) -> 0.29039301 | L67: =VLOOKUP(C67,'Team Total Goals'!$D$2:$N$21,10,0) -> 0.3546798 | M67: =VLOOKUP(C67,'Team Total Goals'!$D$2:$N$21,11,0) -> 0.050949051 | N67: =VLOOKUP(A67,'Goalkeeper Saves'!$D$2:$N$15,10,0) -> #N/A | O67: =VLOOKUP(A67,'Goalkeeper Saves'!$D$2:$N$15,11,0) -> #N/A | P67: =IF(B67="DEF",IFERROR(VLOOKUP(A67,'Defensive Contribution - DEF'!A65:H563,8,FALSE),'Defensive Contribution - DEF'!K$2),0) -> 0 | Q67: =IF(B67="MID",IFERROR(VLOOKUP(A67,'Defensive Contribution - MID'!A$2:I$500,9,FALSE),'Defensive Contribution - MID'!L$2),0) -> 0 | R67: =IFERROR(IFERROR(E67,0)*IF(B67="GK",2+IFERROR(F67*10,0)+IFERROR(G67*10,0)+IFERROR(H67*10,0)+IFERROR(I67*3,0)-IFERROR(J67*1,0)+IFERROR(K67*4,0)+IFERROR(N67*1,0)+IFERROR(O67*1,0)-IFERROR(L67*2,0)-IFERROR(M67*2,0),IF(B67="DEF",2+IFERROR(F67*6,0)+IFERROR(G67*6,0)+IFERROR(H67*6,0)+IFERROR(I67*3,0)-IFERROR(J67*1,0)+IFERROR(K67*4,0)-IFERROR(L67*2,0)-IFERROR(M67*2,0)+IFERROR(P67*2,0),IF(B67="MID",2+IFERROR(F67*5,0)+IFERROR(G67*5,0)+IFERROR(H67*5,0)+IFERROR(I67*3,0)-IFERROR(J67*1,0)+IFERROR(K67*1,0)+IFERROR(Q67*2,0),IF(B67="FWD",2+IFERROR(F67*4,0)+IFERROR(G67*4,0)+IFERROR(H67*4,0)+IFERROR(I67*3,0)-IFERROR(J67*1,0),"ERROR")))),0) -> 4.1457478 | S67: =MAX(0, MIN(1, -0.021039 + 0.023522 * R67)) -> 0.07647728 | T67: =R67+S67*2 -> 4.2987024 | U67: =VLOOKUP($C67,'Team Fixtures'!$A$2:$Q$21,2,FALSE) -> 0.42328042 | V67: =VLOOKUP($C67,'Team Fixtures'!$A$2:$Q$21,4,FALSE) -> 0.056022409 | W67: =VLOOKUP($C67,'Team Fixtures'!$A$2:$Q$21,5,FALSE) -> 0.36725801 | X67: =VLOOKUP($C67,'Team Fixtures'!$A$2:$Q$21,6,FALSE) -> A | Y67: =R67/(2.926+0.578*U67-0.576*V67-0.561*W67+0.469*IF(X67="H",1,0)) -> 1.4137944 | Z67: =VLOOKUP($C67,'Team Fixtures'!$A$2:$Q$21,2,FALSE) -> 0.42328042 | AA67: =VLOOKUP($C67,'Team Fixtures'!$A$2:$Q$21,8,FALSE) -> 0.10582011 | AB67: =VLOOKUP($C67,'Team Fixtures'!$A$2:$Q$21,9,FALSE) -> 0.31746032 | AC67: =VLOOKUP($C67,'Team Fixtures'!$A$2:$Q$21,10,FALSE) -> H | AD67: =IFERROR((2.926+0.578*Z67-0.576*AA67-0.561*AB67+0.469*IF(AC67="H",1,0))*$Y67,0) -> 4.8077613 | AE67: =MAX(0, MIN(1, -0.021039 + 0.023522 * AD67)) -> 0.092049162 | AF67: =AD67+AE67*2 -> 4.9918597 | AG67: =VLOOKUP($C67,'Team Fixtures'!$A$2:$Q$21,2,FALSE) -> 0.42328042 | AH67: =VLOOKUP($C67,'Team Fixtures'!$A$2:$Q$21,12,FALSE) -> 0.086580087 | AI67: =VLOOKUP($C67,'Team Fixtures'!$A$2:$Q$21,13,FALSE) -> 0.33670034 | AJ67: =VLOOKUP($C67,'Team Fixtures'!$A$2:$Q$21,14,FALSE) -> H | AK67: =IFERROR((2.926+0.578*AG67-0.576*AH67-0.561*AI67+0.469*IF(AJ67="H",1,0))*$Y67,0) -> 4.8081694 | AL67: =MAX(0, MIN(1, -0.021039 + 0.023522 * AK67)) -> 0.09205876 | AM67: =AK67+AL67*2 -> 4.9922869 | AN67: =VLOOKUP($C67,'Team Fixtures'!$A$2:$Q$21,2,FALSE) -> 0.42328042 | AO67: =VLOOKUP($C67,'Team Fixtures'!$A$2:$Q$21,16,FALSE) -> 0.018674136 | AP67: =VLOOKUP($C67,'Team Fixtures'!$A$2:$Q$21,17,FALSE) -> 0.40460629 | AQ67: =VLOOKUP($C67,'Team Fixtures'!$A$2:$V$21,18,FALSE) -> A | AR67: =IFERROR((2.926+0.578*AN67-0.576*AO67-0.561*AP67+0.469*IF(AQ67="H",1,0))*$Y67,0) -> 4.1465398 | AS67: =MAX(0, MIN(1, -0.021039 + 0.023522 * AR67)) -> 0.07649591 | AT67: =AR67+AS67*2 -> 4.2995317 | AU67: =VLOOKUP($C67,'Team Fixtures'!$A$2:$Q$21,2,FALSE) -> 0.42328042 | AV67: =VLOOKUP($C67,'Team Fixtures'!$A$2:$V$21,20,FALSE) -> 0.063492063 | AW67: =VLOOKUP($C67,'Team Fixtures'!$A$2:$V$21,21,FALSE) -> 0.35978836 | AX67: =VLOOKUP($C67,'Team Fixtures'!$A$2:$V$21,22,FALSE) -> H | AY67: =IFERROR((2.926+0.578*AU67-0.576*AV67-0.561*AW67+0.469*IF(AX67="H",1,0))*$Y67,0) -> 4.808659 | AZ67: =MAX(0, MIN(1, -0.021039 + 0.023522 * AY67)) -> 0.092070277 | BA67: =AY67+AZ67*2 -> 4.9927995 | BB67: =IFERROR(T67*1+AF67*0.85+AM67*0.7+AT67*0.55+BA67*0.4,0) -> 16.398246
A68: ='Players Full'!CU68 -> ZÃ©piqueno Redmond | B68: =VLOOKUP(_xlfn.CONCAT('Players Full'!AK68,'Players Full'!BV68),'Players Summarised'!$A$1:$T$1000,20,0) -> FWD | C68: =VLOOKUP('Players Full'!CF68,Teams!$A$1:$G$21,6,0) -> Aston Villa | D68: ='Players Full'!BD68/10 -> 4.5 | E68: =IFERROR(VLOOKUP($A68,'Starting Lineups'!$A$2:$C$510,3,FALSE),0) -> 0 | F68: =VLOOKUP(A68,'Score & Assist'!$A$1:$G$2000,6,0) -> #N/A | G68: =IF(F68<0.3, 0.01,IF(F68=0.3,0.03,IF(F68<0.5,0.05,IF(F68<0.55,0.06,IF(F68<0.57,0.1,IF(F68<0.58,0.11,IF(F68<0.59,0.12,IF(F68<0.6,0.15,0.28)))))))) -> #N/A | H68: =IF(F68<0.3,0,IF(F68<0.55,0.01,IF(F68<0.59,0.02,IF(F68<0.6,0.03,0.11)))) -> #N/A | I68: =VLOOKUP(A68,'Score & Assist'!$A$1:$G$2000,7,0) -> #N/A | J68: =VLOOKUP(A68,'Yellow Card'!$C$1:$E$987,3,0) -> #N/A | K68: =VLOOKUP(C68,'Team Clean Sheet'!$C$2:$F$21,4,0) -> 0.29039301 | L68: =VLOOKUP(C68,'Team Total Goals'!$D$2:$N$21,10,0) -> 0.3546798 | M68: =VLOOKUP(C68,'Team Total Goals'!$D$2:$N$21,11,0) -> 0.050949051 | N68: =VLOOKUP(A68,'Goalkeeper Saves'!$D$2:$N$15,10,0) -> #N/A | O68: =VLOOKUP(A68,'Goalkeeper Saves'!$D$2:$N$15,11,0) -> #N/A | P68: =IF(B68="DEF",IFERROR(VLOOKUP(A68,'Defensive Contribution - DEF'!A66:H564,8,FALSE),'Defensive Contribution - DEF'!K$2),0) -> 0 | Q68: =IF(B68="MID",IFERROR(VLOOKUP(A68,'Defensive Contribution - MID'!A$2:I$500,9,FALSE),'Defensive Contribution - MID'!L$2),0) -> 0 | R68: =IFERROR(IFERROR(E68,0)*IF(B68="GK",2+IFERROR(F68*10,0)+IFERROR(G68*10,0)+IFERROR(H68*10,0)+IFERROR(I68*3,0)-IFERROR(J68*1,0)+IFERROR(K68*4,0)+IFERROR(N68*1,0)+IFERROR(O68*1,0)-IFERROR(L68*2,0)-IFERROR(M68*2,0),IF(B68="DEF",2+IFERROR(F68*6,0)+IFERROR(G68*6,0)+IFERROR(H68*6,0)+IFERROR(I68*3,0)-IFERROR(J68*1,0)+IFERROR(K68*4,0)-IFERROR(L68*2,0)-IFERROR(M68*2,0)+IFERROR(P68*2,0),IF(B68="MID",2+IFERROR(F68*5,0)+IFERROR(G68*5,0)+IFERROR(H68*5,0)+IFERROR(I68*3,0)-IFERROR(J68*1,0)+IFERROR(K68*1,0)+IFERROR(Q68*2,0),IF(B68="FWD",2+IFERROR(F68*4,0)+IFERROR(G68*4,0)+IFERROR(H68*4,0)+IFERROR(I68*3,0)-IFERROR(J68*1,0),"ERROR")))),0) -> 0 | S68: =MAX(0, MIN(1, -0.021039 + 0.023522 * R68)) -> 0 | T68: =R68+S68*2 -> 0 | U68: =VLOOKUP($C68,'Team Fixtures'!$A$2:$Q$21,2,FALSE) -> 0.42328042 | V68: =VLOOKUP($C68,'Team Fixtures'!$A$2:$Q$21,4,FALSE) -> 0.056022409 | W68: =VLOOKUP($C68,'Team Fixtures'!$A$2:$Q$21,5,FALSE) -> 0.36725801 | X68: =VLOOKUP($C68,'Team Fixtures'!$A$2:$Q$21,6,FALSE) -> A | Y68: =R68/(2.926+0.578*U68-0.576*V68-0.561*W68+0.469*IF(X68="H",1,0)) -> 0 | Z68: =VLOOKUP($C68,'Team Fixtures'!$A$2:$Q$21,2,FALSE) -> 0.42328042 | AA68: =VLOOKUP($C68,'Team Fixtures'!$A$2:$Q$21,8,FALSE) -> 0.10582011 | AB68: =VLOOKUP($C68,'Team Fixtures'!$A$2:$Q$21,9,FALSE) -> 0.31746032 | AC68: =VLOOKUP($C68,'Team Fixtures'!$A$2:$Q$21,10,FALSE) -> H | AD68: =IFERROR((2.926+0.578*Z68-0.576*AA68-0.561*AB68+0.469*IF(AC68="H",1,0))*$Y68,0) -> 0 | AE68: =MAX(0, MIN(1, -0.021039 + 0.023522 * AD68)) -> 0 | AF68: =AD68+AE68*2 -> 0 | AG68: =VLOOKUP($C68,'Team Fixtures'!$A$2:$Q$21,2,FALSE) -> 0.42328042 | AH68: =VLOOKUP($C68,'Team Fixtures'!$A$2:$Q$21,12,FALSE) -> 0.086580087 | AI68: =VLOOKUP($C68,'Team Fixtures'!$A$2:$Q$21,13,FALSE) -> 0.33670034 | AJ68: =VLOOKUP($C68,'Team Fixtures'!$A$2:$Q$21,14,FALSE) -> H | AK68: =IFERROR((2.926+0.578*AG68-0.576*AH68-0.561*AI68+0.469*IF(AJ68="H",1,0))*$Y68,0) -> 0 | AL68: =MAX(0, MIN(1, -0.021039 + 0.023522 * AK68)) -> 0 | AM68: =AK68+AL68*2 -> 0 | AN68: =VLOOKUP($C68,'Team Fixtures'!$A$2:$Q$21,2,FALSE) -> 0.42328042 | AO68: =VLOOKUP($C68,'Team Fixtures'!$A$2:$Q$21,16,FALSE) -> 0.018674136 | AP68: =VLOOKUP($C68,'Team Fixtures'!$A$2:$Q$21,17,FALSE) -> 0.40460629 | AQ68: =VLOOKUP($C68,'Team Fixtures'!$A$2:$V$21,18,FALSE) -> A | AR68: =IFERROR((2.926+0.578*AN68-0.576*AO68-0.561*AP68+0.469*IF(AQ68="H",1,0))*$Y68,0) -> 0 | AS68: =MAX(0, MIN(1, -0.021039 + 0.023522 * AR68)) -> 0 | AT68: =AR68+AS68*2 -> 0 | AU68: =VLOOKUP($C68,'Team Fixtures'!$A$2:$Q$21,2,FALSE) -> 0.42328042 | AV68: =VLOOKUP($C68,'Team Fixtures'!$A$2:$V$21,20,FALSE) -> 0.063492063 | AW68: =VLOOKUP($C68,'Team Fixtures'!$A$2:$V$21,21,FALSE) -> 0.35978836 | AX68: =VLOOKUP($C68,'Team Fixtures'!$A$2:$V$21,22,FALSE) -> H | AY68: =IFERROR((2.926+0.578*AU68-0.576*AV68-0.561*AW68+0.469*IF(AX68="H",1,0))*$Y68,0) -> 0 | AZ68: =MAX(0, MIN(1, -0.021039 + 0.023522 * AY68)) -> 0 | BA68: =AY68+AZ68*2 -> 0 | BB68: =IFERROR(T68*1+AF68*0.85+AM68*0.7+AT68*0.55+BA68*0.4,0) -> 0
A69: ='Players Full'!CU69 -> Max Weiss | B69: =VLOOKUP(_xlfn.CONCAT('Players Full'!AK69,'Players Full'!BV69),'Players Summarised'!$A$1:$T$1000,20,0) -> GK | C69: =VLOOKUP('Players Full'!CF69,Teams!$A$1:$G$21,6,0) -> Burnley | D69: ='Players Full'!BD69/10 -> 4.5 | E69: =IFERROR(VLOOKUP($A69,'Starting Lineups'!$A$2:$C$510,3,FALSE),0) -> 0 | F69: =VLOOKUP(A69,'Score & Assist'!$A$1:$G$2000,6,0) -> #N/A | G69: =IF(F69<0.3, 0.01,IF(F69=0.3,0.03,IF(F69<0.5,0.05,IF(F69<0.55,0.06,IF(F69<0.57,0.1,IF(F69<0.58,0.11,IF(F69<0.59,0.12,IF(F69<0.6,0.15,0.28)))))))) -> #N/A | H69: =IF(F69<0.3,0,IF(F69<0.55,0.01,IF(F69<0.59,0.02,IF(F69<0.6,0.03,0.11)))) -> #N/A | I69: =VLOOKUP(A69,'Score & Assist'!$A$1:$G$2000,7,0) -> #N/A | J69: =VLOOKUP(A69,'Yellow Card'!$C$1:$E$987,3,0) -> 0.073260073 | K69: =VLOOKUP(C69,'Team Clean Sheet'!$C$2:$F$21,4,0) -> 0.3546798 | L69: =VLOOKUP(C69,'Team Total Goals'!$D$2:$N$21,10,0) -> 0.29039301 | M69: =VLOOKUP(C69,'Team Total Goals'!$D$2:$N$21,11,0) -> 0.037393558 | N69: =VLOOKUP(A69,'Goalkeeper Saves'!$D$2:$N$15,10,0) -> #N/A | O69: =VLOOKUP(A69,'Goalkeeper Saves'!$D$2:$N$15,11,0) -> #N/A | P69: =IF(B69="DEF",IFERROR(VLOOKUP(A69,'Defensive Contribution - DEF'!A67:H565,8,FALSE),'Defensive Contribution - DEF'!K$2),0) -> 0 | Q69: =IF(B69="MID",IFERROR(VLOOKUP(A69,'Defensive Contribution - MID'!A$2:I$500,9,FALSE),'Defensive Contribution - MID'!L$2),0) -> 0 | R69: =IFERROR(IFERROR(E69,0)*IF(B69="GK",2+IFERROR(F69*10,0)+IFERROR(G69*10,0)+IFERROR(H69*10,0)+IFERROR(I69*3,0)-IFERROR(J69*1,0)+IFERROR(K69*4,0)+IFERROR(N69*1,0)+IFERROR(O69*1,0)-IFERROR(L69*2,0)-IFERROR(M69*2,0),IF(B69="DEF",2+IFERROR(F69*6,0)+IFERROR(G69*6,0)+IFERROR(H69*6,0)+IFERROR(I69*3,0)-IFERROR(J69*1,0)+IFERROR(K69*4,0)-IFERROR(L69*2,0)-IFERROR(M69*2,0)+IFERROR(P69*2,0),IF(B69="MID",2+IFERROR(F69*5,0)+IFERROR(G69*5,0)+IFERROR(H69*5,0)+IFERROR(I69*3,0)-IFERROR(J69*1,0)+IFERROR(K69*1,0)+IFERROR(Q69*2,0),IF(B69="FWD",2+IFERROR(F69*4,0)+IFERROR(G69*4,0)+IFERROR(H69*4,0)+IFERROR(I69*3,0)-IFERROR(J69*1,0),"ERROR")))),0) -> 0 | S69: =MAX(0, MIN(1, -0.021039 + 0.023522 * R69)) -> 0 | T69: =R69+S69*2 -> 0 | U69: =VLOOKUP($C69,'Team Fixtures'!$A$2:$Q$21,2,FALSE) -> 0.014214641 | V69: =VLOOKUP($C69,'Team Fixtures'!$A$2:$Q$21,4,FALSE) -> 0.018674136 | W69: =VLOOKUP($C69,'Team Fixtures'!$A$2:$Q$21,5,FALSE) -> -0.0044594952 | X69: =VLOOKUP($C69,'Team Fixtures'!$A$2:$Q$21,6,FALSE) -> H | Y69: =R69/(2.926+0.578*U69-0.576*V69-0.561*W69+0.469*IF(X69="H",1,0)) -> 0 | Z69: =VLOOKUP($C69,'Team Fixtures'!$A$2:$Q$21,2,FALSE) -> 0.014214641 | AA69: =VLOOKUP($C69,'Team Fixtures'!$A$2:$Q$21,8,FALSE) -> 0.52910053 | AB69: =VLOOKUP($C69,'Team Fixtures'!$A$2:$Q$21,9,FALSE) -> -0.51488589 | AC69: =VLOOKUP($C69,'Team Fixtures'!$A$2:$Q$21,10,FALSE) -> A | AD69: =IFERROR((2.926+0.578*Z69-0.576*AA69-0.561*AB69+0.469*IF(AC69="H",1,0))*$Y69,0) -> 0 | AE69: =MAX(0, MIN(1, -0.021039 + 0.023522 * AD69)) -> 0 | AF69: =AD69+AE69*2 -> 0 | AG69: =VLOOKUP($C69,'Team Fixtures'!$A$2:$Q$21,2,FALSE) -> 0.014214641 | AH69: =VLOOKUP($C69,'Team Fixtures'!$A$2:$Q$21,12,FALSE) -> 0.89678056 | AI69: =VLOOKUP($C69,'Team Fixtures'!$A$2:$Q$21,13,FALSE) -> -0.88256592 | AJ69: =VLOOKUP($C69,'Team Fixtures'!$A$2:$Q$21,14,FALSE) -> A | AK69: =IFERROR((2.926+0.578*AG69-0.576*AH69-0.561*AI69+0.469*IF(AJ69="H",1,0))*$Y69,0) -> 0 | AL69: =MAX(0, MIN(1, -0.021039 + 0.023522 * AK69)) -> 0 | AM69: =AK69+AL69*2 -> 0 | AN69: =VLOOKUP($C69,'Team Fixtures'!$A$2:$Q$21,2,FALSE) -> 0.014214641 | AO69: =VLOOKUP($C69,'Team Fixtures'!$A$2:$Q$21,16,FALSE) -> 0.10582011 | AP69: =VLOOKUP($C69,'Team Fixtures'!$A$2:$Q$21,17,FALSE) -> -0.091605465 | AQ69: =VLOOKUP($C69,'Team Fixtures'!$A$2:$V$21,18,FALSE) -> H | AR69: =IFERROR((2.926+0.578*AN69-0.576*AO69-0.561*AP69+0.469*IF(AQ69="H",1,0))*$Y69,0) -> 0 | AS69: =MAX(0, MIN(1, -0.021039 + 0.023522 * AR69)) -> 0 | AT69: =AR69+AS69*2 -> 0 | AU69: =VLOOKUP($C69,'Team Fixtures'!$A$2:$Q$21,2,FALSE) -> 0.014214641 | AV69: =VLOOKUP($C69,'Team Fixtures'!$A$2:$V$21,20,FALSE) -> 0.87939146 | AW69: =VLOOKUP($C69,'Team Fixtures'!$A$2:$V$21,21,FALSE) -> -0.86517682 | AX69: =VLOOKUP($C69,'Team Fixtures'!$A$2:$V$21,22,FALSE) -> A | AY69: =IFERROR((2.926+0.578*AU69-0.576*AV69-0.561*AW69+0.469*IF(AX69="H",1,0))*$Y69,0) -> 0 | AZ69: =MAX(0, MIN(1, -0.021039 + 0.023522 * AY69)) -> 0 | BA69: =AY69+AZ69*2 -> 0 | BB69: =IFERROR(T69*1+AF69*0.85+AM69*0.7+AT69*0.55+BA69*0.4,0) -> 0
A70: ='Players Full'!CU70 -> Etienne Green | B70: =VLOOKUP(_xlfn.CONCAT('Players Full'!AK70,'Players Full'!BV70),'Players Summarised'!$A$1:$T$1000,20,0) -> GK | C70: =VLOOKUP('Players Full'!CF70,Teams!$A$1:$G$21,6,0) -> Burnley | D70: ='Players Full'!BD70/10 -> 4 | E70: =IFERROR(VLOOKUP($A70,'Starting Lineups'!$A$2:$C$510,3,FALSE),0) -> 0 | F70: =VLOOKUP(A70,'Score & Assist'!$A$1:$G$2000,6,0) -> #N/A | G70: =IF(F70<0.3, 0.01,IF(F70=0.3,0.03,IF(F70<0.5,0.05,IF(F70<0.55,0.06,IF(F70<0.57,0.1,IF(F70<0.58,0.11,IF(F70<0.59,0.12,IF(F70<0.6,0.15,0.28)))))))) -> #N/A | H70: =IF(F70<0.3,0,IF(F70<0.55,0.01,IF(F70<0.59,0.02,IF(F70<0.6,0.03,0.11)))) -> #N/A | I70: =VLOOKUP(A70,'Score & Assist'!$A$1:$G$2000,7,0) -> #N/A | J70: =VLOOKUP(A70,'Yellow Card'!$C$1:$E$987,3,0) -> 0.13605442 | K70: =VLOOKUP(C70,'Team Clean Sheet'!$C$2:$F$21,4,0) -> 0.3546798 | L70: =VLOOKUP(C70,'Team Total Goals'!$D$2:$N$21,10,0) -> 0.29039301 | M70: =VLOOKUP(C70,'Team Total Goals'!$D$2:$N$21,11,0) -> 0.037393558 | N70: =VLOOKUP(A70,'Goalkeeper Saves'!$D$2:$N$15,10,0) -> #N/A | O70: =VLOOKUP(A70,'Goalkeeper Saves'!$D$2:$N$15,11,0) -> #N/A | P70: =IF(B70="DEF",IFERROR(VLOOKUP(A70,'Defensive Contribution - DEF'!A68:H566,8,FALSE),'Defensive Contribution - DEF'!K$2),0) -> 0 | Q70: =IF(B70="MID",IFERROR(VLOOKUP(A70,'Defensive Contribution - MID'!A$2:I$500,9,FALSE),'Defensive Contribution - MID'!L$2),0) -> 0 | R70: =IFERROR(IFERROR(E70,0)*IF(B70="GK",2+IFERROR(F70*10,0)+IFERROR(G70*10,0)+IFERROR(H70*10,0)+IFERROR(I70*3,0)-IFERROR(J70*1,0)+IFERROR(K70*4,0)+IFERROR(N70*1,0)+IFERROR(O70*1,0)-IFERROR(L70*2,0)-IFERROR(M70*2,0),IF(B70="DEF",2+IFERROR(F70*6,0)+IFERROR(G70*6,0)+IFERROR(H70*6,0)+IFERROR(I70*3,0)-IFERROR(J70*1,0)+IFERROR(K70*4,0)-IFERROR(L70*2,0)-IFERROR(M70*2,0)+IFERROR(P70*2,0),IF(B70="MID",2+IFERROR(F70*5,0)+IFERROR(G70*5,0)+IFERROR(H70*5,0)+IFERROR(I70*3,0)-IFERROR(J70*1,0)+IFERROR(K70*1,0)+IFERROR(Q70*2,0),IF(B70="FWD",2+IFERROR(F70*4,0)+IFERROR(G70*4,0)+IFERROR(H70*4,0)+IFERROR(I70*3,0)-IFERROR(J70*1,0),"ERROR")))),0) -> 0 | S70: =MAX(0, MIN(1, -0.021039 + 0.023522 * R70)) -> 0 | T70: =R70+S70*2 -> 0 | U70: =VLOOKUP($C70,'Team Fixtures'!$A$2:$Q$21,2,FALSE) -> 0.014214641 | V70: =VLOOKUP($C70,'Team Fixtures'!$A$2:$Q$21,4,FALSE) -> 0.018674136 | W70: =VLOOKUP($C70,'Team Fixtures'!$A$2:$Q$21,5,FALSE) -> -0.0044594952 | X70: =VLOOKUP($C70,'Team Fixtures'!$A$2:$Q$21,6,FALSE) -> H | Y70: =R70/(2.926+0.578*U70-0.576*V70-0.561*W70+0.469*IF(X70="H",1,0)) -> 0 | Z70: =VLOOKUP($C70,'Team Fixtures'!$A$2:$Q$21,2,FALSE) -> 0.014214641 | AA70: =VLOOKUP($C70,'Team Fixtures'!$A$2:$Q$21,8,FALSE) -> 0.52910053 | AB70: =VLOOKUP($C70,'Team Fixtures'!$A$2:$Q$21,9,FALSE) -> -0.51488589 | AC70: =VLOOKUP($C70,'Team Fixtures'!$A$2:$Q$21,10,FALSE) -> A | AD70: =IFERROR((2.926+0.578*Z70-0.576*AA70-0.561*AB70+0.469*IF(AC70="H",1,0))*$Y70,0) -> 0 | AE70: =MAX(0, MIN(1, -0.021039 + 0.023522 * AD70)) -> 0 | AF70: =AD70+AE70*2 -> 0 | AG70: =VLOOKUP($C70,'Team Fixtures'!$A$2:$Q$21,2,FALSE) -> 0.014214641 | AH70: =VLOOKUP($C70,'Team Fixtures'!$A$2:$Q$21,12,FALSE) -> 0.89678056 | AI70: =VLOOKUP($C70,'Team Fixtures'!$A$2:$Q$21,13,FALSE) -> -0.88256592 | AJ70: =VLOOKUP($C70,'Team Fixtures'!$A$2:$Q$21,14,FALSE) -> A | AK70: =IFERROR((2.926+0.578*AG70-0.576*AH70-0.561*AI70+0.469*IF(AJ70="H",1,0))*$Y70,0) -> 0 | AL70: =MAX(0, MIN(1, -0.021039 + 0.023522 * AK70)) -> 0 | AM70: =AK70+AL70*2 -> 0 | AN70: =VLOOKUP($C70,'Team Fixtures'!$A$2:$Q$21,2,FALSE) -> 0.014214641 | AO70: =VLOOKUP($C70,'Team Fixtures'!$A$2:$Q$21,16,FALSE) -> 0.10582011 | AP70: =VLOOKUP($C70,'Team Fixtures'!$A$2:$Q$21,17,FALSE) -> -0.091605465 | AQ70: =VLOOKUP($C70,'Team Fixtures'!$A$2:$V$21,18,FALSE) -> H | AR70: =IFERROR((2.926+0.578*AN70-0.576*AO70-0.561*AP70+0.469*IF(AQ70="H",1,0))*$Y70,0) -> 0 | AS70: =MAX(0, MIN(1, -0.021039 + 0.023522 * AR70)) -> 0 | AT70: =AR70+AS70*2 -> 0 | AU70: =VLOOKUP($C70,'Team Fixtures'!$A$2:$Q$21,2,FALSE) -> 0.014214641 | AV70: =VLOOKUP($C70,'Team Fixtures'!$A$2:$V$21,20,FALSE) -> 0.87939146 | AW70: =VLOOKUP($C70,'Team Fixtures'!$A$2:$V$21,21,FALSE) -> -0.86517682 | AX70: =VLOOKUP($C70,'Team Fixtures'!$A$2:$V$21,22,FALSE) -> A | AY70: =IFERROR((2.926+0.578*AU70-0.576*AV70-0.561*AW70+0.469*IF(AX70="H",1,0))*$Y70,0) -> 0 | AZ70: =MAX(0, MIN(1, -0.021039 + 0.023522 * AY70)) -> 0 | BA70: =AY70+AZ70*2 -> 0 | BB70: =IFERROR(T70*1+AF70*0.85+AM70*0.7+AT70*0.55+BA70*0.4,0) -> 0
... A701: ='Players Full'!CU701 | B701: =VLOOKUP(_xlfn.CONCAT('Players Full'!AK701,'Players Full'!BV701),'Players Summarised'!$A$1:$T$1000,20,0) -> 0 | C701: =VLOOKUP('Players Full'!CF701,Teams!$A$1:$G$21,6,0) -> #N/A | D701: ='Players Full'!BD701/10 -> 0 | E701: =IFERROR(VLOOKUP($A701,'Starting Lineups'!$A$2:$C$510,3,FALSE),0) -> 0 | F701: =VLOOKUP(A701,'Score & Assist'!$A$1:$G$2000,6,0) -> #N/A | G701: =IF(F701<0.3, 0.01,IF(F701=0.3,0.03,IF(F701<0.5,0.05,IF(F701<0.55,0.06,IF(F701<0.57,0.1,IF(F701<0.58,0.11,IF(F701<0.59,0.12,IF(F701<0.6,0.15,0.28)))))))) -> #N/A | H701: =IF(F701<0.3,0,IF(F701<0.55,0.01,IF(F701<0.59,0.02,IF(F701<0.6,0.03,0.11)))) -> #N/A | I701: =VLOOKUP(A701,'Score & Assist'!$A$1:$G$2000,7,0) -> #N/A | J701: =VLOOKUP(A701,'Yellow Card'!$C$1:$E$987,3,0) -> #N/A | K701: =VLOOKUP(C701,'Team Clean Sheet'!$C$2:$F$21,4,0) -> #N/A | L701: =VLOOKUP(C701,'Team Total Goals'!$D$2:$N$21,10,0) -> #N/A | M701: =VLOOKUP(C701,'Team Total Goals'!$D$2:$N$21,11,0) -> #N/A | N701: =VLOOKUP(A701,'Goalkeeper Saves'!$D$2:$N$15,10,0) -> #N/A | O701: =VLOOKUP(A701,'Goalkeeper Saves'!$D$2:$N$15,11,0) -> #N/A | P701: =IF(B701="DEF",IFERROR(VLOOKUP(A701,'Defensive Contribution - DEF'!A699:H1197,8,FALSE),'Defensive Contribution - DEF'!K$2),0) -> 0 | Q701: =IF(B701="MID",IFERROR(VLOOKUP(A701,'Defensive Contribution - MID'!A$2:I$500,9,FALSE),'Defensive Contribution - MID'!L$2),0) -> 0 | R701: =IFERROR(IFERROR(E701,0)*IF(B701="GK",2+IFERROR(F701*10,0)+IFERROR(G701*10,0)+IFERROR(H701*10,0)+IFERROR(I701*3,0)-IFERROR(J701*1,0)+IFERROR(K701*4,0)+IFERROR(N701*1,0)+IFERROR(O701*1,0)-IFERROR(L701*2,0)-IFERROR(M701*2,0),IF(B701="DEF",2+IFERROR(F701*6,0)+IFERROR(G701*6,0)+IFERROR(H701*6,0)+IFERROR(I701*3,0)-IFERROR(J701*1,0)+IFERROR(K701*4,0)-IFERROR(L701*2,0)-IFERROR(M701*2,0)+IFERROR(P701*2,0),IF(B701="MID",2+IFERROR(F701*5,0)+IFERROR(G701*5,0)+IFERROR(H701*5,0)+IFERROR(I701*3,0)-IFERROR(J701*1,0)+IFERROR(K701*1,0)+IFERROR(Q701*2,0),IF(B701="FWD",2+IFERROR(F701*4,0)+IFERROR(G701*4,0)+IFERROR(H701*4,0)+IFERROR(I701*3,0)-IFERROR(J701*1,0),"ERROR")))),0) -> 0 | S701: =MAX(0, MIN(1, -0.021039 + 0.023522 * R701)) -> 0 | T701: =R701+S701*2 -> 0 | U701: =VLOOKUP($C701,'Team Fixtures'!$A$2:$Q$21,2,FALSE) -> #N/A | V701: =VLOOKUP($C701,'Team Fixtures'!$A$2:$Q$21,4,FALSE) -> #N/A | W701: =VLOOKUP($C701,'Team Fixtures'!$A$2:$Q$21,5,FALSE) -> #N/A | X701: =VLOOKUP($C701,'Team Fixtures'!$A$2:$Q$21,6,FALSE) -> #N/A | Y701: =R701/(2.926+0.578*U701-0.576*V701-0.561*W701+0.469*IF(X701="H",1,0)) -> #N/A | Z701: =VLOOKUP($C701,'Team Fixtures'!$A$2:$Q$21,2,FALSE) -> #N/A | AA701: =VLOOKUP($C701,'Team Fixtures'!$A$2:$Q$21,8,FALSE) -> #N/A | AB701: =VLOOKUP($C701,'Team Fixtures'!$A$2:$Q$21,9,FALSE) -> #N/A | AC701: =VLOOKUP($C701,'Team Fixtures'!$A$2:$Q$21,10,FALSE) -> #N/A | AD701: =IFERROR((2.926+0.578*Z701-0.576*AA701-0.561*AB701+0.469*IF(AC701="H",1,0))*$Y701,0) -> 0 | AE701: =MAX(0, MIN(1, -0.021039 + 0.023522 * AD701)) -> 0 | AF701: =AD701+AE701*2 -> 0 | AG701: =VLOOKUP($C701,'Team Fixtures'!$A$2:$Q$21,2,FALSE) -> #N/A | AH701: =VLOOKUP($C701,'Team Fixtures'!$A$2:$Q$21,12,FALSE) -> #N/A | AI701: =VLOOKUP($C701,'Team Fixtures'!$A$2:$Q$21,13,FALSE) -> #N/A | AJ701: =VLOOKUP($C701,'Team Fixtures'!$A$2:$Q$21,14,FALSE) -> #N/A | AK701: =IFERROR((2.926+0.578*AG701-0.576*AH701-0.561*AI701+0.469*IF(AJ701="H",1,0))*$Y701,0) -> 0 | AL701: =MAX(0, MIN(1, -0.021039 + 0.023522 * AK701)) -> 0 | AM701: =AK701+AL701*2 -> 0 | AN701: =VLOOKUP($C701,'Team Fixtures'!$A$2:$Q$21,2,FALSE) -> #N/A | AO701: =VLOOKUP($C701,'Team Fixtures'!$A$2:$Q$21,16,FALSE) -> #N/A | AP701: =VLOOKUP($C701,'Team Fixtures'!$A$2:$Q$21,17,FALSE) -> #N/A | AQ701: =VLOOKUP($C701,'Team Fixtures'!$A$2:$V$21,18,FALSE) -> #N/A | AR701: =IFERROR((2.926+0.578*AN701-0.576*AO701-0.561*AP701+0.469*IF(AQ701="H",1,0))*$Y701,0) -> 0 | AS701: =MAX(0, MIN(1, -0.021039 + 0.023522 * AR701)) -> 0 | AT701: =AR701+AS701*2 -> 0 | AU701: =VLOOKUP($C701,'Team Fixtures'!$A$2:$Q$21,2,FALSE) -> #N/A | AV701: =VLOOKUP($C701,'Team Fixtures'!$A$2:$V$21,20,FALSE) -> #N/A | AW701: =VLOOKUP($C701,'Team Fixtures'!$A$2:$V$21,21,FALSE) -> #N/A | AX701: =VLOOKUP($C701,'Team Fixtures'!$A$2:$V$21,22,FALSE) -> #N/A | AY701: =IFERROR((2.926+0.578*AU701-0.576*AV701-0.561*AW701+0.469*IF(AX701="H",1,0))*$Y701,0) -> 0 | AZ701: =MAX(0, MIN(1, -0.021039 + 0.023522 * AY701)) -> 0 | BA701: =AY701+AZ701*2 -> 0 | BB701: =IFERROR(T701*1+AF701*0.85+AM701*0.7+AT701*0.55+BA701*0.4,0) -> 0

Sheet Starting Lineups
A1: Player | B1: Team | C1: Starting Prob | D1: XP | F1: Row Labels | G1: Count of Player | H1: Sum of Starting Prob | I1: Count of XP
A2: David Raya | B2: Arsenal | C2: 1 | D2: =IFERROR(VLOOKUP(A2,Players!A$2:Z$1000,20,FALSE),"") -> 3.8886759 | F2: Arsenal | G2: 11 | H2: 10.5 | I2: 11
A3: Ben White | B3: Arsenal | C3: 1 | D3: =IFERROR(VLOOKUP(A3,Players!A$2:Z$1000,20,FALSE),"") -> 4.9076243 | F3: Aston Villa | G3: 11 | H3: 11 | I3: 11
A4: Gabriel Magalhaes | B4: Arsenal | C4: 1 | D4: =IFERROR(VLOOKUP(A4,Players!A$2:Z$1000,20,FALSE),"") -> 5.257717 | F4: Bournemouth | G4: 11 | H4: 11 | I4: 11
A5: William Saliba | B5: Arsenal | C5: 1 | D5: =IFERROR(VLOOKUP(A5,Players!A$2:Z$1000,20,FALSE),"") -> 4.7045805 | F5: Brentford | G5: 12 | H5: 11 | I5: 12
A6: Myles Lewis-Skelly | B6: Arsenal | C6: 1 | D6: =IFERROR(VLOOKUP(A6,Players!A$2:Z$1000,20,FALSE),"") -> 4.8097611 | F6: Brighton | G6: 11 | H6: 11 | I6: 11
A7: Martin Odegaard | B7: Arsenal | C7: 1 | D7: =IFERROR(VLOOKUP(A7,Players!A$2:Z$1000,20,FALSE),"") -> 6.3502271 | F7: Burnley | G7: 12 | H7: 11 | I7: 12
A8: Martin Zubimendi | B8: Arsenal | C8: 1 | D8: =IFERROR(VLOOKUP(A8,Players!A$2:Z$1000,20,FALSE),"") -> 4.9629327 | F8: Chelsea | G8: 11 | H8: 11 | I8: 11
A9: Declan Rice | B9: Arsenal | C9: 1 | D9: =IFERROR(VLOOKUP(A9,Players!A$2:Z$1000,20,FALSE),"") -> 5.2604573 | F9: Crystal Palace | G9: 11 | H9: 11 | I9: 11
A10: Bukayo Saka | B10: Arsenal | C10: 1 | D10: =IFERROR(VLOOKUP(A10,Players!A$2:Z$1000,20,FALSE),"") -> 7.1535915 | F10: Everton | G10: 11 | H10: 11 | I10: 11
A11: Gabriel Martinelli | B11: Arsenal | C11: 0.5 | D11: =IFERROR(VLOOKUP(A11,Players!A$2:Z$1000,20,FALSE),"") -> 3.178413 | F11: Fulham | G11: 12 | H11: 11 | I11: 12
A12: Viktor Gyokeres | B12: Arsenal | C12: 1 | D12: =IFERROR(VLOOKUP(A12,Players!A$2:Z$1000,20,FALSE),"") -> 5.8308333 | F12: Leeds | G12: 11 | H12: 11 | I12: 11
A13: Marco Bizot | B13: Aston Villa | C13: 1 | D13: =IFERROR(VLOOKUP(A13,Players!A$2:Z$1000,20,FALSE),"") -> 2.3281514 | F13: Liverpool | G13: 12 | H13: 11 | I13: 12
... A21: John McGinn | B21: Aston Villa | C21: 1 | D21: =IFERROR(VLOOKUP(A21,Players!A$2:Z$1000,20,FALSE),"") -> 4.2549451 | F21: Wolves | G21: 11 | H21: 11 | I21: 11
A22: Youri Tielemans | B22: Aston Villa | C22: 1 | D22: =IFERROR(VLOOKUP(A22,Players!A$2:Z$1000,20,FALSE),"") -> 4.1894103
A23: Ollie Watkins | B23: Aston Villa | C23: 1 | D23: =IFERROR(VLOOKUP(A23,Players!A$2:Z$1000,20,FALSE),"") -> 4.2987024
A24: Djordje Petrovic | B24: Bournemouth | C24: 1 | D24: =IFERROR(VLOOKUP(A24,Players!A$2:Z$1000,20,FALSE),"") -> 3.3885113
A25: Julian Araujo | B25: Bournemouth | C25: 1 | D25: =IFERROR(VLOOKUP(A25,Players!A$2:Z$1000,20,FALSE),"") -> 4.2651216
A26: James Hill | B26: Bournemouth | C26: 1 | D26: =IFERROR(VLOOKUP(A26,Players!A$2:Z$1000,20,FALSE),"") -> 4.3181674
A27: Marcos Senesi | B27: Bournemouth | C27: 1 | D27: =IFERROR(VLOOKUP(A27,Players!A$2:Z$1000,20,FALSE),"") -> 4.5189711
A28: Adrien Truffert | B28: Bournemouth | C28: 1 | D28: =IFERROR(VLOOKUP(A28,Players!A$2:Z$1000,20,FALSE),"") -> 4.4428155
A29: Marcus Tavernier | B29: Bournemouth | C29: 1 | D29: =IFERROR(VLOOKUP(A29,Players!A$2:Z$1000,20,FALSE),"") -> 4.9757144
A30: Tyler Adams | B30: Bournemouth | C30: 1 | D30: =IFERROR(VLOOKUP(A30,Players!A$2:Z$1000,20,FALSE),"") -> 4.2332477
A31: David Brooks | B31: Bournemouth | C31: 1 | D31: =IFERROR(VLOOKUP(A31,Players!A$2:Z$1000,20,FALSE),"") -> 5.7202279
A32: Alex Scott | B32: Bournemouth | C32: 1 | D32: =IFERROR(VLOOKUP(A32,Players!A$2:Z$1000,20,FALSE),"") -> 5.0342245
A33: Antoine Semenyo | B33: Bournemouth | C33: 1 | D33: =IFERROR(VLOOKUP(A33,Players!A$2:Z$1000,20,FALSE),"") -> 5.6719686
... A227: Jorgen Larsen | B227: Wolves | C227: 1 | D227: =IFERROR(VLOOKUP(A227,Players!A$2:Z$1000,20,FALSE),"") -> 3.314256

Sheet GW Teams
A1: Position | B1: GW1
A2: GK | B2: Lucas Perri
A3: GK | B3: Alphonse Areola
A4: DEF | B4: Jeremie Frimpong
A5: DEF | B5: Rayan Ait Nouri
A6: DEF | B6: Maxim De Cuyper
A7: DEF | B7: El Hadji Diouf
A8: DEF | B8: Gabriel Gudmundsson
A9: MID | B9: Mohamed Salah
A10: MID | B10: Bukayo Saka
A11: MID | B11: Florian Wirtz
A12: MID | B12: Kaoru Mitoma
... A16: FWD | B16: Lyle Foster

Sheet Player Names Cleaned
A1: name | B1: name_cleaned
A2: David Raya MartÃ­n | B2: David Raya
A3: Kepa Arrizabalaga Revuelta | B3: Kepa Arrizabalaga
A4: Gabriel dos Santos MagalhÃ£es | B4: Gabriel Magalhaes
A5: Benjamin White | B5: Ben White
A6: Martin Ã˜degaard | B6: Martin Odegaard
A7: Gabriel Martinelli Silva | B7: Gabriel Martinelli
A8: MartÃ­n Zubimendi IbÃ¡Ã±ez | B8: Martin Zubimendi
A9: Viktor GyÃ¶keres | B9: Viktor Gyokeres
A10: Ezri Konsa Ngoyo | B10: Ezri Konsa
A11: Max WeiÃŸ | B11: Max Weiss
A12: Maxime EstÃ¨ve | B12: Maxime Esteve
... A84: Mikel Merino ZazÃ³n | B84: Mikel Merino

Sheet Players Full
A1: assists | B1: birth_date | C1: bonus | D1: bps | E1: can_select | F1: can_transact | G1: chance_of_playing_next_round | H1: chance_of_playing_this_round | I1: clean_sheets | J1: clean_sheets_per_90 | K1: code | L1: corners_and_indirect_freekicks_order | M1: corners_and_indirect_freekicks_text | N1: cost_change_event | O1: cost_change_event_fall | P1: cost_change_start | Q1: cost_change_start_fall | R1: creativity | S1: creativity_rank | T1: creativity_rank_type | U1: defensive_contribution | V1: direct_freekicks_order | W1: direct_freekicks_text | X1: dreamteam_count | Y1: element_type | Z1: ep_next | AA1: ep_this | AB1: event_points | AC1: expected_assists | AD1: expected_assists_per_90 | AE1: expected_goal_involvements | AF1: expected_goal_involvements_per_90 | AG1: expected_goals | AH1: expected_goals_conceded | AI1: expected_goals_conceded_per_90 | AJ1: expected_goals_per_90 | AK1: first_name | AL1: form | AM1: form_rank | AN1: form_rank_type | AO1: goals_conceded | AP1: goals_conceded_per_90 | AQ1: goals_scored | AR1: has_temporary_code | AS1: ict_index | AT1: ict_index_rank | AU1: ict_index_rank_type | AV1: id | AW1: in_dreamteam | AX1: influence | AY1: influence_rank | AZ1: influence_rank_type | BA1: minutes | BB1: news | BC1: news_added | BD1: now_cost | BE1: now_cost_rank | BF1: now_cost_rank_type | BG1: opta_code | BH1: own_goals | BI1: penalties_missed | BJ1: penalties_order | BK1: penalties_saved | BL1: penalties_text | BM1: photo | BN1: points_per_game | BO1: points_per_game_rank | BP1: points_per_game_rank_type | BQ1: red_cards | BR1: region | BS1: removed | BT1: saves | BU1: saves_per_90 | BV1: second_name | BW1: selected_by_percent | BX1: selected_rank | BY1: selected_rank_type | BZ1: special | CA1: squad_number | CB1: starts | CC1: starts_per_90 | CD1: status | CE1: team | CF1: team_code | CG1: team_join_date | CH1: threat | CI1: threat_rank | CJ1: threat_rank_type | CK1: total_points | CL1: transfers_in | CM1: transfers_in_event | CN1: transfers_out | CO1: transfers_out_event | CP1: value_form | CQ1: value_season | CR1: web_name | CS1: yellow_cards | CT1: name | CU1: name_cleaned
A2: 0 | B2: 34957 | C2: 10 | D2: 555 | E2: TRUE | F2: TRUE | G2: None | H2: None | I2: 13 | J2: 0.34 | K2: 154561 | L2: None | N2: 0 | O2: 0 | P2: 0 | Q2: 0 | R2: 10.7 | S2: 342 | T2: 11 | U2: 0 | V2: None | X2: 0 | Y2: 1 | Z2: 4.5 | AA2: None | AB2: 0 | AC2: 0.03 | AD2: 0 | AE2: 0.03 | AF2: 0 | AG2: 0 | AH2: 35.03 | AI2: 0.92 | AJ2: 0 | AK2: David | AL2: 0 | AM2: 475 | AN2: 76 | AO2: 34 | AP2: 0.89 | AQ2: 0 | AR2: FALSE | AS2: 76.7 | AT2: 178 | AU2: 8 | AV2: 1 | AW2: FALSE | AX2: 755.4 | AY2: 37 | AZ2: 8 | BA2: 3420 | BC2: None | BD2: 55 | BE2: 125 | BF2: 4 | BG2: p154561 | BH2: 0 | BI2: 0 | BJ2: None | BK2: 0 | BM2: 154561.jpg | BN2: 3.7 | BO2: 68 | BP2: 11 | BQ2: 0 | BR2: 200 | BS2: FALSE | BT2: 86 | BU2: 2.26 | BV2: Raya MartÃ­n | BW2: 18.4 | BX2: 20 | BY2: 2 | BZ2: FALSE | CA2: None | CB2: 38 | CC2: 1 | CD2: a | CE2: 1 | CF2: 3 | CG2: 45477 | CH2: 0 | CI2: 634 | CJ2: 76 | CK2: 142 | CL2: 0 | CM2: 0 | CN2: 0 | CO2: 0 | CP2: 0 | CQ2: 25.8 | CR2: Raya | CS2: 3 | CT2: =_xlfn.CONCAT(AK2," ",BV2) -> David Raya MartÃ­n | CU2: =IFERROR(VLOOKUP(CT2,'Player Names Cleaned'!$A$1:$B$997,2,0),CT2) -> David Raya
A3: 0 | B3: 34610 | C3: 7 | D3: 406 | E3: TRUE | F3: TRUE | G3: None | H3: None | I3: 8 | J3: 0.26 | K3: 109745 | L3: None | N3: 0 | O3: 0 | P3: 0 | Q3: 0 | R3: 10.4 | S3: 344 | T3: 12 | U3: 0 | V3: None | X3: 0 | Y3: 1 | Z3: 2.8 | AA3: None | AB3: 0 | AC3: 0.03 | AD3: 0 | AE3: 0.09 | AF3: 0 | AG3: 0.06 | AH3: 38.83 | AI3: 1.25 | AJ3: 0 | AK3: Kepa | AL3: 0 | AM3: 143 | AN3: 50 | AO3: 39 | AP3: 1.26 | AQ3: 0 | AR3: FALSE | AS3: 75.8 | AT3: 183 | AU3: 9 | AV3: 2 | AW3: FALSE | AX3: 744.4 | AY3: 38 | AZ3: 9 | BA3: 2790 | BC3: None | BD3: 45 | BE3: 365 | BF3: 21 | BG3: p109745 | BH3: 0 | BI3: 0 | BJ3: None | BK3: 0 | BM3: 109745.jpg | BN3: 3.4 | BO3: 94 | BP3: 16 | BQ3: 0 | BR3: 200 | BS3: FALSE | BT3: 97 | BU3: 3.13 | BV3: Arrizabalaga Revuelta | BW3: 1 | BX3: 188 | BY3: 28 | BZ3: FALSE | CA3: None | CB3: 31 | CC3: 1 | CD3: a | CE3: 1 | CF3: 3 | CG3: 45839 | CH3: 4 | CI3: 333 | CJ3: 1 | CK3: 106 | CL3: 0 | CM3: 0 | CN3: 0 | CO3: 0 | CP3: 0 | CQ3: 23.6 | CR3: Arrizabalaga | CS3: 3 | CT3: =_xlfn.CONCAT(AK3," ",BV3) -> Kepa Arrizabalaga Revuelta | CU3: =IFERROR(VLOOKUP(CT3,'Player Names Cleaned'!$A$1:$B$997,2,0),CT3) -> Kepa Arrizabalaga
A4: 0 | B4: 37359 | C4: 0 | D4: 0 | E4: TRUE | F4: TRUE | G4: None | H4: None | I4: 0 | J4: 0 | K4: 463748 | L4: None | N4: 0 | O4: 0 | P4: 0 | Q4: 0 | R4: 0 | S4: 426 | T4: 45 | U4: 0 | V4: None | X4: 0 | Y4: 1 | Z4: 1.5 | AA4: None | AB4: 0 | AC4: 0 | AD4: 0 | AE4: 0 | AF4: 0 | AG4: 0 | AH4: 0 | AI4: 0 | AJ4: 0 | AK4: Karl | AL4: 0 | AM4: 57 | AN4: 28 | AO4: 0 | AP4: 0 | AQ4: 0 | AR4: FALSE | AS4: 0 | AT4: 436 | AU4: 54 | AV4: 3 | AW4: FALSE | AX4: 0 | AY4: 436 | AZ4: 54 | BA4: 0 | BC4: None | BD4: 40 | BE4: 601 | BF4: 60 | BG4: p463748 | BH4: 0 | BI4: 0 | BJ4: None | BK4: 0 | BM4: 463748.jpg | BN4: 0 | BO4: 439 | BP4: 54 | BQ4: 0 | BR4: 67 | BS4: FALSE | BT4: 0 | BU4: 0 | BV4: Hein | BW4: 0.6 | BX4: 232 | BY4: 32 | BZ4: FALSE | CA4: None | CB4: 0 | CC4: 0 | CD4: a | CE4: 1 | CF4: 3 | CG4: 44132 | CH4: 0 | CI4: 395 | CJ4: 30 | CK4: 0 | CL4: 0 | CM4: 0 | CN4: 0 | CO4: 0 | CP4: 0 | CQ4: 0 | CR4: Hein | CS4: 0 | CT4: =_xlfn.CONCAT(AK4," ",BV4) -> Karl Hein | CU4: =IFERROR(VLOOKUP(CT4,'Player Names Cleaned'!$A$1:$B$997,2,0),CT4) -> Karl Hein
A5: 0 | B5: 38789 | C5: 0 | D5: 0 | E5: TRUE | F5: TRUE | G5: None | H5: None | I5: 0 | J5: 0 | K5: 551221 | L5: None | N5: 0 | O5: 0 | P5: 0 | Q5: 0 | R5: 0 | S5: 461 | T5: 56 | U5: 0 | V5: None | X5: 0 | Y5: 1 | Z5: 1.5 | AA5: None | AB5: 0 | AC5: 0 | AD5: 0 | AE5: 0 | AF5: 0 | AG5: 0 | AH5: 0 | AI5: 0 | AJ5: 0 | AK5: Tommy | AL5: 0 | AM5: 100 | AN5: 41 | AO5: 0 | AP5: 0 | AQ5: 0 | AR5: FALSE | AS5: 0 | AT5: 470 | AU5: 65 | AV5: 4 | AW5: FALSE | AX5: 0 | AY5: 470 | AZ5: 65 | BA5: 0 | BC5: None | BD5: 40 | BE5: 644 | BF5: 73 | BG5: p551221 | BH5: 0 | BI5: 0 | BJ5: None | BK5: 0 | BM5: 551221.jpg | BN5: 0 | BO5: 473 | BP5: 65 | BQ5: 0 | BR5: 241 | BS5: FALSE | BT5: 0 | BU5: 0 | BV5: Setford | BW5: 0.2 | BX5: 447 | BY5: 61 | BZ5: FALSE | CA5: None | CB5: 0 | CC5: 0 | CD5: a | CE5: 1 | CF5: 3 | CG5: 45497 | CH5: 0 | CI5: 435 | CJ5: 43 | CK5: 0 | CL5: 0 | CM5: 0 | CN5: 0 | CO5: 0 | CP5: 0 | CQ5: 0 | CR5: Setford | CS5: 0 | CT5: =_xlfn.CONCAT(AK5," ",BV5) -> Tommy Setford | CU5: =IFERROR(VLOOKUP(CT5,'Player Names Cleaned'!$A$1:$B$997,2,0),CT5) -> Tommy Setford
A6: 2 | B6: 35783 | C6: 9 | D6: 459 | E6: TRUE | F6: TRUE | G6: None | H6: None | I6: 10 | J6: 0.38 | K6: 226597 | L6: None | N6: 0 | O6: 0 | P6: 0 | Q6: 0 | R6: 208.8 | S6: 167 | T6: 36 | U6: 0 | V6: None | X6: 0 | Y6: 2 | Z6: 4.5 | AA6: None | AB6: 0 | AC6: 1.21 | AD6: 0.05 | AE6: 3.91 | AF6: 0.15 | AG6: 2.7 | AH6: 23.09 | AI6: 0.88 | AJ6: 0.1 | AK6: Gabriel | AL6: 0 | AM6: 577 | AN6: 218 | AO6: 22 | AP6: 0.84 | AQ6: 3 | AR6: FALSE | AS6: 108.2 | AT6: 121 | AU6: 31 | AV6: 5 | AW6: FALSE | AX6: 584.6 | AY6: 96 | AZ6: 32 | BA6: 2363 | BC6: None | BD6: 60 | BE6: 96 | BF6: 5 | BG6: p226597 | BH6: 0 | BI6: 0 | BJ6: None | BK6: 0 | BM6: 226597.jpg | BN6: 4.2 | BO6: 32 | BP6: 1 | BQ6: 0 | BR6: 30 | BS6: FALSE | BT6: 0 | BU6: 0 | BV6: dos Santos MagalhÃ£es | BW6: 24.9 | BX6: 11 | BY6: 4 | BZ6: FALSE | CA6: None | CB6: 28 | CC6: 1.07 | CD6: a | CE6: 1 | CF6: 3 | CG6: 44075 | CH6: 287 | CI6: 107 | CJ6: 12 | CK6: 117 | CL6: 0 | CM6: 0 | CN6: 0 | CO6: 0 | CP6: 0 | CQ6: 19.5 | CR6: Gabriel | CS6: 4 | CT6: =_xlfn.CONCAT(AK6," ",BV6) -> Gabriel dos Santos MagalhÃ£es | CU6: =IFERROR(VLOOKUP(CT6,'Player Names Cleaned'!$A$1:$B$997,2,0),CT6) -> Gabriel Magalhaes
A7: 0 | B7: 36974 | C7: 14 | D7: 564 | E7: TRUE | F7: TRUE | G7: None | H7: None | I7: 12 | J7: 0.36 | K7: 462424 | L7: None | N7: 0 | O7: 0 | P7: 0 | Q7: 0 | R7: 150.1 | S7: 203 | T7: 55 | U7: 0 | V7: None | X7: 0 | Y7: 2 | Z7: 4.5 | AA7: None | AB7: 0 | AC7: 1.28 | AD7: 0.04 | AE7: 3.7 | AF7: 0.11 | AG7: 2.42 | AH7: 30.32 | AI7: 0.9 | AJ7: 0.07 | AK7: William | AL7: 0 | AM7: 582 | AN7: 220 | AO7: 29 | AP7: 0.86 | AQ7: 2 | AR7: FALSE | AS7: 94.2 | AT7: 139 | AU7: 36 | AV7: 6 | AW7: FALSE | AX7: 672.6 | AY7: 59 | AZ7: 21 | BA7: 3039 | BC7: None | BD7: 60 | BE7: 101 | BF7: 7 | BG7: p462424 | BH7: 0 | BI7: 0 | BJ7: None | BK7: 0 | BM7: 462424.jpg | BN7: 3.7 | BO7: 70 | BP7: 11 | BQ7: 1 | BR7: 73 | BS7: FALSE | BT7: 0 | BU7: 0 | BV7: Saliba | BW7: 13.6 | BX7: 31 | BY7: 11 | BZ7: FALSE | CA7: None | CB7: 35 | CC7: 1.04 | CD7: a | CE7: 1 | CF7: 3 | CG7: 43671 | CH7: 116 | CI7: 209 | CJ7: 62 | CK7: 130 | CL7: 0 | CM7: 0 | CN7: 0 | CO7: 0 | CP7: 0 | CQ7: 21.7 | CR7: Saliba | CS7: 2 | CT7: =_xlfn.CONCAT(AK7," ",BV7) -> William Saliba | CU7: =IFERROR(VLOOKUP(CT7,'Player Names Cleaned'!$A$1:$B$997,2,0),CT7) -> William Saliba
A8: 1 | B8: 37395 | C8: 1 | D8: 142 | E8: TRUE | F8: TRUE | G8: None | H8: None | I8: 1 | J8: 0.09 | K8: 466075 | L8: None | N8: 0 | O8: 0 | P8: 0 | Q8: 0 | R8: 118.2 | S8: 221 | T8: 65 | U8: 0 | V8: None | X8: 0 | Y8: 2 | Z8: 3.8 | AA8: None | AB8: 0 | AC8: 0.69 | AD8: 0.06 | AE8: 1.55 | AF8: 0.14 | AG8: 0.86 | AH8: 10.28 | AI8: 0.95 | AJ8: 0.08 | AK8: Riccardo | AL8: 0 | AM8: 526 | AN8: 207 | AO8: 12 | AP8: 1.1 | AQ8: 2 | AR8: FALSE | AS8: 54.6 | AT8: 230 | AU8: 68 | AV8: 7 | AW8: FALSE | AX8: 252.6 | AY8: 222 | AZ8: 80 | BA8: 978 | BC8: None | BD8: 55 | BE8: 176 | BF8: 25 | BG8: p466075 | BH8: 0 | BI8: 0 | BJ8: None | BK8: 0 | BM8: 466075.jpg | BN8: 2.1 | BO8: 236 | BP8: 83 | BQ8: 0 | BR8: 106 | BS8: FALSE | BT8: 0 | BU8: 0 | BV8: Calafiori | BW8: 0.6 | BX8: 235 | BY8: 80 | BZ8: FALSE | CA8: None | CB8: 11 | CC8: 1.01 | CD8: a | CE8: 1 | CF8: 3 | CG8: 45502 | CH8: 176 | CI8: 167 | CJ8: 35 | CK8: 39 | CL8: 0 | CM8: 0 | CN8: 0 | CO8: 0 | CP8: 0 | CQ8: 7.1 | CR8: Calafiori | CS8: 4 | CT8: =_xlfn.CONCAT(AK8," ",BV8) -> Riccardo Calafiori | CU8: =IFERROR(VLOOKUP(CT8,'Player Names Cleaned'!$A$1:$B$997,2,0),CT8) -> Riccardo Calafiori
A9: 3 | B9: 37059 | C9: 9 | D9: 426 | E9: TRUE | F9: TRUE | G9: None | H9: None | I9: 11 | J9: 0.41 | K9: 445122 | L9: None | N9: 0 | O9: 0 | P9: 0 | Q9: 0 | R9: 296.8 | S9: 123 | T9: 24 | U9: 0 | V9: None | X9: 0 | Y9: 2 | Z9: 3.8 | AA9: None | AB9: 0 | AC9: 1.3 | AD9: 0.05 | AE9: 2.53 | AF9: 0.1 | AG9: 1.23 | AH9: 21.09 | AI9: 0.79 | AJ9: 0.05 | AK9: JurriÃ«n | AL9: 0 | AM9: 522 | AN9: 205 | AO9: 21 | AP9: 0.78 | AQ9: 1 | AR9: FALSE | AS9: 94.2 | AT9: 138 | AU9: 35 | AV9: 8 | AW9: FALSE | AX9: 393 | AY9: 162 | AZ9: 56 | BA9: 2415 | BC9: None | BD9: 55 | BE9: 172 | BF9: 23 | BG9: p445122 | BH9: 0 | BI9: 0 | BJ9: None | BK9: 0 | BM9: 445122.jpg | BN9: 3.8 | BO9: 59 | BP9: 6 | BQ9: 0 | BR9: 152 | BS9: FALSE | BT9: 0 | BU9: 0 | BV9: Timber | BW9: 2.4 | BX9: 117 | BY9: 38 | BZ9: FALSE | CA9: None | CB9: 27 | CC9: 1.01 | CD9: a | CE9: 1 | CF9: 3 | CG9: 45121 | CH9: 254 | CI9: 117 | CJ9: 15 | CK9: 114 | CL9: 0 | CM9: 0 | CN9: 0 | CO9: 0 | CP9: 0 | CQ9: 20.7 | CR9: J.Timber | CS9: 7 | CT9: =_xlfn.CONCAT(AK9," ",BV9) -> JurriÃ«n Timber | CU9: =IFERROR(VLOOKUP(CT9,'Player Names Cleaned'!$A$1:$B$997,2,0),CT9) -> Jurrian Timber
A10: 0 | B10: 36571 | C10: 2 | D10: 178 | E10: TRUE | F10: TRUE | G10: None | H10: None | I10: 3 | J10: 0.24 | K10: 440854 | L10: None | N10: 0 | O10: 0 | P10: 0 | Q10: 0 | R10: 91.3 | S10: 244 | T10: 82 | U10: 0 | V10: None | X10: 0 | Y10: 2 | Z10: 3.8 | AA10: None | AB10: 0 | AC10: 0.29 | AD10: 0.02 | AE10: 0.46 | AF10: 0.03 | AG10: 0.17 | AH10: 14.71 | AI10: 1.19 | AJ10: 0.01 | AK10: Jakub | AL10: 0 | AM10: 517 | AN10: 203 | AO10: 15 | AP10: 1.21 | AQ10: 1 | AR10: FALSE | AS10: 39.2 | AT10: 261 | AU10: 88 | AV10: 9 | AW10: FALSE | AX10: 267.2 | AY10: 214 | AZ10: 77 | BA10: 1117 | BC10: None | BD10: 55 | BE10: 167 | BF10: 21 | BG10: p440854 | BH10: 0 | BI10: 0 | BJ10: None | BK10: 0 | BM10: 440854.jpg | BN10: 2.5 | BO10: 187 | BP10: 65 | BQ10: 0 | BR10: 172 | BS10: FALSE | BT10: 0 | BU10: 0 | BV10: Kiwior | BW10: 0.1 | BX10: 503 | BY10: 193 | BZ10: FALSE | CA10: None | CB10: 10 | CC10: 0.81 | CD10: a | CE10: 1 | CF10: 3 | CG10: 44949 | CH10: 32 | CI10: 286 | CJ10: 102 | CK10: 43 | CL10: 0 | CM10: 0 | CN10: 0 | CO10: 0 | CP10: 0 | CQ10: 7.8 | CR10: Kiwior | CS10: 1 | CT10: =_xlfn.CONCAT(AK10," ",BV10) -> Jakub Kiwior | CU10: =IFERROR(VLOOKUP(CT10,'Player Names Cleaned'!$A$1:$B$997,2,0),CT10) -> Jakub Kiwior
A11: 0 | B11: 38986 | C11: 0 | D11: 237 | E11: TRUE | F11: TRUE | G11: None | H11: None | I11: 5 | J11: 0.33 | K11: 499169 | L11: None | N11: 0 | O11: 0 | P11: 0 | Q11: 0 | R11: 170.7 | S11: 193 | T11: 49 | U11: 0 | V11: None | X11: 0 | Y11: 2 | Z11: 3.8 | AA11: None | AB11: 0 | AC11: 0.51 | AD11: 0.03 | AE11: 0.67 | AF11: 0.04 | AG11: 0.16 | AH11: 16.65 | AI11: 1.1 | AJ11: 0.01 | AK11: Myles | AL11: 0 | AM11: 537 | AN11: 210 | AO11: 16 | AP11: 1.06 | AQ11: 1 | AR11: FALSE | AS11: 40 | AT11: 258 | AU11: 85 | AV11: 10 | AW11: FALSE | AX11: 176 | AY11: 268 | AZ11: 99 | BA11: 1362 | BC11: None | BD11: 55 | BE11: 187 | BF11: 28 | BG11: p499169 | BH11: 0 | BI11: 0 | BJ11: None | BK11: 0 | BM11: 499169.jpg | BN11: 1.6 | BO11: 297 | BP11: 105 | BQ11: 2 | BR11: 241 | BS11: FALSE | BT11: 0 | BU11: 0 | BV11: Lewis-Skelly | BW11: 5.9 | BX11: 63 | BY11: 23 | BZ11: FALSE | CA11: None | CB11: 15 | CC11: 0.99 | CD11: a | CE11: 1 | CF11: 3 | CG11: 44899 | CH11: 57 | CI11: 257 | CJ11: 90 | CK11: 37 | CL11: 0 | CM11: 0 | CN11: 0 | CO11: 0 | CP11: 0 | CQ11: 6.7 | CR11: Lewis-Skelly | CS11: 3 | CT11: =_xlfn.CONCAT(AK11," ",BV11) -> Myles Lewis-Skelly | CU11: =IFERROR(VLOOKUP(CT11,'Player Names Cleaned'!$A$1:$B$997,2,0),CT11) -> Myles Lewis-Skelly
A12: 2 | B12: 35711 | C12: 0 | D12: 211 | E12: TRUE | F12: TRUE | G12: None | H12: None | I12: 5 | J12: 0.38 | K12: 198869 | L12: None | N12: 0 | O12: 0 | P12: 0 | Q12: 0 | R12: 162.6 | S12: 197 | T12: 51 | U12: 0 | V12: None | X12: 0 | Y12: 2 | Z12: 3.8 | AA12: None | AB12: 0 | AC12: 1.3 | AD12: 0.1 | AE12: 1.76 | AF12: 0.13 | AG12: 0.46 | AH12: 16.88 | AI12: 1.27 | AJ12: 0.03 | AK12: Benjamin | AL12: 0 | AM12: 485 | AN12: 197 | AO12: 13 | AP12: 0.98 | AQ12: 0 | AR12: FALSE | AS12: 51 | AT12: 237 | AU12: 72 | AV12: 11 | AW12: FALSE | AX12: 247.6 | AY12: 225 | AZ12: 82 | BA12: 1195 | BC12: None | BD12: 55 | BE12: 135 | BF12: 15 | BG12: p198869 | BH12: 0 | BI12: 0 | BJ12: None | BK12: 0 | BM12: 198869.jpg | BN12: 2.9 | BO12: 142 | BP12: 41 | BQ12: 0 | BR12: 241 | BS12: FALSE | BT12: 0 | BU12: 0 | BV12: White | BW12: 0.8 | BX12: 210 | BY12: 71 | BZ12: FALSE | CA12: None | CB12: 13 | CC12: 0.98 | CD12: a | CE12: 1 | CF12: 3 | CG12: 44407 | CH12: 100 | CI12: 222 | CJ12: 72 | CK12: 50 | CL12: 0 | CM12: 0 | CN12: 0 | CO12: 0 | CP12: 0 | CQ12: 9.1 | CR12: White | CS12: 2 | CT12: =_xlfn.CONCAT(AK12," ",BV12) -> Benjamin White | CU12: =IFERROR(VLOOKUP(CT12,'Player Names Cleaned'!$A$1:$B$997,2,0),CT12) -> Ben White
A13: 1 | B13: 35414 | C13: 2 | D13: 141 | E13: TRUE | F13: TRUE | G13: None | H13: None | I13: 4 | J13: 0.69 | K13: 206325 | L13: None | N13: 0 | O13: 0 | P13: 0 | Q13: 0 | R13: 92.8 | S13: 243 | T13: 81 | U13: 0 | V13: None | X13: 0 | Y13: 2 | Z13: 3.1 | AA13: None | AB13: 0 | AC13: 0.52 | AD13: 0.09 | AE13: 1.17 | AF13: 0.2 | AG13: 0.65 | AH13: 3.21 | AI13: 0.56 | AJ13: 0.11 | AK13: Oleksandr | AL13: 0 | AM13: 365 | AN13: 169 | AO13: 1 | AP13: 0.17 | AQ13: 0 | AR13: FALSE | AS13: 24.1 | AT13: 294 | AU13: 105 | AV13: 12 | AW13: FALSE | AX13: 83.4 | AY13: 312 | AZ13: 115 | BA13: 518 | BC13: None | BD13: 50 | BE13: 250 | BF13: 38 | BG13: p206325 | BH13: 0 | BI13: 0 | BJ13: None | BK13: 0 | BM13: 206325.jpg | BN13: 2.7 | BO13: 167 | BP13: 53 | BQ13: 0 | BR13: 225 | BS13: FALSE | BT13: 0 | BU13: 0 | BV13: Zinchenko | BW13: 0.3 | BX13: 338 | BY13: 125 | BZ13: FALSE | CA13: None | CB13: 5 | CC13: 0.87 | CD13: a | CE13: 1 | CF13: 3 | CG13: 44764 | CH13: 66 | CI13: 250 | CJ13: 85 | CK13: 40 | CL13: 0 | CM13: 0 | CN13: 0 | CO13: 0 | CP13: 0 | CQ13: 8 | CR13: Zinchenko | CS13: 1 | CT13: =_xlfn.CONCAT(AK13," ",BV13) -> Oleksandr Zinchenko | CU13: =IFERROR(VLOOKUP(CT13,'Player Names Cleaned'!$A$1:$B$997,2,0),CT13) -> Oleksandr Zinchenko
A14: 0 | B14: None | C14: 0 | D14: 0 | E14: TRUE | F14: TRUE | G14: None | H14: None | I14: 0 | J14: 0 | K14: 563324 | L14: None | N14: 0 | O14: 0 | P14: 0 | Q14: 0 | R14: 0 | S14: 464 | T14: 188 | U14: 0 | V14: None | X14: 0 | Y14: 2 | Z14: 1.5 | AA14: None | AB14: 0 | AC14: 0 | AD14: 0 | AE14: 0 | AF14: 0 | AG14: 0 | AH14: 0 | AI14: 0 | AJ14: 0 | AK14: Brayden | AL14: 0 | AM14: 103 | AN14: 62 | AO14: 0 | AP14: 0 | AQ14: 0 | AR14: FALSE | AS14: 0 | AT14: 473 | AU14: 189 | AV14: 13 | AW14: FALSE | AX14: 0 | AY14: 473 | AZ14: 189 | BA14: 0 | BC14: None | BD14: 40 | BE14: 647 | BF14: 204 | BG14: p563324 | BH14: 0 | BI14: 0 | BJ14: None | BK14: 0 | BM14: 563324.jpg | BN14: 0 | BO14: 476 | BP14: 189 | BQ14: 0 | BR14: None | BS14: FALSE | BT14: 0 | BU14: 0 | BV14: Clarke | BW14: 0.7 | BX14: 225 | BY14: 77 | BZ14: FALSE | CA14: None | CB14: 0 | CC14: 0 | CD14: a | CE14: 1 | CF14: 3 | CG14: None | CH14: 0 | CI14: 438 | CJ14: 184 | CK14: 0 | CL14: 0 | CM14: 0 | CN14: 0 | CO14: 0 | CP14: 0 | CQ14: 0 | CR14: Clarke | CS14: 0 | CT14: =_xlfn.CONCAT(AK14," ",BV14) -> Brayden Clarke | CU14: =IFERROR(VLOOKUP(CT14,'Player Names Cleaned'!$A$1:$B$997,2,0),CT14) -> Brayden Clarke
A15: 0 | B15: None | C15: 0 | D15: 0 | E15: TRUE | F15: TRUE | G15: None | H15: None | I15: 0 | J15: 0 | K15: 588793 | L15: None | N15: 0 | O15: 0 | P15: 0 | Q15: 0 | R15: 0 | S15: 470 | T15: 191 | U15: 0 | V15: None | X15: 0 | Y15: 2 | Z15: 1.5 | AA15: None | AB15: 0 | AC15: 0 | AD15: 0 | AE15: 0 | AF15: 0 | AG15: 0 | AH15: 0 | AI15: 0 | AJ15: 0 | AK15: Maldini | AL15: 0 | AM15: 113 | AN15: 69 | AO15: 0 | AP15: 0 | AQ15: 0 | AR15: FALSE | AS15: 0 | AT15: 479 | AU15: 192 | AV15: 14 | AW15: FALSE | AX15: 0 | AY15: 479 | AZ15: 192 | BA15: 0 | BC15: None | BD15: 40 | BE15: 657 | BF15: 211 | BG15: p588793 | BH15: 0 | BI15: 0 | BJ15: None | BK15: 0 | BM15: 588793.jpg | BN15: 0 | BO15: 482 | BP15: 192 | BQ15: 0 | BR15: None | BS15: FALSE | BT15: 0 | BU15: 0 | BV15: Kacurri | BW15: 0.3 | BX15: 369 | BY15: 146 | BZ15: FALSE | CA15: None | CB15: 0 | CC15: 0 | CD15: a | CE15: 1 | CF15: 3 | CG15: None | CH15: 0 | CI15: 446 | CJ15: 189 | CK15: 0 | CL15: 0 | CM15: 0 | CN15: 0 | CO15: 0 | CP15: 0 | CQ15: 0 | CR15: Kacurri | CS15: 0 | CT15: =_xlfn.CONCAT(AK15," ",BV15) -> Maldini Kacurri | CU15: =IFERROR(VLOOKUP(CT15,'Player Names Cleaned'!$A$1:$B$997,2,0),CT15) -> Maldini Kacurri
A16: 0 | B16: 38924 | C16: 0 | D16: 0 | E16: TRUE | F16: TRUE | G16: None | H16: None | I16: 0 | J16: 0 | K16: 499167 | L16: None | N16: 0 | O16: 0 | P16: 0 | Q16: 0 | R16: 0 | S16: 444 | T16: 172 | U16: 0 | V16: None | X16: 0 | Y16: 2 | Z16: 1.5 | AA16: None | AB16: 0 | AC16: 0 | AD16: 0 | AE16: 0 | AF16: 0 | AG16: 0 | AH16: 0 | AI16: 0 | AJ16: 0 | AK16: Josh | AL16: 0 | AM16: 78 | AN16: 42 | AO16: 0 | AP16: 0 | AQ16: 0 | AR16: FALSE | AS16: 0 | AT16: 454 | AU16: 174 | AV16: 15 | AW16: FALSE | AX16: 0 | AY16: 454 | AZ16: 174 | BA16: 0 | BC16: None | BD16: 40 | BE16: 622 | BF16: 184 | BG16: p499167 | BH16: 0 | BI16: 0 | BJ16: None | BK16: 0 | BM16: 499167.jpg | BN16: 0 | BO16: 458 | BP16: 175 | BQ16: 0 | BR16: 241 | BS16: FALSE | BT16: 0 | BU16: 0 | BV16: Nichols | BW16: 0.3 | BX16: 380 | BY16: 153 | BZ16: FALSE | CA16: None | CB16: 0 | CC16: 0 | CD16: a | CE16: 1 | CF16: 3 | CG16: 45497 | CH16: 0 | CI16: 415 | CJ16: 166 | CK16: 0 | CL16: 0 | CM16: 0 | CN16: 0 | CO16: 0 | CP16: 0 | CQ16: 0 | CR16: Nichols | CS16: 0 | CT16: =_xlfn.CONCAT(AK16," ",BV16) -> Josh Nichols | CU16: =IFERROR(VLOOKUP(CT16,'Player Names Cleaned'!$A$1:$B$997,2,0),CT16) -> Josh Nichols
A17: 11 | B17: 37139 | C17: 18 | D17: 508 | E17: TRUE | F17: TRUE | G17: None | H17: None | I17: 7 | J17: 0.37 | K17: 223340 | L17: 1 | N17: 0 | O17: 0 | P17: 0 | Q17: 0 | R17: 842.8 | S17: 16 | T17: 15 | U17: 0 | V17: 4 | X17: 0 | Y17: 3 | Z17: 3.5 | AA17: None | AB17: 0 | AC17: 7.78 | AD17: 0.41 | AE17: 14.65 | AF17: 0.77 | AG17: 6.87 | AH17: 17.72 | AI17: 0.93 | AJ17: 0.36 | AK17: Bukayo | AL17: 0 | AM17: 664 | AN17: 298 | AO17: 21 | AP17: 1.1 | AQ17: 6 | AR17: FALSE | AS17: 227.9 | AT17: 14 | AU17: 10 | AV17: 16 | AW17: FALSE | AX17: 606 | AY17: 87 | AZ17: 36 | BA17: 1724 | BC17: None | BD17: 100 | BE17: 5 | BF17: 3 | BG17: p223340 | BH17: 0 | BI17: 0 | BJ17: 1 | BK17: 0 | BM17: 223340.jpg | BN17: 5.1 | BO17: 11 | BP17: 6 | BQ17: 0 | BR17: 241 | BS17: FALSE | BT17: 0 | BU17: 0 | BV17: Saka | BW17: 16.4 | BX17: 24 | BY17: 7 | BZ17: FALSE | CA17: None | CB17: 20 | CC17: 1.04 | CD17: a | CE17: 1 | CF17: 3 | CG17: 43432 | CH17: 830 | CI17: 23 | CJ17: 13 | CK17: 127 | CL17: 0 | CM17: 0 | CN17: 0 | CO17: 0 | CP17: 0 | CQ17: 12.7 | CR17: Saka | CS17: 3 | CT17: =_xlfn.CONCAT(AK17," ",BV17) -> Bukayo Saka | CU17: =IFERROR(VLOOKUP(CT17,'Player Names Cleaned'!$A$1:$B$997,2,0),CT17) -> Bukayo Saka
A18: 9 | B18: 36146 | C18: 11 | D18: 529 | E18: TRUE | F18: TRUE | G18: None | H18: None | I18: 11 | J18: 0.43 | K18: 184029 | L18: 3 | N18: 0 | O18: 0 | P18: 0 | Q18: 0 | R18: 968.7 | S18: 7 | T18: 7 | U18: 0 | V18: 2 | X18: 0 | Y18: 3 | Z18: 3.1 | AA18: None | AB18: 0 | AC18: 6.68 | AD18: 0.26 | AE18: 11.53 | AF18: 0.45 | AG18: 4.85 | AH18: 22.16 | AI18: 0.86 | AJ18: 0.19 | AK18: Martin | AL18: 0 | AM18: 652 | AN18: 289 | AO18: 21 | AP18: 0.81 | AQ18: 3 | AR18: FALSE | AS18: 198.8 | AT18: 32 | AU18: 25 | AV18: 17 | AW18: FALSE | AX18: 524.6 | AY18: 113 | AZ18: 46 | BA18: 2321 | BC18: None | BD18: 80 | BE18: 14 | BF18: 8 | BG18: p184029 | BH18: 0 | BI18: 0 | BJ18: 2 | BK18: 0 | BM18: 184029.jpg | BN18: 3.9 | BO18: 56 | BP18: 28 | BQ18: 0 | BR18: 161 | BS18: FALSE | BT18: 0 | BU18: 0 | BV18: Ã˜degaard | BW18: 3.3 | BX18: 95 | BY18: 30 | BZ18: FALSE | CA18: None | CB18: 26 | CC18: 1.01 | CD18: a | CE18: 1 | CF18: 3 | CG18: 44428 | CH18: 493 | CI18: 63 | CJ18: 43 | CK18: 116 | CL18: 0 | CM18: 0 | CN18: 0 | CO18: 0 | CP18: 0 | CQ18: 14.5 | CR18: Ã˜degaard | CS18: 4 | CT18: =_xlfn.CONCAT(AK18," ",BV18) -> Martin Ã˜degaard | CU18: =IFERROR(VLOOKUP(CT18,'Player Names Cleaned'!$A$1:$B$997,2,0),CT18) -> Martin Odegaard
A19: 5 | B19: 37325 | C19: 12 | D19: 425 | E19: TRUE | F19: TRUE | G19: None | H19: None | I19: 6 | J19: 0.27 | K19: 248857 | L19: None | N19: 0 | O19: 0 | P19: 0 | Q19: 0 | R19: 475.1 | S19: 73 | T19: 59 | U19: 0 | V19: None | X19: 0 | Y19: 3 | Z19: 2.8 | AA19: None | AB19: 0 | AC19: 2.86 | AD19: 0.13 | AE19: 12.48 | AF19: 0.56 | AG19: 9.62 | AH19: 29.55 | AI19: 1.31 | AJ19: 0.43 | AK19: Noni | AL19: 0 | AM19: 634 | AN19: 279 | AO19: 28 | AP19: 1.24 | AQ19: 7 | AR19: FALSE | AS19: 195.3 | AT19: 37 | AU19: 29 | AV19: 18 | AW19: FALSE | AX19: 479.2 | AY19: 130 | AZ19: 54 | BA19: 2028 | BC19: None | BD19: 70 | BE19: 36 | BF19: 24 | BG19: p248857 | BH19: 0 | BI19: 0 | BJ19: None | BK19: 0 | BM19: 248857.jpg | BN19: 3.8 | BO19: 63 | BP19: 31 | BQ19: 0 | BR19: 241 | BS19: FALSE | BT19: 0 | BU19: 0 | BV19: Madueke | BW19: 1.8 | BX19: 136 | BY19: 43 | BZ19: FALSE | CA19: None | CB19: 27 | CC19: 1.2 | CD19: a | CE19: 1 | CF19: 3 | CG19: 45856 | CH19: 998 | CI19: 11 | CJ19: 5 | CK19: 120 | CL19: 0 | CM19: 0 | CN19: 0 | CO19: 0 | CP19: 0 | CQ19: 17.1 | CR19: Madueke | CS19: 3 | CT19: =_xlfn.CONCAT(AK19," ",BV19) -> Noni Madueke | CU19: =IFERROR(VLOOKUP(CT19,'Player Names Cleaned'!$A$1:$B$997,2,0),CT19) -> Noni Madueke
A20: 4 | B20: 37060 | C20: 6 | D20: 422 | E20: TRUE | F20: TRUE | G20: None | H20: None | I20: 10 | J20: 0.39 | K20: 444145 | L20: None | N20: 0 | O20: 0 | P20: 0 | Q20: 0 | R20: 587.8 | S20: 51 | T20: 44 | U20: 0 | V20: None | X20: 0 | Y20: 3 | Z20: 2.8 | AA20: None | AB20: 0 | AC20: 4.46 | AD20: 0.18 | AE20: 11.59 | AF20: 0.46 | AG20: 7.13 | AH20: 26.22 | AI20: 1.03 | AJ20: 0.28 | AK20: Gabriel | AL20: 0 | AM20: 637 | AN20: 281 | AO20: 25 | AP20: 0.99 | AQ20: 8 | AR20: FALSE | AS20: 206.1 | AT20: 26 | AU20: 21 | AV20: 19 | AW20: FALSE | AX20: 559.8 | AY20: 103 | AZ20: 41 | BA20: 2284 | BC20: None | BD20: 70 | BE20: 39 | BF20: 26 | BG20: p444145 | BH20: 0 | BI20: 0 | BJ20: None | BK20: 0 | BM20: 444145.jpg | BN20: 3.8 | BO20: 64 | BP20: 32 | BQ20: 0 | BR20: 30 | BS20: FALSE | BT20: 0 | BU20: 0 | BV20: Martinelli Silva | BW20: 1.4 | BX20: 158 | BY20: 53 | BZ20: FALSE | CA20: None | CB20: 25 | CC20: 0.99 | CD20: a | CE20: 1 | CF20: 3 | CG20: 43661 | CH20: 912 | CI20: 16 | CJ20: 8 | CK20: 125 | CL20: 0 | CM20: 0 | CN20: 0 | CO20: 0 | CP20: 0 | CQ20: 17.9 | CR20: Martinelli | CS20: 1 | CT20: =_xlfn.CONCAT(AK20," ",BV20) -> Gabriel Martinelli Silva | CU20: =IFERROR(VLOOKUP(CT20,'Player Names Cleaned'!$A$1:$B$997,2,0),CT20) -> Gabriel Martinelli
A21: 8 | B21: 34672 | C21: 18 | D21: 561 | E21: TRUE | F21: TRUE | G21: None | H21: None | I21: 11 | J21: 0.39 | K21: 116216 | L21: None | N21: 0 | O21: 0 | P21: 0 | Q21: 0 | R21: 617.6 | S21: 49 | T21: 42 | U21: 0 | V21: None | X21: 0 | Y21: 3 | Z21: 2.8 | AA21: None | AB21: 0 | AC21: 4.12 | AD21: 0.15 | AE21: 10.86 | AF21: 0.39 | AG21: 6.74 | AH21: 24.76 | AI21: 0.88 | AJ21: 0.24 | AK21: Leandro | AL21: 0 | AM21: 627 | AN21: 272 | AO21: 27 | AP21: 0.95 | AQ21: 8 | AR21: FALSE | AS21: 202.1 | AT21: 29 | AU21: 23 | AV21: 20 | AW21: FALSE | AX21: 609 | AY21: 84 | AZ21: 33 | BA21: 2546 | BC21: None | BD21: 70 | BE21: 29 | BF21: 17 | BG21: p116216 | BH21: 0 | BI21: 0 | BJ21: 4 | BK21: 0 | BM21: 116216.jpg | BN21: 4 | BO21: 45 | BP21: 23 | BQ21: 1 | BR21: 21 | BS21: FALSE | BT21: 0 | BU21: 0 | BV21: Trossard | BW21: 1.6 | BX21: 151 | BY21: 51 | BZ21: FALSE | CA21: None | CB21: 28 | CC21: 0.99 | CD21: a | CE21: 1 | CF21: 3 | CG21: 44946 | CH21: 798 | CI21: 25 | CJ21: 14 | CK21: 152 | CL21: 0 | CM21: 0 | CN21: 0 | CO21: 0 | CP21: 0 | CQ21: 21.7 | CR21: Trossard | CS21: 2 | CT21: =_xlfn.CONCAT(AK21," ",BV21) -> Leandro Trossard | CU21: =IFERROR(VLOOKUP(CT21,'Player Names Cleaned'!$A$1:$B$997,2,0),CT21) -> Leandro Trossard
A22: 7 | B22: 36174 | C22: 17 | D22: 627 | E22: TRUE | F22: TRUE | G22: None | H22: None | I22: 11 | J22: 0.35 | K22: 204480 | L22: 2 | N22: 0 | O22: 0 | P22: 0 | Q22: 0 | R22: 959.6 | S22: 9 | T22: 9 | U22: 0 | V22: 1 | X22: 0 | Y22: 3 | Z22: 2.7 | AA22: None | AB22: 0 | AC22: 5.64 | AD22: 0.18 | AE22: 9.14 | AF22: 0.29 | AG22: 3.51 | AH22: 27.13 | AI22: 0.86 | AJ22: 0.11 | AK22: Declan | AL22: 0 | AM22: 601 | AN22: 253 | AO22: 29 | AP22: 0.92 | AQ22: 4 | AR22: FALSE | AS22: 208.8 | AT22: 24 | AU22: 19 | AV22: 21 | AW22: FALSE | AX22: 733 | AY22: 44 | AZ22: 12 | BA22: 2823 | BC22: None | BD22: 65 | BE22: 51 | BF22: 36 | BG22: p204480 | BH22: 0 | BI22: 0 | BJ22: None | BK22: 0 | BM22: 204480.jpg | BN22: 3.6 | BO22: 79 | BP22: 39 | BQ22: 1 | BR22: 241 | BS22: FALSE | BT22: 0 | BU22: 0 | BV22: Rice | BW22: 7.4 | BX22: 57 | BY22: 17 | BZ22: FALSE | CA22: None | CB22: 33 | CC22: 1.05 | CD22: a | CE22: 1 | CF22: 3 | CG22: 45122 | CH22: 399 | CI22: 80 | CJ22: 56 | CK22: 127 | CL22: 0 | CM22: 0 | CN22: 0 | CO22: 0 | CP22: 0 | CQ22: 19.5 | CR22: Rice | CS22: 5 | CT22: =_xlfn.CONCAT(AK22," ",BV22) -> Declan Rice | CU22: =IFERROR(VLOOKUP(CT22,'Player Names Cleaned'!$A$1:$B$997,2,0),CT22) -> Declan Rice
A23: 2 | B23: 35238 | C23: 8 | D23: 326 | E23: TRUE | F23: TRUE | G23: None | H23: None | I23: 4 | J23: 0.23 | K23: 195384 | L23: None | N23: 0 | O23: 0 | P23: 0 | Q23: 0 | R23: 265.8 | S23: 137 | T23: 96 | U23: 0 | V23: None | X23: 0 | Y23: 3 | Z23: 2.6 | AA23: None | AB23: 0 | AC23: 1.18 | AD23: 0.07 | AE23: 6.93 | AF23: 0.4 | AG23: 5.75 | AH23: 15.71 | AI23: 0.9 | AJ23: 0.33 | AK23: Mikel | AL23: 0 | AM23: 569 | AN23: 233 | AO23: 17 | AP23: 0.97 | AQ23: 7 | AR23: FALSE | AS23: 123.3 | AT23: 99 | AU23: 65 | AV23: 22 | AW23: FALSE | AX23: 456.8 | AY23: 136 | AZ23: 57 | BA23: 1575 | BC23: None | BD23: 60 | BE23: 88 | BF23: 62 | BG23: p195384 | BH23: 0 | BI23: 0 | BJ23: None | BK23: 0 | BM23: 195384.jpg | BN23: 3.3 | BO23: 112 | BP23: 53 | BQ23: 1 | BR23: 200 | BS23: FALSE | BT23: 0 | BU23: 0 | BV23: Merino ZazÃ³n | BW23: 1 | BX23: 194 | BY23: 68 | BZ23: FALSE | CA23: None | CB23: 17 | CC23: 0.97 | CD23: a | CE23: 1 | CF23: 3 | CG23: 45531 | CH23: 511 | CI23: 58 | CJ23: 40 | CK23: 92 | CL23: 0 | CM23: 0 | CN23: 0 | CO23: 0 | CP23: 0 | CQ23: 15.3 | CR23: Merino | CS23: 2 | CT23: =_xlfn.CONCAT(AK23," ",BV23) -> Mikel Merino ZazÃ³n | CU23: =IFERROR(VLOOKUP(CT23,'Player Names Cleaned'!$A$1:$B$997,2,0),CT23) -> Mikel Merino
A24: 0 | B24: 36676 | C24: 0 | D24: 0 | E24: TRUE | F24: TRUE | G24: None | H24: None | I24: 0 | J24: 0 | K24: 438098 | L24: None | N24: 0 | O24: 0 | P24: 0 | Q24: 0 | R24: 0 | S24: 648 | T24: 288 | U24: 0 | V24: None | X24: 0 | Y24: 3 | Z24: 2.5 | AA24: None | AB24: 0 | AC24: 0 | AD24: 0 | AE24: 0 | AF24: 0 | AG24: 0 | AH24: 0 | AI24: 0 | AJ24: 0 | AK24: FÃ¡bio | AL24: 0 | AM24: 516 | AN24: 200 | AO24: 0 | AP24: 0 | AQ24: 0 | AR24: FALSE | AS24: 0 | AT24: 648 | AU24: 288 | AV24: 23 | AW24: FALSE | AX24: 0 | AY24: 648 | AZ24: 288 | BA24: 0 | BC24: None | BD24: 55 | BE24: 166 | BF24: 108 | BG24: p438098 | BH24: 0 | BI24: 0 | BJ24: None | BK24: 0 | BM24: 438098.jpg | BN24: 0 | BO24: 648 | BP24: 288 | BQ24: 0 | BR24: 173 | BS24: FALSE | BT24: 0 | BU24: 0 | BV24: Ferreira Vieira | BW24: 0.1 | BX24: 633 | BY24: 274 | BZ24: FALSE | CA24: None | CB24: 0 | CC24: 0 | CD24: a | CE24: 1 | CF24: 3 | CG24: 44733 | CH24: 0 | CI24: 645 | CJ24: 285 | CK24: 0 | CL24: 0 | CM24: 0 | CN24: 0 | CO24: 0 | CP24: 0 | CQ24: 0 | CR24: FÃ¡bio Vieira | CS24: 0 | CT24: =_xlfn.CONCAT(AK24," ",BV24) -> FÃ¡bio Ferreira Vieira | CU24: =IFERROR(VLOOKUP(CT24,'Player Names Cleaned'!$A$1:$B$997,2,0),CT24) -> Fabio Vieira
A25: 5 | B25: 34403 | C25: 7 | D25: 580 | E25: TRUE | F25: TRUE | G25: None | H25: None | I25: 6 | J25: 0.19 | K25: 128295 | L25: None | N25: 0 | O25: 0 | P25: 0 | Q25: 0 | R25: 333 | S25: 105 | T25: 76 | U25: 0 | V25: None | X25: 0 | Y25: 3 | Z25: 2.5 | AA25: None | AB25: 0 | AC25: 1.38 | AD25: 0.04 | AE25: 5.61 | AF25: 0.18 | AG25: 4.23 | AH25: 44.54 | AI25: 1.42 | AJ25: 0.14 | AK25: Christian | AL25: 0 | AM25: 473 | AN25: 172 | AO25: 45 | AP25: 1.44 | AQ25: 5 | AR25: FALSE | AS25: 147.9 | AT25: 74 | AU25: 52 | AV25: 24 | AW25: FALSE | AX25: 735.4 | AY25: 42 | AZ25: 11 | BA25: 2820 | BC25: None | BD25: 55 | BE25: 123 | BF25: 80 | BG25: p128295 | BH25: 0 | BI25: 0 | BJ25: None | BK25: 0 | BM25: 128295.jpg | BN25: 3.1 | BO25: 127 | BP25: 60 | BQ25: 1 | BR25: 58 | BS25: FALSE | BT25: 0 | BU25: 0 | BV25: NÃ¸rgaard | BW25: 0.7 | BX25: 224 | BY25: 75 | BZ25: FALSE | CA25: None | CB25: 34 | CC25: 1.09 | CD25: a | CE25: 1 | CF25: 3 | CG25: 45848 | CH25: 409 | CI25: 75 | CJ25: 52 | CK25: 107 | CL25: 0 | CM25: 0 | CN25: 0 | CO25: 0 | CP25: 0 | CQ25: 19.5 | CR25: NÃ¸rgaard | CS25: 8 | CT25: =_xlfn.CONCAT(AK25," ",BV25) -> Christian NÃ¸rgaard | CU25: =IFERROR(VLOOKUP(CT25,'Player Names Cleaned'!$A$1:$B$997,2,0),CT25) -> Christian Norgaard
A26: 2 | B26: 39162 | C26: 4 | D26: 251 | E26: TRUE | F26: TRUE | G26: None | H26: None | I26: 4 | J26: 0.41 | K26: 499175 | L26: 4 | N26: 0 | O26: 0 | P26: 0 | Q26: 0 | R26: 282.8 | S26: 130 | T26: 91 | U26: 0 | V26: 3 | X26: 0 | Y26: 3 | Z26: 2.5 | AA26: None | AB26: 0 | AC26: 1.78 | AD26: 0.18 | AE26: 2.97 | AF26: 0.3 | AG26: 1.19 | AH26: 5.38 | AI26: 0.55 | AJ26: 0.12 | AK26: Ethan | AL26: 0 | AM26: 538 | AN26: 212 | AO26: 4 | AP26: 0.41 | AQ26: 4 | AR26: FALSE | AS26: 83 | AT26: 161 | AU26: 89 | AV26: 25 | AW26: FALSE | AX26: 293.2 | AY26: 203 | AZ26: 96 | BA26: 882 | BC26: None | BD26: 55 | BE26: 188 | BF26: 120 | BG26: p499175 | BH26: 0 | BI26: 0 | BJ26: None | BK26: 0 | BM26: 499175.jpg | BN26: 2.5 | BO26: 189 | BP26: 81 | BQ26: 0 | BR26: 241 | BS26: FALSE | BT26: 0 | BU26: 0 | BV26: Nwaneri | BW26: 0.5 | BX26: 264 | BY26: 87 | BZ26: FALSE | CA26: None | CB26: 11 | CC26: 1.12 | CD26: a | CE26: 1 | CF26: 3 | CG26: 44821 | CH26: 255 | CI26: 115 | CJ26: 79 | CK26: 66 | CL26: 0 | CM26: 0 | CN26: 0 | CO26: 0 | CP26: 0 | CQ26: 12 | CR26: Nwaneri | CS26: 1 | CT26: =_xlfn.CONCAT(AK26," ",BV26) -> Ethan Nwaneri | CU26: =IFERROR(VLOOKUP(CT26,'Player Names Cleaned'!$A$1:$B$997,2,0),CT26) -> Ethan Nwaneri
A27: 0 | B27: 36193 | C27: 0 | D27: 0 | E27: TRUE | F27: TRUE | G27: None | H27: None | I27: 0 | J27: 0 | K27: 481655 | L27: None | N27: 0 | O27: 0 | P27: 0 | Q27: 0 | R27: 0 | S27: 651 | T27: 291 | U27: 0 | V27: None | X27: 0 | Y27: 3 | Z27: 2.5 | AA27: None | AB27: 0 | AC27: 0 | AD27: 0 | AE27: 0 | AF27: 0 | AG27: 0 | AH27: 0 | AI27: 0 | AJ27: 0 | AK27: MartÃ­n | AL27: 0 | AM27: 531 | AN27: 209 | AO27: 0 | AP27: 0 | AQ27: 0 | AR27: FALSE | AS27: 0 | AT27: 651 | AU27: 291 | AV27: 26 | AW27: FALSE | AX27: 0 | AY27: 651 | AZ27: 291 | BA27: 0 | BC27: None | BD27: 55 | BE27: 181 | BF27: 117 | BG27: p481655 | BH27: 0 | BI27: 0 | BJ27: None | BK27: 0 | BM27: 481655.jpg | BN27: 0 | BO27: 651 | BP27: 291 | BQ27: 0 | BR27: 200 | BS27: FALSE | BT27: 0 | BU27: 0 | BV27: Zubimendi IbÃ¡Ã±ez | BW27: 1.8 | BX27: 137 | BY27: 44 | BZ27: FALSE | CA27: None | CB27: 0 | CC27: 0 | CD27: a | CE27: 1 | CF27: 3 | CG27: 45844 | CH27: 0 | CI27: 649 | CJ27: 289 | CK27: 0 | CL27: 0 | CM27: 0 | CN27: 0 | CO27: 0 | CP27: 0 | CQ27: 0 | CR27: Zubimendi | CS27: 0 | CT27: =_xlfn.CONCAT(AK27," ",BV27) -> MartÃ­n Zubimendi IbÃ¡Ã±ez | CU27: =IFERROR(VLOOKUP(CT27,'Player Names Cleaned'!$A$1:$B$997,2,0),CT27) -> Martin Zubimendi
A28: 1 | B28: 36504 | C28: 2 | D28: 143 | E28: TRUE | F28: TRUE | G28: None | H28: None | I28: 1 | J28: 0.19 | K28: 200641 | L28: None | N28: 0 | O28: 0 | P28: 0 | Q28: 0 | R28: 223.9 | S28: 158 | T28: 110 | U28: 0 | V28: None | X28: 0 | Y28: 3 | Z28: 2 | AA28: None | AB28: 0 | AC28: 0.96 | AD28: 0.18 | AE28: 2.03 | AF28: 0.38 | AG28: 1.07 | AH28: 6.13 | AI28: 1.14 | AJ28: 0.2 | AK28: Reiss | AL28: 0 | AM28: 360 | AN28: 100 | AO28: 9 | AP28: 1.68 | AQ28: 1 | AR28: FALSE | AS28: 55.1 | AT28: 226 | AU28: 120 | AV28: 27 | AW28: FALSE | AX28: 131.6 | AY28: 287 | AZ28: 136 | BA28: 483 | BC28: None | BD28: 50 | BE28: 245 | BF28: 155 | BG28: p200641 | BH28: 0 | BI28: 0 | BJ28: None | BK28: 0 | BM28: 200641.jpg | BN28: 2.2 | BO28: 220 | BP28: 96 | BQ28: 0 | BR28: 241 | BS28: FALSE | BT28: 0 | BU28: 0 | BV28: Nelson | BW28: 0.2 | BX28: 437 | BY28: 142 | BZ28: FALSE | CA28: None | CB28: 5 | CC28: 0.93 | CD28: a | CE28: 1 | CF28: 3 | CG28: 42928 | CH28: 195 | CI28: 156 | CJ28: 102 | CK28: 27 | CL28: 0 | CM28: 0 | CN28: 0 | CO28: 0 | CP28: 0 | CQ28: 5.4 | CR28: Nelson | CS28: 1 | CT28: =_xlfn.CONCAT(AK28," ",BV28) -> Reiss Nelson | CU28: =IFERROR(VLOOKUP(CT28,'Player Names Cleaned'!$A$1:$B$997,2,0),CT28) -> Reiss Nelson
A29: 0 | B29: 38696 | C29: 0 | D29: 0 | E29: TRUE | F29: TRUE | G29: None | H29: None | I29: 0 | J29: 0 | K29: 588796 | L29: None | N29: 0 | O29: 0 | P29: 0 | Q29: 0 | R29: 0 | S29: 575 | T29: 238 | U29: 0 | V29: None | X29: 0 | Y29: 3 | Z29: 1.5 | AA29: None | AB29: 0 | AC29: 0 | AD29: 0 | AE29: 0 | AF29: 0 | AG29: 0 | AH29: 0 | AI29: 0 | AJ29: 0 | AK29: Ismeal | AL29: 0 | AM29: 302 | AN29: 67 | AO29: 0 | AP29: 0 | AQ29: 0 | AR29: FALSE | AS29: 0 | AT29: 579 | AU29: 238 | AV29: 28 | AW29: FALSE | AX29: 0 | AY29: 579 | AZ29: 238 | BA29: 0 | BC29: None | BD29: 45 | BE29: 524 | BF29: 289 | BG29: p588796 | BH29: 0 | BI29: 0 | BJ29: None | BK29: 0 | BM29: 588796.jpg | BN29: 0 | BO29: 580 | BP29: 239 | BQ29: 0 | BR29: 152 | BS29: FALSE | BT29: 0 | BU29: 0 | BV29: Kabia | BW29: 0.3 | BX29: 336 | BY29: 111 | BZ29: FALSE | CA29: None | CB29: 0 | CC29: 0 | CD29: a | CE29: 1 | CF29: 3 | CG29: 45549 | CH29: 0 | CI29: 559 | CJ29: 232 | CK29: 0 | CL29: 0 | CM29: 0 | CN29: 0 | CO29: 0 | CP29: 0 | CQ29: 0 | CR29: Kabia | CS29: 0 | CT29: =_xlfn.CONCAT(AK29," ",BV29) -> Ismeal Kabia | CU29: =IFERROR(VLOOKUP(CT29,'Player Names Cleaned'!$A$1:$B$997,2,0),CT29) -> Ismeal Kabia
A30: 0 | B30: 36455 | C30: 0 | D30: 0 | E30: TRUE | F30: TRUE | G30: None | H30: None | I30: 0 | J30: 0 | K30: 437742 | L30: None | N30: 0 | O30: 0 | P30: 0 | Q30: 0 | R30: 0 | S30: 503 | T30: 190 | U30: 0 | V30: None | X30: 0 | Y30: 3 | Z30: 1.5 | AA30: None | AB30: 0 | AC30: 0 | AD30: 0 | AE30: 0 | AF30: 0 | AG30: 0 | AH30: 0 | AI30: 0 | AJ30: 0 | AK30: Albert | AL30: 0 | AM30: 201 | AN30: 9 | AO30: 0 | AP30: 0 | AQ30: 0 | AR30: FALSE | AS30: 0 | AT30: 507 | AU30: 190 | AV30: 29 | AW30: FALSE | AX30: 0 | AY30: 507 | AZ30: 190 | BA30: 0 | BC30: None | BD30: 45 | BE30: 423 | BF30: 231 | BG30: p437742 | BH30: 0 | BI30: 0 | BJ30: None | BK30: 0 | BM30: 437742.jpg | BN30: 0 | BO30: 510 | BP30: 191 | BQ30: 0 | BR30: 21 | BS30: FALSE | BT30: 0 | BU30: 0 | BV30: Sambi Lokonga | BW30: 0.2 | BX30: 463 | BY30: 153 | BZ30: FALSE | CA30: None | CB30: 0 | CC30: 0 | CD30: a | CE30: 1 | CF30: 3 | CG30: 44396 | CH30: 0 | CI30: 483 | CJ30: 182 | CK30: 0 | CL30: 0 | CM30: 0 | CN30: 0 | CO30: 0 | CP30: 0 | CQ30: 0 | CR30: Sambi | CS30: 0 | CT30: =_xlfn.CONCAT(AK30," ",BV30) -> Albert Sambi Lokonga | CU30: =IFERROR(VLOOKUP(CT30,'Player Names Cleaned'!$A$1:$B$997,2,0),CT30) -> Albert Sambi Lokonga
A31: 3 | B31: 36322 | C31: 14 | D31: 343 | E31: TRUE | F31: TRUE | G31: None | H31: None | I31: 7 | J31: 0.34 | K31: 219847 | L31: None | N31: 0 | O31: 0 | P31: 0 | Q31: 0 | R31: 269 | S31: 134 | T31: 15 | U31: 0 | V31: None | X31: 0 | Y31: 4 | Z31: 2.9 | AA31: None | AB31: 0 | AC31: 1.65 | AD31: 0.08 | AE31: 11.18 | AF31: 0.54 | AG31: 9.53 | AH31: 19.32 | AI31: 0.93 | AJ31: 0.46 | AK31: Kai | AL31: 0 | AM31: 644 | AN31: 62 | AO31: 20 | AP31: 0.96 | AQ31: 9 | AR31: FALSE | AS31: 144.8 | AT31: 76 | AU31: 15 | AV31: 30 | AW31: FALSE | AX31: 467.6 | AY31: 135 | AZ31: 15 | BA31: 1872 | BC31: None | BD31: 75 | BE31: 22 | BF31: 10 | BG31: p219847 | BH31: 0 | BI31: 0 | BJ31: None | BK31: 0 | BM31: 219847.jpg | BN31: 4.2 | BO31: 35 | BP31: 9 | BQ31: 0 | BR31: 80 | BS31: FALSE | BT31: 0 | BU31: 0 | BV31: Havertz | BW31: 1.5 | BX31: 153 | BY31: 28 | BZ31: FALSE | CA31: None | CB31: 21 | CC31: 1.01 | CD31: a | CE31: 1 | CF31: 3 | CG31: 45105 | CH31: 711 | CI31: 33 | CJ31: 14 | CK31: 97 | CL31: 0 | CM31: 0 | CN31: 0 | CO31: 0 | CP31: 0 | CQ31: 12.9 | CR31: Havertz | CS31: 5 | CT31: =_xlfn.CONCAT(AK31," ",BV31) -> Kai Havertz | CU31: =IFERROR(VLOOKUP(CT31,'Player Names Cleaned'!$A$1:$B$997,2,0),CT31) -> Kai Havertz
A32: 2 | B32: 35523 | C32: 6 | D32: 152 | E32: TRUE | F32: TRUE | G32: 0 | H32: None | I32: 2 | J32: 0.3 | K32: 205651 | L32: None | N32: 0 | O32: 0 | P32: 0 | Q32: 0 | R32: 119.5 | S32: 220 | T32: 23 | U32: 0 | V32: None | X32: 0 | Y32: 4 | Z32: 0 | AA32: None | AB32: 0 | AC32: 0.52 | AD32: 0.08 | AE32: 3.57 | AF32: 0.54 | AG32: 3.05 | AH32: 5.82 | AI32: 0.87 | AJ32: 0.46 | AK32: Gabriel | AL32: 0 | AM32: 602 | AN32: 51 | AO32: 5 | AP32: 0.75 | AQ32: 3 | AR32: FALSE | AS32: 52.6 | AT32: 233 | AU32: 24 | AV32: 31 | AW32: FALSE | AX32: 154.4 | AY32: 278 | AZ32: 25 | BA32: 600 | BB32: Knee injury - Unknown return date | BC32: 2025-07-21T10:00:04.697564Z | BD32: 65 | BE32: 52 | BF32: 16 | BG32: p205651 | BH32: 0 | BI32: 0 | BJ32: None | BK32: 0 | BM32: 205651.jpg | BN32: 2.5 | BO32: 190 | BP32: 19 | BQ32: 0 | BR32: 30 | BS32: FALSE | BT32: 0 | BU32: 0 | BV32: Fernando de Jesus | BW32: 0 | BX32: 646 | BY32: 69 | BZ32: FALSE | CA32: None | CB32: 6 | CC32: 0.9 | CD32: i | CE32: 1 | CF32: 3 | CG32: 44746 | CH32: 255 | CI32: 116 | CJ32: 23 | CK32: 42 | CL32: 0 | CM32: 0 | CN32: 0 | CO32: 0 | CP32: 0 | CQ32: 6.5 | CR32: G.Jesus | CS32: 4 | CT32: =_xlfn.CONCAT(AK32," ",BV32) -> Gabriel Fernando de Jesus | CU32: =IFERROR(VLOOKUP(CT32,'Player Names Cleaned'!$A$1:$B$997,2,0),CT32) -> Gabriel Fernando de Jesus
A33: 0 | B33: 38165 | C33: 0 | D33: 0 | E33: TRUE | F33: TRUE | G33: None | H33: None | I33: 0 | J33: 0 | K33: 500040 | L33: None | N33: 0 | O33: 0 | P33: 0 | Q33: 0 | R33: 0 | S33: 653 | T33: 221 | U33: 0 | V33: None | X33: 0 | Y33: 2 | Z33: 3.8 | AA33: None | AB33: 0 | AC33: 0 | AD33: 0 | AE33: 0 | AF33: 0 | AG33: 0 | AH33: 0 | AI33: 0 | AJ33: 0 | AK33: Cristhian | AL33: 0 | AM33: 539 | AN33: 211 | AO33: 0 | AP33: 0 | AQ33: 0 | AR33: FALSE | AS33: 0 | AT33: 653 | AU33: 221 | AV33: 662 | AW33: FALSE | AX33: 0 | AY33: 653 | AZ33: 221 | BA33: 0 | BC33: None | BD33: 55 | BE33: 189 | BF33: 29 | BG33: p500040 | BH33: 0 | BI33: 0 | BJ33: None | BK33: 0 | BM33: 500040.jpg | BN33: 0 | BO33: 653 | BP33: 221 | BQ33: 0 | BR33: 200 | BS33: FALSE | BT33: 0 | BU33: 0 | BV33: Mosquera | BW33: 0.1 | BX33: 549 | BY33: 206 | BZ33: FALSE | CA33: None | CB33: 0 | CC33: 0 | CD33: a | CE33: 1 | CF33: 3 | CG33: 45862 | CH33: 0 | CI33: 651 | CJ33: 221 | CK33: 0 | CL33: 0 | CM33: 0 | CN33: 0 | CO33: 0 | CP33: 0 | CQ33: 0 | CR33: Mosquera | CS33: 0 | CT33: =_xlfn.CONCAT(AK33," ",BV33) -> Cristhian Mosquera | CU33: =IFERROR(VLOOKUP(CT33,'Player Names Cleaned'!$A$1:$B$997,2,0),CT33) -> Cristhian Mosquera
A34: 0 | B34: 35950 | C34: 0 | D34: 0 | E34: TRUE | F34: TRUE | G34: None | H34: None | I34: 0 | J34: 0 | K34: 224117 | L34: None | N34: 0 | O34: 0 | P34: 0 | Q34: 0 | R34: 0 | S34: 668 | T34: 70 | U34: 0 | V34: None | X34: 0 | Y34: 4 | Z34: 3.3 | AA34: None | AB34: 0 | AC34: 0 | AD34: 0 | AE34: 0 | AF34: 0 | AG34: 0 | AH34: 0 | AI34: 0 | AJ34: 0 | AK34: Viktor | AL34: 0 | AM34: 663 | AN34: 68 | AO34: 0 | AP34: 0 | AQ34: 0 | AR34: FALSE | AS34: 0 | AT34: 668 | AU34: 70 | AV34: 666 | AW34: FALSE | AX34: 0 | AY34: 668 | AZ34: 70 | BA34: 0 | BC34: None | BD34: 90 | BE34: 8 | BF34: 4 | BG34: p224117 | BH34: 0 | BI34: 0 | BJ34: None | BK34: 0 | BM34: 224117.jpg | BN34: 0 | BO34: 668 | BP34: 70 | BQ34: 0 | BR34: 206 | BS34: FALSE | BT34: 0 | BU34: 0 | BV34: GyÃ¶keres | BW34: 23.1 | BX34: 14 | BY34: 3 | BZ34: FALSE | CA34: None | CB34: 0 | CC34: 0 | CD34: a | CE34: 1 | CF34: 3 | CG34: 45864 | CH34: 0 | CI34: 668 | CJ34: 70 | CK34: 0 | CL34: 0 | CM34: 0 | CN34: 0 | CO34: 0 | CP34: 0 | CQ34: 0 | CR34: GyÃ¶keres | CS34: 0 | CT34: =_xlfn.CONCAT(AK34," ",BV34) -> Viktor GyÃ¶keres | CU34: =IFERROR(VLOOKUP(CT34,'Player Names Cleaned'!$A$1:$B$997,2,0),CT34) -> Viktor Gyokeres
A35: 0 | B35: 33849 | C35: 6 | D35: 457 | E35: TRUE | F35: TRUE | G35: 0 | H35: None | I35: 8 | J35: 0.23 | K35: 98980 | L35: None | N35: 0 | O35: 0 | P35: 0 | Q35: 0 | R35: 20 | S35: 325 | T35: 7 | U35: 0 | V35: None | X35: 0 | Y35: 1 | Z35: 0 | AA35: None | AB35: 0 | AC35: 0.02 | AD35: 0 | AE35: 0.02 | AF35: 0 | AG35: 0 | AH35: 44.99 | AI35: 1.27 | AJ35: 0 | AK35: Emiliano | AL35: 0 | AM35: 334 | AN35: 66 | AO35: 47 | AP35: 1.32 | AQ35: 0 | AR35: FALSE | AS35: 86 | AT35: 155 | AU35: 5 | AV35: 32 | AW35: FALSE | AX35: 839.6 | AY35: 21 | AZ35: 6 | BA35: 3195 | BB35: Suspended until 23 Aug | BC35: 2025-07-21T10:00:04.758838Z | BD35: 50 | BE35: 219 | BF35: 9 | BG35: p98980 | BH35: 0 | BI35: 0 | BJ35: None | BK35: 1 | BM35: 98980.jpg | BN35: 3 | BO35: 133 | BP35: 20 | BQ35: 1 | BR35: 10 | BS35: FALSE | BT35: 100 | BU35: 2.82 | BV35: MartÃ­nez Romero | BW35: 0.5 | BX35: 261 | BY35: 37 | BZ35: FALSE | CA35: None | CB35: 37 | CC35: 1.04 | CD35: s | CE35: 2 | CF35: 7 | CG35: 44090 | CH35: 0 | CI35: 580 | CJ35: 67 | CK35: 111 | CL35: 0 | CM35: 0 | CN35: 0 | CO35: 0 | CP35: 0 | CQ35: 22.2 | CR35: Martinez | CS35: 5 | CT35: =_xlfn.CONCAT(AK35," ",BV35) -> Emiliano MartÃ­nez Romero | CU35: =IFERROR(VLOOKUP(CT35,'Player Names Cleaned'!$A$1:$B$997,2,0),CT35) -> Emiliano Martinez
A36: 0 | B36: 33307 | C36: 0 | D36: 0 | E36: TRUE | F36: TRUE | G36: None | H36: None | I36: 0 | J36: 0 | K36: 72147 | L36: None | N36: 0 | O36: 0 | P36: 0 | Q36: 0 | R36: 0 | S36: 481 | T36: 62 | U36: 0 | V36: None | X36: 0 | Y36: 1 | Z36: 1.8 | AA36: None | AB36: 0 | AC36: 0 | AD36: 0 | AE36: 0 | AF36: 0 | AG36: 0 | AH36: 0 | AI36: 0 | AJ36: 0 | AK36: Marco | AL36: 0 | AM36: 131 | AN36: 47 | AO36: 0 | AP36: 0 | AQ36: 0 | AR36: FALSE | AS36: 0 | AT36: 488 | AU36: 69 | AV36: 33 | AW36: FALSE | AX36: 0 | AY36: 488 | AZ36: 69 | BA36: 0 | BC36: None | BD36: 45 | BE36: 353 | BF36: 18 | BG36: p72147 | BH36: 0 | BI36: 0 | BJ36: None | BK36: 0 | BM36: 72147.jpg | BN36: 0 | BO36: 491 | BP36: 69 | BQ36: 0 | BR36: 152 | BS36: FALSE | BT36: 0 | BU36: 0 | BV36: Bizot | BW36: 0.3 | BX36: 346 | BY36: 48 | BZ36: FALSE | CA36: None | CB36: 0 | CC36: 0 | CD36: a | CE36: 2 | CF36: 7 | CG36: 45853 | CH36: 0 | CI36: 458 | CJ36: 49 | CK36: 0 | CL36: 0 | CM36: 0 | CN36: 0 | CO36: 0 | CP36: 0 | CQ36: 0 | CR36: M.Bizot | CS36: 0 | CT36: =_xlfn.CONCAT(AK36," ",BV36) -> Marco Bizot | CU36: =IFERROR(VLOOKUP(CT36,'Player Names Cleaned'!$A$1:$B$997,2,0),CT36) -> Marco Bizot
A37: 0 | B37: 36711 | C37: 0 | D37: 0 | E37: TRUE | F37: TRUE | G37: None | H37: None | I37: 0 | J37: 0 | K37: 462492 | L37: None | N37: 0 | O37: 0 | P37: 0 | Q37: 0 | R37: 0 | S37: 425 | T37: 44 | U37: 0 | V37: None | X37: 0 | Y37: 1 | Z37: 0.5 | AA37: None | AB37: 0 | AC37: 0 | AD37: 0 | AE37: 0 | AF37: 0 | AG37: 0 | AH37: 0 | AI37: 0 | AJ37: 0 | AK37: Joe | AL37: 0 | AM37: 56 | AN37: 27 | AO37: 0 | AP37: 0 | AQ37: 0 | AR37: FALSE | AS37: 0 | AT37: 435 | AU37: 53 | AV37: 34 | AW37: FALSE | AX37: 0 | AY37: 435 | AZ37: 53 | BA37: 0 | BC37: None | BD37: 40 | BE37: 600 | BF37: 59 | BG37: p462492 | BH37: 0 | BI37: 0 | BJ37: None | BK37: 0 | BM37: 462492.jpg | BN37: 0 | BO37: 438 | BP37: 53 | BQ37: 0 | BR37: 13 | BS37: FALSE | BT37: 0 | BU37: 0 | BV37: Gauci | BW37: 1 | BX37: 184 | BY37: 26 | BZ37: FALSE | CA37: None | CB37: 0 | CC37: 0 | CD37: a | CE37: 2 | CF37: 7 | CG37: 45323 | CH37: 0 | CI37: 394 | CJ37: 29 | CK37: 0 | CL37: 0 | CM37: 0 | CN37: 0 | CO37: 0 | CP37: 0 | CQ37: 0 | CR37: Gauci | CS37: 0 | CT37: =_xlfn.CONCAT(AK37," ",BV37) -> Joe Gauci | CU37: =IFERROR(VLOOKUP(CT37,'Player Names Cleaned'!$A$1:$B$997,2,0),CT37) -> Joe Gauci
A38: 0 | B38: 37735 | C38: 0 | D38: 0 | E38: FALSE | F38: TRUE | G38: 0 | H38: None | I38: 0 | J38: 0 | K38: 462381 | L38: None | N38: 0 | O38: 0 | P38: 0 | Q38: 0 | R38: 0 | S38: 424 | T38: 43 | U38: 0 | V38: None | X38: 0 | Y38: 1 | Z38: 0 | AA38: None | AB38: 0 | AC38: 0 | AD38: 0 | AE38: 0 | AF38: 0 | AG38: 0 | AH38: 0 | AI38: 0 | AJ38: 0 | AK38: Filip | AL38: 0 | AM38: 55 | AN38: 26 | AO38: 0 | AP38: 0 | AQ38: 0 | AR38: FALSE | AS38: 0 | AT38: 434 | AU38: 52 | AV38: 35 | AW38: FALSE | AX38: 0 | AY38: 434 | AZ38: 52 | BA38: 0 | BB38: Has joined Stevenage permanently. | BC38: 2025-07-30T14:08:21.698398Z | BD38: 40 | BE38: 599 | BF38: 58 | BG38: p462381 | BH38: 0 | BI38: 0 | BJ38: None | BK38: 0 | BM38: 462381.jpg | BN38: 0 | BO38: 437 | BP38: 52 | BQ38: 0 | BR38: 241 | BS38: FALSE | BT38: 0 | BU38: 0 | BV38: Marschall | BW38: 0.2 | BX38: 406 | BY38: 54 | BZ38: FALSE | CA38: None | CB38: 0 | CC38: 0 | CD38: u | CE38: 2 | CF38: 7 | CG38: 44543 | CH38: 0 | CI38: 393 | CJ38: 28 | CK38: 0 | CL38: 0 | CM38: 0 | CN38: 0 | CO38: 0 | CP38: 0 | CQ38: 0 | CR38: Marschall | CS38: 0 | CT38: =_xlfn.CONCAT(AK38," ",BV38) -> Filip Marschall | CU38: =IFERROR(VLOOKUP(CT38,'Player Names Cleaned'!$A$1:$B$997,2,0),CT38) -> Filip Marschall
A39: 1 | B39: 35649 | C39: 2 | D39: 286 | E39: TRUE | F39: TRUE | G39: None | H39: None | I39: 7 | J39: 0.3 | K39: 199796 | L39: None | N39: 0 | O39: 0 | P39: 0 | Q39: 0 | R39: 181 | S39: 185 | T39: 43 | U39: 0 | V39: None | X39: 0 | Y39: 2 | Z39: 1.4 | AA39: None | AB39: 0 | AC39: 1.23 | AD39: 0.05 | AE39: 1.71 | AF39: 0.07 | AG39: 0.48 | AH39: 28.64 | AI39: 1.25 | AJ39: 0.02 | AK39: Matty | AL39: 0 | AM39: 162 | AN39: 106 | AO39: 22 | AP39: 0.96 | AQ39: 1 | AR39: FALSE | AS39: 71.3 | AT39: 191 | AU39: 60 | AV39: 36 | AW39: FALSE | AX39: 359.2 | AY39: 173 | AZ39: 61 | BA39: 2069 | BC39: None | BD39: 45 | BE39: 384 | BF39: 86 | BG39: p199796 | BH39: 0 | BI39: 0 | BJ39: None | BK39: 0 | BM39: 199796.jpg | BN39: 2.8 | BO39: 153 | BP39: 46 | BQ39: 0 | BR39: 172 | BS39: FALSE | BT39: 0 | BU39: 0 | BV39: Cash | BW39: 1.6 | BX39: 145 | BY39: 50 | BZ39: FALSE | CA39: None | CB39: 24 | CC39: 1.04 | CD39: a | CE39: 2 | CF39: 7 | CG39: 44077 | CH39: 171 | CI39: 170 | CJ39: 38 | CK39: 76 | CL39: 0 | CM39: 0 | CN39: 0 | CO39: 0 | CP39: 0 | CQ39: 16.9 | CR39: Cash | CS39: 7 | CT39: =_xlfn.CONCAT(AK39," ",BV39) -> Matty Cash | CU39: =IFERROR(VLOOKUP(CT39,'Player Names Cleaned'!$A$1:$B$997,2,0),CT39) -> Matty Cash
A40: 5 | B40: 34170 | C40: 7 | D40: 383 | E40: TRUE | F40: TRUE | G40: None | H40: None | I40: 6 | J40: 0.23 | K40: 101188 | L40: 7 | N40: 0 | O40: 0 | P40: 0 | Q40: 0 | R40: 583.9 | S40: 52 | T40: 7 | U40: 0 | V40: 2 | X40: 0 | Y40: 2 | Z40: 1.4 | AA40: None | AB40: 0 | AC40: 3.97 | AD40: 0.15 | AE40: 4.77 | AF40: 0.18 | AG40: 0.8 | AH40: 34.94 | AI40: 1.34 | AJ40: 0.03 | AK40: Lucas | AL40: 0 | AM40: 137 | AN40: 88 | AO40: 36 | AP40: 1.38 | AQ40: 0 | AR40: FALSE | AS40: 120.7 | AT40: 103 | AU40: 20 | AV40: 37 | AW40: FALSE | AX40: 512.6 | AY40: 122 | AZ40: 41 | BA40: 2348 | BC40: None | BD40: 45 | BE40: 359 | BF40: 68 | BG40: p101188 | BH40: 0 | BI40: 0 | BJ40: None | BK40: 0 | BM40: 101188.jpg | BN40: 2.8 | BO40: 150 | BP40: 43 | BQ40: 0 | BR40: 73 | BS40: FALSE | BT40: 0 | BU40: 0 | BV40: Digne | BW40: 1.6 | BX40: 147 | BY40: 52 | BZ40: FALSE | CA40: None | CB40: 28 | CC40: 1.07 | CD40: a | CE40: 2 | CF40: 7 | CG40: 44574 | CH40: 112 | CI40: 213 | CJ40: 64 | CK40: 89 | CL40: 0 | CM40: 0 | CN40: 0 | CO40: 0 | CP40: 0 | CQ40: 19.8 | CR40: Digne | CS40: 4 | CT40: =_xlfn.CONCAT(AK40," ",BV40) -> Lucas Digne | CU40: =IFERROR(VLOOKUP(CT40,'Player Names Cleaned'!$A$1:$B$997,2,0),CT40) -> Lucas Digne
A41: 0 | B41: 35726 | C41: 10 | D41: 448 | E41: TRUE | F41: TRUE | G41: None | H41: None | I41: 8 | J41: 0.25 | K41: 199798 | L41: None | N41: 0 | O41: 0 | P41: 0 | Q41: 0 | R41: 123.9 | S41: 217 | T41: 63 | U41: 0 | V41: None | X41: 0 | Y41: 2 | Z41: 1.4 | AA41: None | AB41: 0 | AC41: 0.61 | AD41: 0.02 | AE41: 1.9 | AF41: 0.06 | AG41: 1.29 | AH41: 43.82 | AI41: 1.34 | AJ41: 0.04 | AK41: Ezri | AL41: 0 | AM41: 163 | AN41: 107 | AO41: 45 | AP41: 1.38 | AQ41: 2 | AR41: FALSE | AS41: 82.4 | AT41: 163 | AU41: 48 | AV41: 38 | AW41: FALSE | AX41: 532.8 | AY41: 112 | AZ41: 39 | BA41: 2936 | BC41: None | BD41: 45 | BE41: 385 | BF41: 87 | BG41: p199798 | BH41: 0 | BI41: 0 | BJ41: None | BK41: 0 | BM41: 199798.jpg | BN41: 3 | BO41: 130 | BP41: 36 | BQ41: 0 | BR41: 241 | BS41: FALSE | BT41: 0 | BU41: 0 | BV41: Konsa Ngoyo | BW41: 24 | BX41: 13 | BY41: 5 | BZ41: FALSE | CA41: None | CB41: 33 | CC41: 1.01 | CD41: a | CE41: 2 | CF41: 7 | CG41: 43657 | CH41: 166 | CI41: 172 | CJ41: 40 | CK41: 103 | CL41: 0 | CM41: 0 | CN41: 0 | CO41: 0 | CP41: 0 | CQ41: 22.9 | CR41: Konsa | CS41: 1 | CT41: =_xlfn.CONCAT(AK41," ",BV41) -> Ezri Konsa Ngoyo | CU41: =IFERROR(VLOOKUP(CT41,'Player Names Cleaned'!$A$1:$B$997,2,0),CT41) -> Ezri Konsa
A42: 2 | B42: 37325 | C42: 0 | D42: 204 | E42: TRUE | F42: TRUE | G42: None | H42: None | I42: 3 | J42: 0.24 | K42: 441302 | L42: None | N42: 0 | O42: 0 | P42: 0 | Q42: 0 | R42: 293.4 | S42: 125 | T42: 25 | U42: 0 | V42: None | X42: 0 | Y42: 2 | Z42: 1.4 | AA42: None | AB42: 0 | AC42: 2.43 | AD42: 0.19 | AE42: 3.3 | AF42: 0.26 | AG42: 0.87 | AH42: 17.31 | AI42: 1.38 | AJ42: 0.07 | AK42: Ian | AL42: 0 | AM42: 206 | AN42: 135 | AO42: 16 | AP42: 1.28 | AQ42: 1 | AR42: FALSE | AS42: 74.3 | AT42: 187 | AU42: 56 | AV42: 39 | AW42: FALSE | AX42: 252 | AY42: 223 | AZ42: 81 | BA42: 1125 | BC42: None | BD42: 45 | BE42: 428 | BF42: 115 | BG42: p441302 | BH42: 0 | BI42: 0 | BJ42: None | BK42: 0 | BM42: 441302.jpg | BN42: 2 | BO42: 242 | BP42: 85 | BQ42: 0 | BR42: 152 | BS42: FALSE | BT42: 0 | BU42: 0 | BV42: Maatsen | BW42: 1 | BX42: 186 | BY42: 60 | BZ42: FALSE | CA42: None | CB42: 10 | CC42: 0.8 | CD42: a | CE42: 2 | CF42: 7 | CG42: 45471 | CH42: 197 | CI42: 153 | CJ42: 28 | CK42: 57 | CL42: 0 | CM42: 0 | CN42: 0 | CO42: 0 | CP42: 0 | CQ42: 12.7 | CR42: Maatsen | CS42: 2 | CT42: =_xlfn.CONCAT(AK42," ",BV42) -> Ian Maatsen | CU42: =IFERROR(VLOOKUP(CT42,'Player Names Cleaned'!$A$1:$B$997,2,0),CT42) -> Ian Maatsen
A43: 1 | B43: 34041 | C43: 5 | D43: 207 | E43: TRUE | F43: TRUE | G43: None | H43: None | I43: 4 | J43: 0.32 | K43: 149484 | L43: None | N43: 0 | O43: 0 | P43: 0 | Q43: 0 | R43: 49.2 | S43: 279 | T43: 102 | U43: 0 | V43: None | X43: 0 | Y43: 2 | Z43: 1.4 | AA43: None | AB43: 0 | AC43: 0.23 | AD43: 0.02 | AE43: 1.11 | AF43: 0.09 | AG43: 0.88 | AH43: 13.2 | AI43: 1.06 | AJ43: 0.07 | AK43: Tyrone | AL43: 0 | AM43: 150 | AN43: 98 | AO43: 11 | AP43: 0.88 | AQ43: 0 | AR43: FALSE | AS43: 34.6 | AT43: 272 | AU43: 95 | AV43: 40 | AW43: FALSE | AX43: 220.4 | AY43: 233 | AZ43: 84 | BA43: 1119 | BC43: None | BD43: 45 | BE43: 372 | BF43: 78 | BG43: p149484 | BH43: 0 | BI43: 0 | BJ43: None | BK43: 0 | BM43: 149484.jpg | BN43: 3.4 | BO43: 95 | BP43: 17 | BQ43: 0 | BR43: 241 | BS43: FALSE | BT43: 0 | BU43: 0 | BV43: Mings | BW43: 0.5 | BX43: 268 | BY43: 95 | BZ43: FALSE | CA43: None | CB43: 12 | CC43: 0.97 | CD43: a | CE43: 2 | CF43: 7 | CG43: 43654 | CH43: 74 | CI43: 242 | CJ43: 81 | CK43: 47 | CL43: 0 | CM43: 0 | CN43: 0 | CO43: 0 | CP43: 0 | CQ43: 10.4 | CR43: Mings | CS43: 1 | CT43: =_xlfn.CONCAT(AK43," ",BV43) -> Tyrone Mings | CU43: =IFERROR(VLOOKUP(CT43,'Player Names Cleaned'!$A$1:$B$997,2,0),CT43) -> Tyrone Mings
A44: 0 | B44: 35446 | C44: 3 | D44: 254 | E44: TRUE | F44: TRUE | G44: None | H44: None | I44: 5 | J44: 0.22 | K44: 244954 | L44: None | N44: 0 | O44: 0 | P44: 0 | Q44: 0 | R44: 84.5 | S44: 247 | T44: 85 | U44: 0 | V44: None | X44: 0 | Y44: 2 | Z44: 1.4 | AA44: None | AB44: 0 | AC44: 0.43 | AD44: 0.02 | AE44: 0.94 | AF44: 0.04 | AG44: 0.51 | AH44: 29.69 | AI44: 1.32 | AJ44: 0.02 | AK44: Pau | AL44: 0 | AM44: 196 | AN44: 132 | AO44: 33 | AP44: 1.47 | AQ44: 0 | AR44: FALSE | AS44: 54 | AT44: 232 | AU44: 69 | AV44: 41 | AW44: FALSE | AX44: 350.6 | AY44: 181 | AZ44: 64 | BA44: 2019 | BC44: None | BD44: 45 | BE44: 418 | BF44: 112 | BG44: p244954 | BH44: 0 | BI44: 0 | BJ44: None | BK44: 0 | BM44: 244954.jpg | BN44: 2.3 | BO44: 205 | BP44: 71 | BQ44: 0 | BR44: 200 | BS44: FALSE | BT44: 0 | BU44: 0 | BV44: Torres | BW44: 0.4 | BX44: 288 | BY44: 102 | BZ44: FALSE | CA44: None | CB44: 23 | CC44: 1.03 | CD44: a | CE44: 2 | CF44: 7 | CG44: 45119 | CH44: 102 | CI44: 218 | CJ44: 68 | CK44: 55 | CL44: 0 | CM44: 0 | CN44: 0 | CO44: 0 | CP44: 0 | CQ44: 12.2 | CR44: Pau | CS44: 2 | CT44: =_xlfn.CONCAT(AK44," ",BV44) -> Pau Torres | CU44: =IFERROR(VLOOKUP(CT44,'Player Names Cleaned'!$A$1:$B$997,2,0),CT44) -> Pau Torres
A45: 0 | B45: 37659 | C45: 0 | D45: 26 | E45: TRUE | F45: TRUE | G45: None | H45: None | I45: 0 | J45: 0 | K45: 606798 | L45: None | N45: 0 | O45: 0 | P45: 0 | Q45: 0 | R45: 68.4 | S45: 262 | T45: 91 | U45: 0 | V45: None | X45: 0 | Y45: 2 | Z45: 0.5 | AA45: None | AB45: 0 | AC45: 0.49 | AD45: 0.14 | AE45: 0.53 | AF45: 0.15 | AG45: 0.04 | AH45: 6.49 | AI45: 1.85 | AJ45: 0.01 | AK45: AndrÃ©s | AL45: 0 | AM45: 118 | AN45: 74 | AO45: 5 | AP45: 1.42 | AQ45: 0 | AR45: FALSE | AS45: 12 | AT45: 323 | AU45: 119 | AV45: 42 | AW45: FALSE | AX45: 45.6 | AY45: 333 | AZ45: 124 | BA45: 316 | BC45: None | BD45: 40 | BE45: 662 | BF45: 216 | BG45: p606798 | BH45: 0 | BI45: 0 | BJ45: None | BK45: 0 | BM45: 606798.jpg | BN45: 1.1 | BO45: 332 | BP45: 117 | BQ45: 0 | BR45: 200 | BS45: FALSE | BT45: 0 | BU45: 0 | BV45: GarcÃ­a | BW45: 1 | BX45: 192 | BY45: 62 | BZ45: FALSE | CA45: None | CB45: 5 | CC45: 1.42 | CD45: a | CE45: 2 | CF45: 7 | CG45: 45678 | CH45: 7 | CI45: 326 | CJ45: 124 | CK45: 8 | CL45: 0 | CM45: 0 | CN45: 0 | CO45: 0 | CP45: 0 | CQ45: 2 | CR45: A.GarcÃ­a | CS45: 0 | CT45: =_xlfn.CONCAT(AK45," ",BV45) -> AndrÃ©s GarcÃ­a | CU45: =IFERROR(VLOOKUP(CT45,'Player Names Cleaned'!$A$1:$B$997,2,0),CT45) -> AndrÃ©s GarcÃ­a
A46: 1 | B46: 34128 | C46: 1 | D46: 126 | E46: TRUE | F46: TRUE | G46: None | H46: None | I46: 3 | J46: 0.28 | K46: 106468 | L46: None | N46: 0 | O46: 0 | P46: 0 | Q46: 0 | R46: 134.5 | S46: 211 | T46: 60 | U46: 0 | V46: None | X46: 0 | Y46: 2 | Z46: 0.5 | AA46: None | AB46: 0 | AC46: 1.1 | AD46: 0.1 | AE46: 1.27 | AF46: 0.12 | AG46: 0.17 | AH46: 13.94 | AI46: 1.32 | AJ46: 0.02 | AK46: Ãlex | AL46: 0 | AM46: 13 | AN46: 3 | AO46: 16 | AP46: 1.51 | AQ46: 0 | AR46: FALSE | AS46: 36.4 | AT46: 266 | AU46: 91 | AV46: 43 | AW46: FALSE | AX46: 200.8 | AY46: 250 | AZ46: 92 | BA46: 952 | BC46: None | BD46: 40 | BE46: 557 | BF46: 145 | BG46: p106468 | BH46: 0 | BI46: 0 | BJ46: None | BK46: 0 | BM46: 106468.jpg | BN46: 2.3 | BO46: 203 | BP46: 69 | BQ46: 0 | BR46: 200 | BS46: FALSE | BT46: 0 | BU46: 0 | BV46: Moreno Lopera | BW46: 11.7 | BX46: 36 | BY46: 13 | BZ46: FALSE | CA46: None | CB46: 11 | CC46: 1.04 | CD46: a | CE46: 2 | CF46: 7 | CG46: 44937 | CH46: 29 | CI46: 290 | CJ46: 104 | CK46: 34 | CL46: 0 | CM46: 0 | CN46: 0 | CO46: 0 | CP46: 0 | CQ46: 8.5 | CR46: Alex Moreno | CS46: 2 | CT46: =_xlfn.CONCAT(AK46," ",BV46) -> Ãlex Moreno Lopera | CU46: =IFERROR(VLOOKUP(CT46,'Player Names Cleaned'!$A$1:$B$997,2,0),CT46) -> Ãlex Moreno Lopera
A47: 0 | B47: 37991 | C47: 0 | D47: 22 | E47: TRUE | F47: TRUE | G47: None | H47: None | I47: 0 | J47: 0 | K47: 515597 | L47: None | N47: 0 | O47: 0 | P47: 0 | Q47: 0 | R47: 33.3 | S47: 303 | T47: 115 | U47: 0 | V47: None | X47: 0 | Y47: 2 | Z47: 0.5 | AA47: None | AB47: 0 | AC47: 0.13 | AD47: 0.02 | AE47: 0.17 | AF47: 0.03 | AG47: 0.04 | AH47: 9.28 | AI47: 1.77 | AJ47: 0.01 | AK47: Lamare | AL47: 0 | AM47: 84 | AN47: 46 | AO47: 11 | AP47: 2.09 | AQ47: 0 | AR47: FALSE | AS47: 13.3 | AT47: 319 | AU47: 116 | AV47: 44 | AW47: FALSE | AX47: 84.8 | AY47: 311 | AZ47: 114 | BA47: 473 | BC47: None | BD47: 40 | BE47: 628 | BF47: 188 | BG47: p515597 | BH47: 0 | BI47: 0 | BJ47: None | BK47: 0 | BM47: 515597.jpg | BN47: 0.8 | BO47: 383 | BP47: 135 | BQ47: 0 | BR47: 152 | BS47: FALSE | BT47: 0 | BU47: 0 | BV47: Bogarde | BW47: 0.3 | BX47: 339 | BY47: 126 | BZ47: FALSE | CA47: None | CB47: 5 | CC47: 0.95 | CD47: a | CE47: 2 | CF47: 7 | CG47: 44203 | CH47: 15 | CI47: 310 | CJ47: 115 | CK47: 6 | CL47: 0 | CM47: 0 | CN47: 0 | CO47: 0 | CP47: 0 | CQ47: 1.5 | CR47: Bogarde | CS47: 2 | CT47: =_xlfn.CONCAT(AK47," ",BV47) -> Lamare Bogarde | CU47: =IFERROR(VLOOKUP(CT47,'Player Names Cleaned'!$A$1:$B$997,2,0),CT47) -> Lamare Bogarde
A48: 0 | B48: None | C48: 0 | D48: 0 | E48: TRUE | F48: TRUE | G48: None | H48: None | I48: 0 | J48: 0 | K48: 514315 | L48: None | N48: 0 | O48: 0 | P48: 0 | Q48: 0 | R48: 0 | S48: 446 | T48: 173 | U48: 0 | V48: None | X48: 0 | Y48: 2 | Z48: 0.5 | AA48: None | AB48: 0 | AC48: 0 | AD48: 0 | AE48: 0 | AF48: 0 | AG48: 0 | AH48: 0 | AI48: 0 | AJ48: 0 | AK48: Lino | AL48: 0 | AM48: 82 | AN48: 44 | AO48: 0 | AP48: 0 | AQ48: 0 | AR48: FALSE | AS48: 0 | AT48: 456 | AU48: 175 | AV48: 45 | AW48: FALSE | AX48: 0 | AY48: 456 | AZ48: 175 | BA48: 0 | BC48: None | BD48: 40 | BE48: 626 | BF48: 186 | BG48: p514315 | BH48: 0 | BI48: 0 | BJ48: None | BK48: 0 | BM48: 514315.jpg | BN48: 0 | BO48: 460 | BP48: 176 | BQ48: 0 | BR48: None | BS48: FALSE | BT48: 0 | BU48: 0 | BV48: da Cruz Sousa | BW48: 0.3 | BX48: 324 | BY48: 119 | BZ48: FALSE | CA48: None | CB48: 0 | CC48: 0 | CD48: a | CE48: 2 | CF48: 7 | CG48: None | CH48: 0 | CI48: 419 | CJ48: 168 | CK48: 0 | CL48: 0 | CM48: 0 | CN48: 0 | CO48: 0 | CP48: 0 | CQ48: 0 | CR48: Sousa | CS48: 0 | CT48: =_xlfn.CONCAT(AK48," ",BV48) -> Lino da Cruz Sousa | CU48: =IFERROR(VLOOKUP(CT48,'Player Names Cleaned'!$A$1:$B$997,2,0),CT48) -> Lino da Cruz Sousa
A49: 0 | B49: 38827 | C49: 0 | D49: 0 | E49: TRUE | F49: TRUE | G49: None | H49: None | I49: 0 | J49: 0 | K49: 587178 | L49: None | N49: 0 | O49: 0 | P49: 0 | Q49: 0 | R49: 0 | S49: 468 | T49: 190 | U49: 0 | V49: None | X49: 0 | Y49: 2 | Z49: 0.5 | AA49: None | AB49: 0 | AC49: 0 | AD49: 0 | AE49: 0 | AF49: 0 | AG49: 0 | AH49: 0 | AI49: 0 | AJ49: 0 | AK49: Yasin | AL49: 0 | AM49: 111 | AN49: 68 | AO49: 0 | AP49: 0 | AQ49: 0 | AR49: FALSE | AS49: 0 | AT49: 477 | AU49: 191 | AV49: 46 | AW49: FALSE | AX49: 0 | AY49: 477 | AZ49: 191 | BA49: 0 | BC49: None | BD49: 40 | BE49: 655 | BF49: 210 | BG49: p587178 | BH49: 0 | BI49: 0 | BJ49: None | BK49: 0 | BM49: 587178.jpg | BN49: 0 | BO49: 480 | BP49: 191 | BQ49: 0 | BR49: 219 | BS49: FALSE | BT49: 0 | BU49: 0 | BV49: Ã–zcan | BW49: 0.3 | BX49: 353 | BY49: 136 | BZ49: FALSE | CA49: None | CB49: 0 | CC49: 0 | CD49: a | CE49: 2 | CF49: 7 | CG49: 45809 | CH49: 0 | CI49: 444 | CJ49: 188 | CK49: 0 | CL49: 0 | CM49: 0 | CN49: 0 | CO49: 0 | CP49: 0 | CQ49: 0 | CR49: Yasin | CS49: 0 | CT49: =_xlfn.CONCAT(AK49," ",BV49) -> Yasin Ã–zcan | CU49: =IFERROR(VLOOKUP(CT49,'Player Names Cleaned'!$A$1:$B$997,2,0),CT49) -> Yasin Ã–zcan
A50: 11 | B50: 37463 | C50: 15 | D50: 534 | E50: TRUE | F50: TRUE | G50: None | H50: None | I50: 10 | J50: 0.29 | K50: 244850 | L50: None | N50: 0 | O50: 0 | P50: 0 | Q50: 0 | R50: 722.7 | S50: 32 | T50: 29 | U50: 0 | V50: None | X50: 0 | Y50: 3 | Z50: 1.8 | AA50: None | AB50: 0 | AC50: 5.24 | AD50: 0.15 | AE50: 11.73 | AF50: 0.34 | AG50: 6.49 | AH50: 43.7 | AI50: 1.26 | AJ50: 0.19 | AK50: Morgan | AL50: 0 | AM50: 632 | AN50: 277 | AO50: 40 | AP50: 1.16 | AQ50: 8 | AR50: FALSE | AS50: 214.3 | AT50: 19 | AU50: 14 | AV50: 47 | AW50: FALSE | AX50: 731.6 | AY50: 45 | AZ50: 13 | BA50: 3115 | BC50: None | BD50: 70 | BE50: 34 | BF50: 22 | BG50: p244850 | BH50: 0 | BI50: 0 | BJ50: None | BK50: 0 | BM50: 244850.jpg | BN50: 4.4 | BO50: 26 | BP50: 15 | BQ50: 0 | BR50: 241 | BS50: FALSE | BT50: 0 | BU50: 0 | BV50: Rogers | BW50: 24.5 | BX50: 12 | BY50: 5 | BZ50: FALSE | CA50: None | CB50: 37 | CC50: 1.07 | CD50: a | CE50: 2 | CF50: 7 | CG50: 45323 | CH50: 689 | CI50: 38 | CJ50: 24 | CK50: 161 | CL50: 0 | CM50: 0 | CN50: 0 | CO50: 0 | CP50: 0 | CQ50: 23 | CR50: Rogers | CS50: 10 | CT50: =_xlfn.CONCAT(AK50," ",BV50) -> Morgan Rogers | CU50: =IFERROR(VLOOKUP(CT50,'Player Names Cleaned'!$A$1:$B$997,2,0),CT50) -> Morgan Rogers
A51: 7 | B51: 35557 | C51: 15 | D51: 686 | E51: TRUE | F51: TRUE | G51: None | H51: None | I51: 7 | J51: 0.21 | K51: 166989 | L51: 3 | N51: 0 | O51: 0 | P51: 0 | Q51: 0 | R51: 963.1 | S51: 8 | T51: 8 | U51: 0 | V51: None | X51: 0 | Y51: 3 | Z51: 1.6 | AA51: None | AB51: 0 | AC51: 5.83 | AD51: 0.17 | AE51: 9.14 | AF51: 0.27 | AG51: 3.31 | AH51: 43.87 | AI51: 1.31 | AJ51: 0.1 | AK51: Youri | AL51: 0 | AM51: 564 | AN51: 229 | AO51: 46 | AP51: 1.37 | AQ51: 3 | AR51: FALSE | AS51: 209.6 | AT51: 23 | AU51: 18 | AV51: 48 | AW51: FALSE | AX51: 799.6 | AY51: 29 | AZ51: 7 | BA51: 3025 | BC51: None | BD51: 60 | BE51: 83 | BF51: 58 | BG51: p166989 | BH51: 0 | BI51: 1 | BJ51: 4 | BK51: 0 | BM51: 166989.jpg | BN51: 3.4 | BO51: 101 | BP51: 48 | BQ51: 0 | BR51: 21 | BS51: FALSE | BT51: 0 | BU51: 0 | BV51: Tielemans | BW51: 1.6 | BX51: 148 | BY51: 49 | BZ51: FALSE | CA51: None | CB51: 35 | CC51: 1.04 | CD51: a | CE51: 2 | CF51: 7 | CG51: 45091 | CH51: 333 | CI51: 93 | CJ51: 64 | CK51: 121 | CL51: 0 | CM51: 0 | CN51: 0 | CO51: 0 | CP51: 0 | CQ51: 20.2 | CR51: Tielemans | CS51: 4 | CT51: =_xlfn.CONCAT(AK51," ",BV51) -> Youri Tielemans | CU51: =IFERROR(VLOOKUP(CT51,'Player Names Cleaned'!$A$1:$B$997,2,0),CT51) -> Youri Tielemans
A52: 2 | B52: 35651 | C52: 2 | D52: 174 | E52: TRUE | F52: TRUE | G52: None | H52: None | I52: 2 | J52: 0.16 | K52: 215711 | L52: 8 | N52: 0 | O52: 0 | P52: 0 | Q52: 0 | R52: 235.8 | S52: 154 | T52: 107 | U52: 0 | V52: 4 | X52: 0 | Y52: 3 | Z52: 1.5 | AA52: None | AB52: 0 | AC52: 2.92 | AD52: 0.23 | AE52: 4.65 | AF52: 0.37 | AG52: 1.73 | AH52: 13.91 | AI52: 1.11 | AJ52: 0.14 | AK52: Leon | AL52: 0 | AM52: 496 | AN52: 187 | AO52: 19 | AP52: 1.51 | AQ52: 1 | AR52: FALSE | AS52: 70.3 | AT52: 194 | AU52: 102 | AV52: 49 | AW52: FALSE | AX52: 146.4 | AY52: 280 | AZ52: 130 | BA52: 1132 | BC52: None | BD52: 55 | BE52: 146 | BF52: 95 | BG52: p215711 | BH52: 0 | BI52: 0 | BJ52: None | BK52: 0 | BM52: 215711.jpg | BN52: 2 | BO52: 251 | BP52: 114 | BQ52: 0 | BR52: 107 | BS52: FALSE | BT52: 0 | BU52: 0 | BV52: Bailey | BW52: 0.5 | BX52: 272 | BY52: 92 | BZ52: FALSE | CA52: None | CB52: 14 | CC52: 1.11 | CD52: a | CE52: 2 | CF52: 7 | CG52: 44412 | CH52: 325 | CI52: 94 | CJ52: 65 | CK52: 47 | CL52: 0 | CM52: 0 | CN52: 0 | CO52: 0 | CP52: 0 | CQ52: 8.5 | CR52: Bailey | CS52: 3 | CT52: =_xlfn.CONCAT(AK52," ",BV52) -> Leon Bailey | CU52: =IFERROR(VLOOKUP(CT52,'Player Names Cleaned'!$A$1:$B$997,2,0),CT52) -> Leon Bailey
A53: 0 | B53: 35424 | C53: 0 | D53: 37 | E53: TRUE | F53: TRUE | G53: None | H53: None | I53: 0 | J53: 0 | K53: 195546 | L53: None | N53: 0 | O53: 0 | P53: 0 | Q53: 0 | R53: 23.2 | S53: 320 | T53: 166 | U53: 0 | V53: None | X53: 0 | Y53: 3 | Z53: 1.5 | AA53: None | AB53: 0 | AC53: 0.03 | AD53: 0.03 | AE53: 0.68 | AF53: 0.69 | AG53: 0.65 | AH53: 2.27 | AI53: 2.3 | AJ53: 0.66 | AK53: Emiliano | AL53: 0 | AM53: 484 | AN53: 180 | AO53: 2 | AP53: 2.02 | AQ53: 0 | AR53: FALSE | AS53: 5.2 | AT53: 355 | AU53: 168 | AV53: 50 | AW53: FALSE | AX53: 16.4 | AY53: 357 | AZ53: 167 | BA53: 89 | BC53: None | BD53: 55 | BE53: 134 | BF53: 88 | BG53: p195546 | BH53: 0 | BI53: 0 | BJ53: None | BK53: 0 | BM53: 195546.jpg | BN53: 0.9 | BO53: 381 | BP53: 181 | BQ53: 0 | BR53: 10 | BS53: FALSE | BT53: 0 | BU53: 0 | BV53: BuendÃ­a Stati | BW53: 0.1 | BX53: 627 | BY53: 269 | BZ53: FALSE | CA53: None | CB53: 0 | CC53: 0 | CD53: a | CE53: 2 | CF53: 7 | CG53: 44357 | CH53: 16 | CI53: 309 | CJ53: 162 | CK53: 11 | CL53: 0 | CM53: 0 | CN53: 0 | CO53: 0 | CP53: 0 | CQ53: 2 | CR53: BuendÃ­a | CS53: 1 | CT53: =_xlfn.CONCAT(AK53," ",BV53) -> Emiliano BuendÃ­a Stati | CU53: =IFERROR(VLOOKUP(CT53,'Player Names Cleaned'!$A$1:$B$997,2,0),CT53) -> Emiliano BuendÃ­a Stati
A54: 0 | B54: 37898 | C54: 0 | D54: 0 | E54: TRUE | F54: TRUE | G54: None | H54: None | I54: 0 | J54: 0 | K54: 469247 | L54: None | N54: 0 | O54: 0 | P54: 0 | Q54: 0 | R54: 0 | S54: 650 | T54: 290 | U54: 0 | V54: None | X54: 0 | Y54: 3 | Z54: 1.5 | AA54: None | AB54: 0 | AC54: 0 | AD54: 0 | AE54: 0 | AF54: 0 | AG54: 0 | AH54: 0 | AI54: 0 | AJ54: 0 | AK54: Samuel | AL54: 0 | AM54: 527 | AN54: 206 | AO54: 0 | AP54: 0 | AQ54: 0 | AR54: FALSE | AS54: 0 | AT54: 650 | AU54: 290 | AV54: 51 | AW54: FALSE | AX54: 0 | AY54: 650 | AZ54: 290 | BA54: 0 | BC54: None | BD54: 55 | BE54: 177 | BF54: 114 | BG54: p469247 | BH54: 0 | BI54: 0 | BJ54: None | BK54: 0 | BM54: 469247.jpg | BN54: 0 | BO54: 650 | BP54: 290 | BQ54: 0 | BR54: 241 | BS54: FALSE | BT54: 0 | BU54: 0 | BV54: Iling-Junior | BW54: 0 | BX54: 644 | BY54: 283 | BZ54: FALSE | CA54: None | CB54: 0 | CC54: 0 | CD54: a | CE54: 2 | CF54: 7 | CG54: 45474 | CH54: 0 | CI54: 647 | CJ54: 287 | CK54: 0 | CL54: 0 | CM54: 0 | CN54: 0 | CO54: 0 | CP54: 0 | CQ54: 0 | CR54: Iling Jr | CS54: 0 | CT54: =_xlfn.CONCAT(AK54," ",BV54) -> Samuel Iling-Junior | CU54: =IFERROR(VLOOKUP(CT54,'Player Names Cleaned'!$A$1:$B$997,2,0),CT54) -> Samuel Iling-Junior
A55: 4 | B55: 37039 | C55: 3 | D55: 265 | E55: TRUE | F55: TRUE | G55: None | H55: None | I55: 5 | J55: 0.28 | K55: 232653 | L55: None | N55: 0 | O55: 0 | P55: 0 | Q55: 0 | R55: 307.9 | S55: 120 | T55: 86 | U55: 0 | V55: None | X55: 0 | Y55: 3 | Z55: 1.5 | AA55: None | AB55: 0 | AC55: 2.18 | AD55: 0.12 | AE55: 3.77 | AF55: 0.21 | AG55: 1.59 | AH55: 23.99 | AI55: 1.34 | AJ55: 0.09 | AK55: Jacob | AL55: 0 | AM55: 504 | AN55: 193 | AO55: 26 | AP55: 1.45 | AQ55: 1 | AR55: FALSE | AS55: 78.7 | AT55: 172 | AU55: 94 | AV55: 52 | AW55: FALSE | AX55: 235.4 | AY55: 228 | AZ55: 109 | BA55: 1616 | BC55: None | BD55: 55 | BE55: 154 | BF55: 101 | BG55: p232653 | BH55: 0 | BI55: 0 | BJ55: None | BK55: 0 | BM55: 232653.jpg | BN55: 2.3 | BO55: 211 | BP55: 93 | BQ55: 1 | BR55: 241 | BS55: FALSE | BT55: 0 | BU55: 0 | BV55: Ramsey | BW55: 0.6 | BX55: 238 | BY55: 78 | BZ55: FALSE | CA55: None | CB55: 19 | CC55: 1.06 | CD55: a | CE55: 2 | CF55: 7 | CG55: 43508 | CH55: 245 | CI55: 120 | CJ55: 81 | CK55: 66 | CL55: 0 | CM55: 0 | CN55: 0 | CO55: 0 | CP55: 0 | CQ55: 12 | CR55: J.Ramsey | CS55: 2 | CT55: =_xlfn.CONCAT(AK55," ",BV55) -> Jacob Ramsey | CU55: =IFERROR(VLOOKUP(CT55,'Player Names Cleaned'!$A$1:$B$997,2,0),CT55) -> Jacob Ramsey
A56: 0 | B56: 36179 | C56: 3 | D56: 112 | E56: TRUE | F56: TRUE | G56: None | H56: None | I56: 0 | J56: 0 | K56: 204646 | L56: None | N56: 0 | O56: 0 | P56: 0 | Q56: 0 | R56: 42.7 | S56: 288 | T56: 155 | U56: 0 | V56: None | X56: 0 | Y56: 3 | Z56: 1.5 | AA56: None | AB56: 0 | AC56: 0.15 | AD56: 0.05 | AE56: 2.3 | AF56: 0.7 | AG56: 2.15 | AH56: 4.77 | AI56: 1.45 | AJ56: 0.65 | AK56: Donyell | AL56: 0 | AM56: 489 | AN56: 184 | AO56: 6 | AP56: 1.82 | AQ56: 3 | AR56: FALSE | AS56: 38.5 | AT56: 262 | AU56: 133 | AV56: 53 | AW56: FALSE | AX56: 138.2 | AY56: 284 | AZ56: 134 | BA56: 296 | BC56: None | BD56: 55 | BE56: 139 | BF56: 92 | BG56: p204646 | BH56: 0 | BI56: 0 | BJ56: None | BK56: 0 | BM56: 204646.jpg | BN56: 2.4 | BO56: 196 | BP56: 84 | BQ56: 0 | BR56: 152 | BS56: FALSE | BT56: 0 | BU56: 0 | BV56: Malen | BW56: 1.3 | BX56: 169 | BY56: 59 | BZ56: FALSE | CA56: None | CB56: 2 | CC56: 0.61 | CD56: a | CE56: 2 | CF56: 7 | CG56: 45671 | CH56: 208 | CI56: 143 | CJ56: 95 | CK56: 34 | CL56: 0 | CM56: 0 | CN56: 0 | CO56: 0 | CP56: 0 | CQ56: 6.2 | CR56: Malen | CS56: 0 | CT56: =_xlfn.CONCAT(AK56," ",BV56) -> Donyell Malen | CU56: =IFERROR(VLOOKUP(CT56,'Player Names Cleaned'!$A$1:$B$997,2,0),CT56) -> Donyell Malen
A57: 4 | B57: 34625 | C57: 1 | D57: 360 | E57: TRUE | F57: TRUE | G57: None | H57: None | I57: 8 | J57: 0.32 | K57: 122806 | L57: 6 | N57: 0 | O57: 0 | P57: 0 | Q57: 0 | R57: 500.6 | S57: 70 | T57: 56 | U57: 0 | V57: 6 | X57: 0 | Y57: 3 | Z57: 1.5 | AA57: None | AB57: 0 | AC57: 2.7 | AD57: 0.11 | AE57: 5.8 | AF57: 0.24 | AG57: 3.1 | AH57: 35.03 | AI57: 1.42 | AJ57: 0.13 | AK57: John | AL57: 0 | AM57: 470 | AN57: 170 | AO57: 34 | AP57: 1.38 | AQ57: 1 | AR57: FALSE | AS57: 103.7 | AT57: 127 | AU57: 77 | AV57: 54 | AW57: FALSE | AX57: 277.2 | AY57: 210 | AZ57: 101 | BA57: 2217 | BC57: None | BD57: 55 | BE57: 120 | BF57: 78 | BG57: p122806 | BH57: 0 | BI57: 0 | BJ57: None | BK57: 0 | BM57: 122806.jpg | BN57: 2.3 | BO57: 209 | BP57: 92 | BQ57: 0 | BR57: 243 | BS57: FALSE | BT57: 0 | BU57: 0 | BV57: McGinn | BW57: 0.6 | BX57: 243 | BY57: 81 | BZ57: FALSE | CA57: None | CB57: 27 | CC57: 1.1 | CD57: a | CE57: 2 | CF57: 7 | CG57: 43320 | CH57: 263 | CI57: 114 | CJ57: 78 | CK57: 78 | CL57: 0 | CM57: 0 | CN57: 0 | CO57: 0 | CP57: 0 | CQ57: 14.2 | CR57: McGinn | CS57: 7 | CT57: =_xlfn.CONCAT(AK57," ",BV57) -> John McGinn | CU57: =IFERROR(VLOOKUP(CT57,'Player Names Cleaned'!$A$1:$B$997,2,0),CT57) -> John McGinn
A58: 1 | B58: 34308 | C58: 5 | D58: 166 | E58: TRUE | F58: TRUE | G58: None | H58: None | I58: 1 | J58: 0.16 | K58: 88894 | L58: None | N58: 0 | O58: 0 | P58: 0 | Q58: 0 | R58: 128.1 | S58: 215 | T58: 132 | U58: 0 | V58: None | X58: 0 | Y58: 3 | Z58: 1 | AA58: None | AB58: 0 | AC58: 0.43 | AD58: 0.07 | AE58: 2.22 | AF58: 0.35 | AG58: 1.79 | AH58: 6.32 | AI58: 1 | AJ58: 0.28 | AK58: Ross | AL58: 0 | AM58: 332 | AN58: 83 | AO58: 10 | AP58: 1.59 | AQ58: 3 | AR58: FALSE | AS58: 54.8 | AT58: 228 | AU58: 122 | AV58: 55 | AW58: FALSE | AX58: 215.4 | AY58: 238 | AZ58: 115 | BA58: 567 | BC58: None | BD58: 50 | BE58: 217 | BF58: 138 | BG58: p88894 | BH58: 0 | BI58: 0 | BJ58: None | BK58: 0 | BM58: 88894.jpg | BN58: 2.2 | BO58: 219 | BP58: 95 | BQ58: 0 | BR58: 241 | BS58: FALSE | BT58: 0 | BU58: 0 | BV58: Barkley | BW58: 0.3 | BX58: 334 | BY58: 109 | BZ58: FALSE | CA58: None | CB58: 3 | CC58: 0.48 | CD58: a | CE58: 2 | CF58: 7 | CG58: 45474 | CH58: 206 | CI58: 146 | CJ58: 97 | CK58: 44 | CL58: 0 | CM58: 0 | CN58: 0 | CO58: 0 | CP58: 0 | CQ58: 8.8 | CR58: Barkley | CS58: 3 | CT58: =_xlfn.CONCAT(AK58," ",BV58) -> Ross Barkley | CU58: =IFERROR(VLOOKUP(CT58,'Player Names Cleaned'!$A$1:$B$997,2,0),CT58) -> Ross Barkley
A59: 0 | B59: None | C59: 0 | D59: 0 | E59: FALSE | F59: TRUE | G59: 0 | H59: None | I59: 0 | J59: 0 | K59: 491287 | L59: None | N59: 0 | O59: 0 | P59: 0 | Q59: 0 | R59: 0 | S59: 622 | T59: 269 | U59: 0 | V59: None | X59: 0 | Y59: 3 | Z59: 0 | AA59: None | AB59: 0 | AC59: 0 | AD59: 0 | AE59: 0 | AF59: 0 | AG59: 0 | AH59: 0 | AI59: 0 | AJ59: 0 | AK59: Enzo | AL59: 0 | AM59: 430 | AN59: 142 | AO59: 0 | AP59: 0 | AQ59: 0 | AR59: FALSE | AS59: 0 | AT59: 623 | AU59: 269 | AV59: 56 | AW59: FALSE | AX59: 0 | AY59: 623 | AZ59: 269 | BA59: 0 | BB59: Season-long loan to Benfica | BC59: 2025-07-22T13:50:13.193555Z | BD59: 50 | BE59: 315 | BF59: 197 | BG59: p491287 | BH59: 0 | BI59: 0 | BJ59: None | BK59: 0 | BM59: 491287.jpg | BN59: 0 | BO59: 623 | BP59: 269 | BQ59: 0 | BR59: None | BS59: FALSE | BT59: 0 | BU59: 0 | BV59: Barrenechea | BW59: 0 | BX59: 660 | BY59: 296 | BZ59: FALSE | CA59: None | CB59: 0 | CC59: 0 | CD59: u | CE59: 2 | CF59: 7 | CG59: None | CH59: 0 | CI59: 615 | CJ59: 266 | CK59: 0 | CL59: 0 | CM59: 0 | CN59: 0 | CO59: 0 | CP59: 0 | CQ59: 0 | CR59: Barrenechea | CS59: 0 | CT59: =_xlfn.CONCAT(AK59," ",BV59) -> Enzo Barrenechea | CU59: =IFERROR(VLOOKUP(CT59,'Player Names Cleaned'!$A$1:$B$997,2,0),CT59) -> Enzo Barrenechea
A60: 0 | B60: 37624 | C60: 0 | D60: 0 | E60: TRUE | F60: TRUE | G60: None | H60: None | I60: 0 | J60: 0 | K60: 461421 | L60: None | N60: 0 | O60: 0 | P60: 0 | Q60: 0 | R60: 0 | S60: 614 | T60: 261 | U60: 0 | V60: None | X60: 0 | Y60: 3 | Z60: 1 | AA60: None | AB60: 0 | AC60: 0 | AD60: 0 | AE60: 0 | AF60: 0 | AG60: 0 | AH60: 0 | AI60: 0 | AJ60: 0 | AK60: Lewis | AL60: 0 | AM60: 413 | AN60: 130 | AO60: 0 | AP60: 0 | AQ60: 0 | AR60: FALSE | AS60: 0 | AT60: 616 | AU60: 262 | AV60: 57 | AW60: FALSE | AX60: 0 | AY60: 616 | AZ60: 262 | BA60: 0 | BC60: None | BD60: 50 | BE60: 298 | BF60: 185 | BG60: p461421 | BH60: 0 | BI60: 0 | BJ60: None | BK60: 0 | BM60: 461421.jpg | BN60: 0 | BO60: 616 | BP60: 262 | BQ60: 0 | BR60: 241 | BS60: FALSE | BT60: 0 | BU60: 0 | BV60: Dobbin | BW60: 0.1 | BX60: 610 | BY60: 255 | BZ60: FALSE | CA60: None | CB60: 0 | CC60: 0 | CD60: a | CE60: 2 | CF60: 7 | CG60: 45466 | CH60: 0 | CI60: 607 | CJ60: 258 | CK60: 0 | CL60: 0 | CM60: 0 | CN60: 0 | CO60: 0 | CP60: 0 | CQ60: 0 | CR60: Dobbin | CS60: 0 | CT60: =_xlfn.CONCAT(AK60," ",BV60) -> Lewis Dobbin | CU60: =IFERROR(VLOOKUP(CT60,'Player Names Cleaned'!$A$1:$B$997,2,0),CT60) -> Lewis Dobbin
A61: 0 | B61: 36487 | C61: 3 | D61: 296 | E61: TRUE | F61: TRUE | G61: None | H61: None | I61: 6 | J61: 0.31 | K61: 226944 | L61: None | N61: 0 | O61: 0 | P61: 0 | Q61: 0 | R61: 191 | S61: 180 | T61: 122 | U61: 0 | V61: None | X61: 0 | Y61: 3 | Z61: 1 | AA61: None | AB61: 0 | AC61: 0.83 | AD61: 0.04 | AE61: 1.65 | AF61: 0.08 | AG61: 0.82 | AH61: 23.03 | AI61: 1.21 | AJ61: 0.04 | AK61: Boubacar | AL61: 0 | AM61: 385 | AN61: 114 | AO61: 22 | AP61: 1.15 | AQ61: 1 | AR61: FALSE | AS61: 60.2 | AT61: 220 | AU61: 117 | AV61: 58 | AW61: FALSE | AX61: 326.6 | AY61: 194 | AZ61: 90 | BA61: 1720 | BC61: None | BD61: 50 | BE61: 270 | BF61: 169 | BG61: p226944 | BH61: 0 | BI61: 0 | BJ61: None | BK61: 0 | BM61: 226944.jpg | BN61: 2.2 | BO61: 222 | BP61: 97 | BQ61: 0 | BR61: 73 | BS61: FALSE | BT61: 0 | BU61: 0 | BV61: Kamara | BW61: 0.2 | BX61: 422 | BY61: 135 | BZ61: FALSE | CA61: None | CB61: 20 | CC61: 1.05 | CD61: a | CE61: 2 | CF61: 7 | CG61: 44723 | CH61: 83 | CI61: 237 | CJ61: 132 | CK61: 57 | CL61: 0 | CM61: 0 | CN61: 0 | CO61: 0 | CP61: 0 | CQ61: 11.4 | CR61: Kamara | CS61: 2 | CT61: =_xlfn.CONCAT(AK61," ",BV61) -> Boubacar Kamara | CU61: =IFERROR(VLOOKUP(CT61,'Player Names Cleaned'!$A$1:$B$997,2,0),CT61) -> Boubacar Kamara
A62: 0 | B62: 37119 | C62: 5 | D62: 324 | E62: TRUE | F62: TRUE | G62: None | H62: None | I62: 6 | J62: 0.33 | K62: 449871 | L62: None | N62: 0 | O62: 0 | P62: 0 | Q62: 0 | R62: 194.8 | S62: 178 | T62: 121 | U62: 0 | V62: None | X62: 0 | Y62: 3 | Z62: 1 | AA62: None | AB62: 0 | AC62: 0.84 | AD62: 0.05 | AE62: 2.96 | AF62: 0.17 | AG62: 2.12 | AH62: 23.66 | AI62: 1.32 | AJ62: 0.12 | AK62: Amadou | AL62: 0 | AM62: 408 | AN62: 128 | AO62: 23 | AP62: 1.28 | AQ62: 3 | AR62: FALSE | AS62: 77 | AT62: 177 | AU62: 97 | AV62: 59 | AW62: FALSE | AX62: 358 | AY62: 174 | AZ62: 80 | BA62: 1613 | BC62: None | BD62: 50 | BE62: 293 | BF62: 183 | BG62: p449871 | BH62: 0 | BI62: 0 | BJ62: None | BK62: 0 | BM62: 449871.jpg | BN62: 2.5 | BO62: 184 | BP62: 78 | BQ62: 0 | BR62: 21 | BS62: FALSE | BT62: 0 | BU62: 0 | BV62: Onana | BW62: 1.8 | BX62: 138 | BY62: 45 | BZ62: FALSE | CA62: None | CB62: 20 | CC62: 1.12 | CD62: a | CE62: 2 | CF62: 7 | CG62: 45495 | CH62: 215 | CI62: 141 | CJ62: 93 | CK62: 65 | CL62: 0 | CM62: 0 | CN62: 0 | CO62: 0 | CP62: 0 | CQ62: 13 | CR62: Onana | CS62: 4 | CT62: =_xlfn.CONCAT(AK62," ",BV62) -> Amadou Onana | CU62: =IFERROR(VLOOKUP(CT62,'Player Names Cleaned'!$A$1:$B$997,2,0),CT62) -> Amadou Onana
